Workbook
Name PCEntradasN1_Nível_1: TbPCEntradasN1[[Nível 1 ]]
Name PCEntradasN2_Nível_1: TbPCEntradasN2[Nível 1]
Name PCEntradasN2_Nível_2: TbPCEntradasN2[Nível 2]
Name PCSaídasN1_Nível_1: TbPCSaídasN1[Nível 1]
Name PCSaídasN2_Nível_1: TbPCSaídasN2[Nível 1]
Name PCSaídasN2_Nível_2: TbPCSaídasN2[Nível 2]
Name SegmentaçãodeDados_Ano_Competência: #N/A
Name SegmentaçãodeDados_Ano_Competência1: #N/A
Name SegmentaçãodeDados_Ano_Competência2: #N/A
Name SegmentaçãodeDados_Ano_Previsto: #N/A
Name SegmentaçãodeDados_Ano_Previsto1: #N/A
Name SegmentaçãodeDados_Mês_Competência: #N/A
Name SegmentaçãodeDados_Mês_Competência1: #N/A
Name SegmentaçãodeDados_Mês_Previsto: #N/A
Name SegmentaçãodeDados_Mês_Previsto1: #N/A

Sheet Início
B1: (NOME DA EMPRESA) | N1: FLUXO DE CAIXA EMPRESARIAL
B3: Empresa
B4: (NOME DA EMPRESA)
B7: Responsável
B16: Desenvolvido por Vinícius Assumpção

Sheet Matriz
B1: (NOME DA EMPRESA) | N1: TÍTULO

Sheet PCEntradasN1
B1: (NOME DA EMPRESA) | N1: Plano de Contas de Entradas - Nível 1
B3: PLANO DE CONTAS DE ENTRADAS NÍVEL 1
B4: Nível 1
B5: Empréstimos de curto prazo
B6: Financiamentos de longo prazo
B7: Receitas Financeiras
B8: Venda de ativos
B9: Vendas de mercadorias

Sheet PCEntradasN2
B1: (NOME DA EMPRESA) | N1: Plano de Contas de Entradas - Nível 2
B3: PLANO DE CONTAS DE ENTRADAS NÍVEL 2
B4: Nível 1 | C4: Nível 2
B5: Empréstimos de curto prazo | C5: Empréstimos capital de giro
B6: Receitas Financeiras | C6: Juros sobre aplicações
B7: Venda de ativos | C7: Mobiliário próprio
B8: Vendas de mercadorias | C8: Eletrodomésticos
B9: Vendas de mercadorias | C9: Informática
B10: Vendas de mercadorias | C10: Livros
B11: Vendas de mercadorias | C11: Móveis
B12: Vendas de mercadorias | C12: Som e imagem
B13: Financiamentos de longo prazo | C13: Geral

Sheet PCSaídasN1
B1: (NOME DA EMPRESA) | N1: Plano de Contas de Saídas - Nível 1
B3: PLANO DE CONTAS DE SAÍDA NÍVEL 1
B4: Nível 1
B5: Compra de mercadorias
B6: Despesas administrativas
B7: Despesas comerciais
B8: Despesas financeiras
B9: Imposto de renda
B10: Impostos sobre as vendas

Sheet PCSaídasN2
B1: (NOME DA EMPRESA) | N1: Plano de Contas de Saídas - Nível 2
B3: PLANO DE CONTAS DE SAÍDAS NÍVEL 2
B4: Nível 1 | C4: Nível 2
B5: Compra de mercadorias | C5: Eletrodomésticos
B6: Compra de mercadorias | C6: Informática
B7: Compra de mercadorias | C7: Livros
B8: Compra de mercadorias | C8: Som e imagem
B9: Compra de mercadorias | C9: Vestuário
B10: Despesas administrativas | C10: Comunicação - internet e telefonia
B11: Despesas administrativas | C11: Energia elétrica
B12: Despesas comerciais | C12: Encargos sobre os salários dos vendedores
B13: Despesas comerciais | C13: Salários dos vendedores
B14: Despesas financeiras | C14: Juros sobre empréstimos
B15: Imposto de renda | C15: IR sobre o lucro presumido
B16: Impostos sobre as vendas | C16: Geral

Sheet RegistroEntradas
B1: (NOME DA EMPRESA) | H1: Registro das Entradas de Caixa
B3: Data do Caixa Realizado | C3: Data da Competência | D3: Data do Caixa Previsto | E3: Conta Nível 1 | F3: Conta Nível 2 | G3: Histórico | H3: Valor | I3: Mês Caixa | J3: Ano Caixa | K3: Mês Competência | L3: Ano Competência | M3: Mês Previsto | N3: Ano Previsto | O3: Conta Vencida | P3: Venda à Vista | Q3: Dias de Atraso
B4: 45551 | C4: 45514 | D4: 45529 | E4: Vendas de mercadorias | F4: Informática | G4: NF7238 | H4: 1133 | I4: =IF(TbRegistroEntradas[[#This Row],[Data do Caixa Realizado]]="",0,MONTH(TbRegistroEntradas[[#This Row],[Data do Caixa Previsto]])) -> 8 | J4: =IF(TbRegistroEntradas[[#This Row],[Data do Caixa Realizado]]="",0,YEAR(TbRegistroEntradas[[#This Row],[Data do Caixa Realizado]])) -> 2024 | K4: =IF(TbRegistroEntradas[[#This Row],[Data da Competência]]="",0,MONTH(TbRegistroEntradas[[#This Row],[Data da Competência]])) -> 8 | L4: =IF(TbRegistroEntradas[[#This Row],[Data da Competência]]="",0,YEAR(TbRegistroEntradas[[#This Row],[Data da Competência]])) -> 2024 | M4: =IF(TbRegistroEntradas[[#This Row],[Data do Caixa Previsto]]="",0,MONTH(TbRegistroEntradas[[#This Row],[Data do Caixa Previsto]])) -> 8 | N4: =IF(TbRegistroEntradas[[#This Row],[Data do Caixa Previsto]]="",0,YEAR(TbRegistroEntradas[[#This Row],[Data do Caixa Previsto]])) -> 2024 | O4: =IF(AND(TbRegistroEntradas[[#This Row],[Data do Caixa Previsto]]<TODAY(),TbRegistroEntradas[[#This Row],[Data do Caixa Realizado]]=""),"Vencida","Não Vencida") -> Não Vencida | P4: =IF(TbRegistroEntradas[[#This Row],[Data da Competência]]=TbRegistroEntradas[[#This Row],[Data do Caixa Previsto]],"Vista","Prazo") -> Prazo | Q4: =IF(TbRegistroEntradas[[#This Row],[Data do Caixa Realizado]]<>"", IF(TbRegistroEntradas[[#This Row],[Data do Caixa Realizado]]>TbRegistroEntradas[[#This Row],[Data do Caixa Previsto]], TbRegistroEntradas[[#This Row],[Data do Caixa Realizado]]-TbRegistroEntradas[[#This Row],[Data do Caixa Previsto]], 0 ), IF(TODAY()>TbRegistroEntradas[[#This Row],[Data do Caixa Previsto]], TODAY()-TbRegistroEntradas[[#This Row],[Data do Caixa Previsto]], 0 ) ) -> 22
B5: 45542 | C5: 45517 | D5: 45542 | E5: Vendas de mercadorias | F5: Móveis | G5: NF9147 | H5: 164 | I5: =IF(TbRegistroEntradas[[#This Row],[Data do Caixa Realizado]]="",0,MONTH(TbRegistroEntradas[[#This Row],[Data do Caixa Previsto]])) -> 9 | J5: =IF(TbRegistroEntradas[[#This Row],[Data do Caixa Realizado]]="",0,YEAR(TbRegistroEntradas[[#This Row],[Data do Caixa Realizado]])) -> 2024 | K5: =IF(TbRegistroEntradas[[#This Row],[Data da Competência]]="",0,MONTH(TbRegistroEntradas[[#This Row],[Data da Competência]])) -> 8 | L5: =IF(TbRegistroEntradas[[#This Row],[Data da Competência]]="",0,YEAR(TbRegistroEntradas[[#This Row],[Data da Competência]])) -> 2024 | M5: =IF(TbRegistroEntradas[[#This Row],[Data do Caixa Previsto]]="",0,MONTH(TbRegistroEntradas[[#This Row],[Data do Caixa Previsto]])) -> 9 | N5: =IF(TbRegistroEntradas[[#This Row],[Data do Caixa Previsto]]="",0,YEAR(TbRegistroEntradas[[#This Row],[Data do Caixa Previsto]])) -> 2024 | O5: =IF(AND(TbRegistroEntradas[[#This Row],[Data do Caixa Previsto]]<TODAY(),TbRegistroEntradas[[#This Row],[Data do Caixa Realizado]]=""),"Vencida","Não Vencida") -> Não Vencida | P5: =IF(TbRegistroEntradas[[#This Row],[Data da Competência]]=TbRegistroEntradas[[#This Row],[Data do Caixa Previsto]],"Vista","Prazo") -> Prazo | Q5: =IF(TbRegistroEntradas[[#This Row],[Data do Caixa Realizado]]<>"", IF(TbRegistroEntradas[[#This Row],[Data do Caixa Realizado]]>TbRegistroEntradas[[#This Row],[Data do Caixa Previsto]], TbRegistroEntradas[[#This Row],[Data do Caixa Realizado]]-TbRegistroEntradas[[#This Row],[Data do Caixa Previsto]], 0 ), IF(TODAY()>TbRegistroEntradas[[#This Row],[Data do Caixa Previsto]], TODAY()-TbRegistroEntradas[[#This Row],[Data do Caixa Previsto]], 0 ) ) -> 0
B6: 45564 | C6: 45521 | D6: 45558 | E6: Vendas de mercadorias | F6: Móveis | G6: NF8005 | H6: 2937 | I6: =IF(TbRegistroEntradas[[#This Row],[Data do Caixa Realizado]]="",0,MONTH(TbRegistroEntradas[[#This Row],[Data do Caixa Previsto]])) -> 9 | J6: =IF(TbRegistroEntradas[[#This Row],[Data do Caixa Realizado]]="",0,YEAR(TbRegistroEntradas[[#This Row],[Data do Caixa Realizado]])) -> 2024 | K6: =IF(TbRegistroEntradas[[#This Row],[Data da Competência]]="",0,MONTH(TbRegistroEntradas[[#This Row],[Data da Competência]])) -> 8 | L6: =IF(TbRegistroEntradas[[#This Row],[Data da Competência]]="",0,YEAR(TbRegistroEntradas[[#This Row],[Data da Competência]])) -> 2024 | M6: =IF(TbRegistroEntradas[[#This Row],[Data do Caixa Previsto]]="",0,MONTH(TbRegistroEntradas[[#This Row],[Data do Caixa Previsto]])) -> 9 | N6: =IF(TbRegistroEntradas[[#This Row],[Data do Caixa Previsto]]="",0,YEAR(TbRegistroEntradas[[#This Row],[Data do Caixa Previsto]])) -> 2024 | O6: =IF(AND(TbRegistroEntradas[[#This Row],[Data do Caixa Previsto]]<TODAY(),TbRegistroEntradas[[#This Row],[Data do Caixa Realizado]]=""),"Vencida","Não Vencida") -> Não Vencida | P6: =IF(TbRegistroEntradas[[#This Row],[Data da Competência]]=TbRegistroEntradas[[#This Row],[Data do Caixa Previsto]],"Vista","Prazo") -> Prazo | Q6: =IF(TbRegistroEntradas[[#This Row],[Data do Caixa Realizado]]<>"", IF(TbRegistroEntradas[[#This Row],[Data do Caixa Realizado]]>TbRegistroEntradas[[#This Row],[Data do Caixa Previsto]], TbRegistroEntradas[[#This Row],[Data do Caixa Realizado]]-TbRegistroEntradas[[#This Row],[Data do Caixa Previsto]], 0 ), IF(TODAY()>TbRegistroEntradas[[#This Row],[Data do Caixa Previsto]], TODAY()-TbRegistroEntradas[[#This Row],[Data do Caixa Previsto]], 0 ) ) -> 6
B7: 45577 | C7: 45526 | D7: 45577 | E7: Vendas de mercadorias | F7: Som e imagem | G7: NF5493 | H7: 807 | I7: =IF(TbRegistroEntradas[[#This Row],[Data do Caixa Realizado]]="",0,MONTH(TbRegistroEntradas[[#This Row],[Data do Caixa Previsto]])) -> 10 | J7: =IF(TbRegistroEntradas[[#This Row],[Data do Caixa Realizado]]="",0,YEAR(TbRegistroEntradas[[#This Row],[Data do Caixa Realizado]])) -> 2024 | K7: =IF(TbRegistroEntradas[[#This Row],[Data da Competência]]="",0,MONTH(TbRegistroEntradas[[#This Row],[Data da Competência]])) -> 8 | L7: =IF(TbRegistroEntradas[[#This Row],[Data da Competência]]="",0,YEAR(TbRegistroEntradas[[#This Row],[Data da Competência]])) -> 2024 | M7: =IF(TbRegistroEntradas[[#This Row],[Data do Caixa Previsto]]="",0,MONTH(TbRegistroEntradas[[#This Row],[Data do Caixa Previsto]])) -> 10 | N7: =IF(TbRegistroEntradas[[#This Row],[Data do Caixa Previsto]]="",0,YEAR(TbRegistroEntradas[[#This Row],[Data do Caixa Previsto]])) -> 2024 | O7: =IF(AND(TbRegistroEntradas[[#This Row],[Data do Caixa Previsto]]<TODAY(),TbRegistroEntradas[[#This Row],[Data do Caixa Realizado]]=""),"Vencida","Não Vencida") -> Não Vencida | P7: =IF(TbRegistroEntradas[[#This Row],[Data da Competência]]=TbRegistroEntradas[[#This Row],[Data do Caixa Previsto]],"Vista","Prazo") -> Prazo | Q7: =IF(TbRegistroEntradas[[#This Row],[Data do Caixa Realizado]]<>"", IF(TbRegistroEntradas[[#This Row],[Data do Caixa Realizado]]>TbRegistroEntradas[[#This Row],[Data do Caixa Previsto]], TbRegistroEntradas[[#This Row],[Data do Caixa Realizado]]-TbRegistroEntradas[[#This Row],[Data do Caixa Previsto]], 0 ), IF(TODAY()>TbRegistroEntradas[[#This Row],[Data do Caixa Previsto]], TODAY()-TbRegistroEntradas[[#This Row],[Data do Caixa Previsto]], 0 ) ) -> 0
B8: 45571 | C8: 45529 | D8: 45571 | E8: Vendas de mercadorias | F8: Informática | G8: NF7946 | H8: 2612 | I8: =IF(TbRegistroEntradas[[#This Row],[Data do Caixa Realizado]]="",0,MONTH(TbRegistroEntradas[[#This Row],[Data do Caixa Previsto]])) -> 10 | J8: =IF(TbRegistroEntradas[[#This Row],[Data do Caixa Realizado]]="",0,YEAR(TbRegistroEntradas[[#This Row],[Data do Caixa Realizado]])) -> 2024 | K8: =IF(TbRegistroEntradas[[#This Row],[Data da Competência]]="",0,MONTH(TbRegistroEntradas[[#This Row],[Data da Competência]])) -> 8 | L8: =IF(TbRegistroEntradas[[#This Row],[Data da Competência]]="",0,YEAR(TbRegistroEntradas[[#This Row],[Data da Competência]])) -> 2024 | M8: =IF(TbRegistroEntradas[[#This Row],[Data do Caixa Previsto]]="",0,MONTH(TbRegistroEntradas[[#This Row],[Data do Caixa Previsto]])) -> 10 | N8: =IF(TbRegistroEntradas[[#This Row],[Data do Caixa Previsto]]="",0,YEAR(TbRegistroEntradas[[#This Row],[Data do Caixa Previsto]])) -> 2024 | O8: =IF(AND(TbRegistroEntradas[[#This Row],[Data do Caixa Previsto]]<TODAY(),TbRegistroEntradas[[#This Row],[Data do Caixa Realizado]]=""),"Vencida","Não Vencida") -> Não Vencida | P8: =IF(TbRegistroEntradas[[#This Row],[Data da Competência]]=TbRegistroEntradas[[#This Row],[Data do Caixa Previsto]],"Vista","Prazo") -> Prazo | Q8: =IF(TbRegistroEntradas[[#This Row],[Data do Caixa Realizado]]<>"", IF(TbRegistroEntradas[[#This Row],[Data do Caixa Realizado]]>TbRegistroEntradas[[#This Row],[Data do Caixa Previsto]], TbRegistroEntradas[[#This Row],[Data do Caixa Realizado]]-TbRegistroEntradas[[#This Row],[Data do Caixa Previsto]], 0 ), IF(TODAY()>TbRegistroEntradas[[#This Row],[Data do Caixa Previsto]], TODAY()-TbRegistroEntradas[[#This Row],[Data do Caixa Previsto]], 0 ) ) -> 0
B9: 45611 | C9: 45531 | D9: 45587 | E9: Vendas de mercadorias | F9: Móveis | G9: NF8598 | H9: 2483 | I9: =IF(TbRegistroEntradas[[#This Row],[Data do Caixa Realizado]]="",0,MONTH(TbRegistroEntradas[[#This Row],[Data do Caixa Previsto]])) -> 10 | J9: =IF(TbRegistroEntradas[[#This Row],[Data do Caixa Realizado]]="",0,YEAR(TbRegistroEntradas[[#This Row],[Data do Caixa Realizado]])) -> 2024 | K9: =IF(TbRegistroEntradas[[#This Row],[Data da Competência]]="",0,MONTH(TbRegistroEntradas[[#This Row],[Data da Competência]])) -> 8 | L9: =IF(TbRegistroEntradas[[#This Row],[Data da Competência]]="",0,YEAR(TbRegistroEntradas[[#This Row],[Data da Competência]])) -> 2024 | M9: =IF(TbRegistroEntradas[[#This Row],[Data do Caixa Previsto]]="",0,MONTH(TbRegistroEntradas[[#This Row],[Data do Caixa Previsto]])) -> 10 | N9: =IF(TbRegistroEntradas[[#This Row],[Data do Caixa Previsto]]="",0,YEAR(TbRegistroEntradas[[#This Row],[Data do Caixa Previsto]])) -> 2024 | O9: =IF(AND(TbRegistroEntradas[[#This Row],[Data do Caixa Previsto]]<TODAY(),TbRegistroEntradas[[#This Row],[Data do Caixa Realizado]]=""),"Vencida","Não Vencida") -> Não Vencida | P9: =IF(TbRegistroEntradas[[#This Row],[Data da Competência]]=TbRegistroEntradas[[#This Row],[Data do Caixa Previsto]],"Vista","Prazo") -> Prazo | Q9: =IF(TbRegistroEntradas[[#This Row],[Data do Caixa Realizado]]<>"", IF(TbRegistroEntradas[[#This Row],[Data do Caixa Realizado]]>TbRegistroEntradas[[#This Row],[Data do Caixa Previsto]], TbRegistroEntradas[[#This Row],[Data do Caixa Realizado]]-TbRegistroEntradas[[#This Row],[Data do Caixa Previsto]], 0 ), IF(TODAY()>TbRegistroEntradas[[#This Row],[Data do Caixa Previsto]], TODAY()-TbRegistroEntradas[[#This Row],[Data do Caixa Previsto]], 0 ) ) -> 24
B10: 45644 | C10: 45536 | D10: 45566 | E10: Vendas de mercadorias | F10: Informática | G10: NF1535 | H10: 4387 | I10: =IF(TbRegistroEntradas[[#This Row],[Data do Caixa Realizado]]="",0,MONTH(TbRegistroEntradas[[#This Row],[Data do Caixa Previsto]])) -> 10 | J10: =IF(TbRegistroEntradas[[#This Row],[Data do Caixa Realizado]]="",0,YEAR(TbRegistroEntradas[[#This Row],[Data do Caixa Realizado]])) -> 2024 | K10: =IF(TbRegistroEntradas[[#This Row],[Data da Competência]]="",0,MONTH(TbRegistroEntradas[[#This Row],[Data da Competência]])) -> 9 | L10: =IF(TbRegistroEntradas[[#This Row],[Data da Competência]]="",0,YEAR(TbRegistroEntradas[[#This Row],[Data da Competência]])) -> 2024 | M10: =IF(TbRegistroEntradas[[#This Row],[Data do Caixa Previsto]]="",0,MONTH(TbRegistroEntradas[[#This Row],[Data do Caixa Previsto]])) -> 10 | N10: =IF(TbRegistroEntradas[[#This Row],[Data do Caixa Previsto]]="",0,YEAR(TbRegistroEntradas[[#This Row],[Data do Caixa Previsto]])) -> 2024 | O10: =IF(AND(TbRegistroEntradas[[#This Row],[Data do Caixa Previsto]]<TODAY(),TbRegistroEntradas[[#This Row],[Data do Caixa Realizado]]=""),"Vencida","Não Vencida") -> Não Vencida | P10: =IF(TbRegistroEntradas[[#This Row],[Data da Competência]]=TbRegistroEntradas[[#This Row],[Data do Caixa Previsto]],"Vista","Prazo") -> Prazo | Q10: =IF(TbRegistroEntradas[[#This Row],[Data do Caixa Realizado]]<>"", IF(TbRegistroEntradas[[#This Row],[Data do Caixa Realizado]]>TbRegistroEntradas[[#This Row],[Data do Caixa Previsto]], TbRegistroEntradas[[#This Row],[Data do Caixa Realizado]]-TbRegistroEntradas[[#This Row],[Data do Caixa Previsto]], 0 ), IF(TODAY()>TbRegistroEntradas[[#This Row],[Data do Caixa Previsto]], TODAY()-TbRegistroEntradas[[#This Row],[Data do Caixa Previsto]], 0 ) ) -> 78
B11: 45561 | C11: 45537 | D11: 45561 | E11: Vendas de mercadorias | F11: Móveis | G11: NF4333 | H11: 4268 | I11: =IF(TbRegistroEntradas[[#This Row],[Data do Caixa Realizado]]="",0,MONTH(TbRegistroEntradas[[#This Row],[Data do Caixa Previsto]])) -> 9 | J11: =IF(TbRegistroEntradas[[#This Row],[Data do Caixa Realizado]]="",0,YEAR(TbRegistroEntradas[[#This Row],[Data do Caixa Realizado]])) -> 2024 | K11: =IF(TbRegistroEntradas[[#This Row],[Data da Competência]]="",0,MONTH(TbRegistroEntradas[[#This Row],[Data da Competência]])) -> 9 | L11: =IF(TbRegistroEntradas[[#This Row],[Data da Competência]]="",0,YEAR(TbRegistroEntradas[[#This Row],[Data da Competência]])) -> 2024 | M11: =IF(TbRegistroEntradas[[#This Row],[Data do Caixa Previsto]]="",0,MONTH(TbRegistroEntradas[[#This Row],[Data do Caixa Previsto]])) -> 9 | N11: =IF(TbRegistroEntradas[[#This Row],[Data do Caixa Previsto]]="",0,YEAR(TbRegistroEntradas[[#This Row],[Data do Caixa Previsto]])) -> 2024 | O11: =IF(AND(TbRegistroEntradas[[#This Row],[Data do Caixa Previsto]]<TODAY(),TbRegistroEntradas[[#This Row],[Data do Caixa Realizado]]=""),"Vencida","Não Vencida") -> Não Vencida | P11: =IF(TbRegistroEntradas[[#This Row],[Data da Competência]]=TbRegistroEntradas[[#This Row],[Data do Caixa Previsto]],"Vista","Prazo") -> Prazo | Q11: =IF(TbRegistroEntradas[[#This Row],[Data do Caixa Realizado]]<>"", IF(TbRegistroEntradas[[#This Row],[Data do Caixa Realizado]]>TbRegistroEntradas[[#This Row],[Data do Caixa Previsto]], TbRegistroEntradas[[#This Row],[Data do Caixa Realizado]]-TbRegistroEntradas[[#This Row],[Data do Caixa Previsto]], 0 ), IF(TODAY()>TbRegistroEntradas[[#This Row],[Data do Caixa Previsto]], TODAY()-TbRegistroEntradas[[#This Row],[Data do Caixa Previsto]], 0 ) ) -> 0
B12: 45572 | C12: 45541 | D12: 45572 | E12: Vendas de mercadorias | F12: Móveis | G12: NF8091 | H12: 3761 | I12: =IF(TbRegistroEntradas[[#This Row],[Data do Caixa Realizado]]="",0,MONTH(TbRegistroEntradas[[#This Row],[Data do Caixa Previsto]])) -> 10 | J12: =IF(TbRegistroEntradas[[#This Row],[Data do Caixa Realizado]]="",0,YEAR(TbRegistroEntradas[[#This Row],[Data do Caixa Realizado]])) -> 2024 | K12: =IF(TbRegistroEntradas[[#This Row],[Data da Competência]]="",0,MONTH(TbRegistroEntradas[[#This Row],[Data da Competência]])) -> 9 | L12: =IF(TbRegistroEntradas[[#This Row],[Data da Competência]]="",0,YEAR(TbRegistroEntradas[[#This Row],[Data da Competência]])) -> 2024 | M12: =IF(TbRegistroEntradas[[#This Row],[Data do Caixa Previsto]]="",0,MONTH(TbRegistroEntradas[[#This Row],[Data do Caixa Previsto]])) -> 10 | N12: =IF(TbRegistroEntradas[[#This Row],[Data do Caixa Previsto]]="",0,YEAR(TbRegistroEntradas[[#This Row],[Data do Caixa Previsto]])) -> 2024 | O12: =IF(AND(TbRegistroEntradas[[#This Row],[Data do Caixa Previsto]]<TODAY(),TbRegistroEntradas[[#This Row],[Data do Caixa Realizado]]=""),"Vencida","Não Vencida") -> Não Vencida | P12: =IF(TbRegistroEntradas[[#This Row],[Data da Competência]]=TbRegistroEntradas[[#This Row],[Data do Caixa Previsto]],"Vista","Prazo") -> Prazo | Q12: =IF(TbRegistroEntradas[[#This Row],[Data do Caixa Realizado]]<>"", IF(TbRegistroEntradas[[#This Row],[Data do Caixa Realizado]]>TbRegistroEntradas[[#This Row],[Data do Caixa Previsto]], TbRegistroEntradas[[#This Row],[Data do Caixa Realizado]]-TbRegistroEntradas[[#This Row],[Data do Caixa Previsto]], 0 ), IF(TODAY()>TbRegistroEntradas[[#This Row],[Data do Caixa Previsto]], TODAY()-TbRegistroEntradas[[#This Row],[Data do Caixa Previsto]], 0 ) ) -> 0
C13: 45545 | D13: 45570 | E13: Vendas de mercadorias | F13: Móveis | G13: NF2421 | H13: 4983 | I13: =IF(TbRegistroEntradas[[#This Row],[Data do Caixa Realizado]]="",0,MONTH(TbRegistroEntradas[[#This Row],[Data do Caixa Previsto]])) -> 0 | J13: =IF(TbRegistroEntradas[[#This Row],[Data do Caixa Realizado]]="",0,YEAR(TbRegistroEntradas[[#This Row],[Data do Caixa Realizado]])) -> 0 | K13: =IF(TbRegistroEntradas[[#This Row],[Data da Competência]]="",0,MONTH(TbRegistroEntradas[[#This Row],[Data da Competência]])) -> 9 | L13: =IF(TbRegistroEntradas[[#This Row],[Data da Competência]]="",0,YEAR(TbRegistroEntradas[[#This Row],[Data da Competência]])) -> 2024 | M13: =IF(TbRegistroEntradas[[#This Row],[Data do Caixa Previsto]]="",0,MONTH(TbRegistroEntradas[[#This Row],[Data do Caixa Previsto]])) -> 10 | N13: =IF(TbRegistroEntradas[[#This Row],[Data do Caixa Previsto]]="",0,YEAR(TbRegistroEntradas[[#This Row],[Data do Caixa Previsto]])) -> 2024 | O13: =IF(AND(TbRegistroEntradas[[#This Row],[Data do Caixa Previsto]]<TODAY(),TbRegistroEntradas[[#This Row],[Data do Caixa Realizado]]=""),"Vencida","Não Vencida") -> Vencida | P13: =IF(TbRegistroEntradas[[#This Row],[Data da Competência]]=TbRegistroEntradas[[#This Row],[Data do Caixa Previsto]],"Vista","Prazo") -> Prazo | Q13: =IF(TbRegistroEntradas[[#This Row],[Data do Caixa Realizado]]<>"", IF(TbRegistroEntradas[[#This Row],[Data do Caixa Realizado]]>TbRegistroEntradas[[#This Row],[Data do Caixa Previsto]], TbRegistroEntradas[[#This Row],[Data do Caixa Realizado]]-TbRegistroEntradas[[#This Row],[Data do Caixa Previsto]], 0 ), IF(TODAY()>TbRegistroEntradas[[#This Row],[Data do Caixa Previsto]], TODAY()-TbRegistroEntradas[[#This Row],[Data do Caixa Previsto]], 0 ) ) -> 639
B14: 45554 | C14: 45547 | D14: 45554 | E14: Vendas de mercadorias | F14: Eletrodomésticos | G14: NF9787 | H14: 2502 | I14: =IF(TbRegistroEntradas[[#This Row],[Data do Caixa Realizado]]="",0,MONTH(TbRegistroEntradas[[#This Row],[Data do Caixa Previsto]])) -> 9 | J14: =IF(TbRegistroEntradas[[#This Row],[Data do Caixa Realizado]]="",0,YEAR(TbRegistroEntradas[[#This Row],[Data do Caixa Realizado]])) -> 2024 | K14: =IF(TbRegistroEntradas[[#This Row],[Data da Competência]]="",0,MONTH(TbRegistroEntradas[[#This Row],[Data da Competência]])) -> 9 | L14: =IF(TbRegistroEntradas[[#This Row],[Data da Competência]]="",0,YEAR(TbRegistroEntradas[[#This Row],[Data da Competência]])) -> 2024 | M14: =IF(TbRegistroEntradas[[#This Row],[Data do Caixa Previsto]]="",0,MONTH(TbRegistroEntradas[[#This Row],[Data do Caixa Previsto]])) -> 9 | N14: =IF(TbRegistroEntradas[[#This Row],[Data do Caixa Previsto]]="",0,YEAR(TbRegistroEntradas[[#This Row],[Data do Caixa Previsto]])) -> 2024 | O14: =IF(AND(TbRegistroEntradas[[#This Row],[Data do Caixa Previsto]]<TODAY(),TbRegistroEntradas[[#This Row],[Data do Caixa Realizado]]=""),"Vencida","Não Vencida") -> Não Vencida | P14: =IF(TbRegistroEntradas[[#This Row],[Data da Competência]]=TbRegistroEntradas[[#This Row],[Data do Caixa Previsto]],"Vista","Prazo") -> Prazo | Q14: =IF(TbRegistroEntradas[[#This Row],[Data do Caixa Realizado]]<>"", IF(TbRegistroEntradas[[#This Row],[Data do Caixa Realizado]]>TbRegistroEntradas[[#This Row],[Data do Caixa Previsto]], TbRegistroEntradas[[#This Row],[Data do Caixa Realizado]]-TbRegistroEntradas[[#This Row],[Data do Caixa Previsto]], 0 ), IF(TODAY()>TbRegistroEntradas[[#This Row],[Data do Caixa Previsto]], TODAY()-TbRegistroEntradas[[#This Row],[Data do Caixa Previsto]], 0 ) ) -> 0
B15: 45561 | C15: 45551 | D15: 45559 | E15: Vendas de mercadorias | F15: Móveis | G15: NF8674 | H15: 2337 | I15: =IF(TbRegistroEntradas[[#This Row],[Data do Caixa Realizado]]="",0,MONTH(TbRegistroEntradas[[#This Row],[Data do Caixa Previsto]])) -> 9 | J15: =IF(TbRegistroEntradas[[#This Row],[Data do Caixa Realizado]]="",0,YEAR(TbRegistroEntradas[[#This Row],[Data do Caixa Realizado]])) -> 2024 | K15: =IF(TbRegistroEntradas[[#This Row],[Data da Competência]]="",0,MONTH(TbRegistroEntradas[[#This Row],[Data da Competência]])) -> 9 | L15: =IF(TbRegistroEntradas[[#This Row],[Data da Competência]]="",0,YEAR(TbRegistroEntradas[[#This Row],[Data da Competência]])) -> 2024 | M15: =IF(TbRegistroEntradas[[#This Row],[Data do Caixa Previsto]]="",0,MONTH(TbRegistroEntradas[[#This Row],[Data do Caixa Previsto]])) -> 9 | N15: =IF(TbRegistroEntradas[[#This Row],[Data do Caixa Previsto]]="",0,YEAR(TbRegistroEntradas[[#This Row],[Data do Caixa Previsto]])) -> 2024 | O15: =IF(AND(TbRegistroEntradas[[#This Row],[Data do Caixa Previsto]]<TODAY(),TbRegistroEntradas[[#This Row],[Data do Caixa Realizado]]=""),"Vencida","Não Vencida") -> Não Vencida | P15: =IF(TbRegistroEntradas[[#This Row],[Data da Competência]]=TbRegistroEntradas[[#This Row],[Data do Caixa Previsto]],"Vista","Prazo") -> Prazo | Q15: =IF(TbRegistroEntradas[[#This Row],[Data do Caixa Realizado]]<>"", IF(TbRegistroEntradas[[#This Row],[Data do Caixa Realizado]]>TbRegistroEntradas[[#This Row],[Data do Caixa Previsto]], TbRegistroEntradas[[#This Row],[Data do Caixa Realizado]]-TbRegistroEntradas[[#This Row],[Data do Caixa Previsto]], 0 ), IF(TODAY()>TbRegistroEntradas[[#This Row],[Data do Caixa Previsto]], TODAY()-TbRegistroEntradas[[#This Row],[Data do Caixa Previsto]], 0 ) ) -> 2
B16: 45567 | C16: 45558 | D16: 45567 | E16: Vendas de mercadorias | F16: Livros | G16: NF5880 | H16: 3125 | I16: =IF(TbRegistroEntradas[[#This Row],[Data do Caixa Realizado]]="",0,MONTH(TbRegistroEntradas[[#This Row],[Data do Caixa Previsto]])) -> 10 | J16: =IF(TbRegistroEntradas[[#This Row],[Data do Caixa Realizado]]="",0,YEAR(TbRegistroEntradas[[#This Row],[Data do Caixa Realizado]])) -> 2024 | K16: =IF(TbRegistroEntradas[[#This Row],[Data da Competência]]="",0,MONTH(TbRegistroEntradas[[#This Row],[Data da Competência]])) -> 9 | L16: =IF(TbRegistroEntradas[[#This Row],[Data da Competência]]="",0,YEAR(TbRegistroEntradas[[#This Row],[Data da Competência]])) -> 2024 | M16: =IF(TbRegistroEntradas[[#This Row],[Data do Caixa Previsto]]="",0,MONTH(TbRegistroEntradas[[#This Row],[Data do Caixa Previsto]])) -> 10 | N16: =IF(TbRegistroEntradas[[#This Row],[Data do Caixa Previsto]]="",0,YEAR(TbRegistroEntradas[[#This Row],[Data do Caixa Previsto]])) -> 2024 | O16: =IF(AND(TbRegistroEntradas[[#This Row],[Data do Caixa Previsto]]<TODAY(),TbRegistroEntradas[[#This Row],[Data do Caixa Realizado]]=""),"Vencida","Não Vencida") -> Não Vencida | P16: =IF(TbRegistroEntradas[[#This Row],[Data da Competência]]=TbRegistroEntradas[[#This Row],[Data do Caixa Previsto]],"Vista","Prazo") -> Prazo | Q16: =IF(TbRegistroEntradas[[#This Row],[Data do Caixa Realizado]]<>"", IF(TbRegistroEntradas[[#This Row],[Data do Caixa Realizado]]>TbRegistroEntradas[[#This Row],[Data do Caixa Previsto]], TbRegistroEntradas[[#This Row],[Data do Caixa Realizado]]-TbRegistroEntradas[[#This Row],[Data do Caixa Previsto]], 0 ), IF(TODAY()>TbRegistroEntradas[[#This Row],[Data do Caixa Previsto]], TODAY()-TbRegistroEntradas[[#This Row],[Data do Caixa Previsto]], 0 ) ) -> 0
B17: 45613 | C17: 45561 | D17: 45613 | E17: Vendas de mercadorias | F17: Móveis | G17: NF2763 | H17: 1201 | I17: =IF(TbRegistroEntradas[[#This Row],[Data do Caixa Realizado]]="",0,MONTH(TbRegistroEntradas[[#This Row],[Data do Caixa Previsto]])) -> 11 | J17: =IF(TbRegistroEntradas[[#This Row],[Data do Caixa Realizado]]="",0,YEAR(TbRegistroEntradas[[#This Row],[Data do Caixa Realizado]])) -> 2024 | K17: =IF(TbRegistroEntradas[[#This Row],[Data da Competência]]="",0,MONTH(TbRegistroEntradas[[#This Row],[Data da Competência]])) -> 9 | L17: =IF(TbRegistroEntradas[[#This Row],[Data da Competência]]="",0,YEAR(TbRegistroEntradas[[#This Row],[Data da Competência]])) -> 2024 | M17: =IF(TbRegistroEntradas[[#This Row],[Data do Caixa Previsto]]="",0,MONTH(TbRegistroEntradas[[#This Row],[Data do Caixa Previsto]])) -> 11 | N17: =IF(TbRegistroEntradas[[#This Row],[Data do Caixa Previsto]]="",0,YEAR(TbRegistroEntradas[[#This Row],[Data do Caixa Previsto]])) -> 2024 | O17: =IF(AND(TbRegistroEntradas[[#This Row],[Data do Caixa Previsto]]<TODAY(),TbRegistroEntradas[[#This Row],[Data do Caixa Realizado]]=""),"Vencida","Não Vencida") -> Não Vencida | P17: =IF(TbRegistroEntradas[[#This Row],[Data da Competência]]=TbRegistroEntradas[[#This Row],[Data do Caixa Previsto]],"Vista","Prazo") -> Prazo | Q17: =IF(TbRegistroEntradas[[#This Row],[Data do Caixa Realizado]]<>"", IF(TbRegistroEntradas[[#This Row],[Data do Caixa Realizado]]>TbRegistroEntradas[[#This Row],[Data do Caixa Previsto]], TbRegistroEntradas[[#This Row],[Data do Caixa Realizado]]-TbRegistroEntradas[[#This Row],[Data do Caixa Previsto]], 0 ), IF(TODAY()>TbRegistroEntradas[[#This Row],[Data do Caixa Previsto]], TODAY()-TbRegistroEntradas[[#This Row],[Data do Caixa Previsto]], 0 ) ) -> 0
B18: 45590 | C18: 45562 | D18: 45575 | E18: Vendas de mercadorias | F18: Informática | G18: NF3303 | H18: 4380 | I18: =IF(TbRegistroEntradas[[#This Row],[Data do Caixa Realizado]]="",0,MONTH(TbRegistroEntradas[[#This Row],[Data do Caixa Previsto]])) -> 10 | J18: =IF(TbRegistroEntradas[[#This Row],[Data do Caixa Realizado]]="",0,YEAR(TbRegistroEntradas[[#This Row],[Data do Caixa Realizado]])) -> 2024 | K18: =IF(TbRegistroEntradas[[#This Row],[Data da Competência]]="",0,MONTH(TbRegistroEntradas[[#This Row],[Data da Competência]])) -> 9 | L18: =IF(TbRegistroEntradas[[#This Row],[Data da Competência]]="",0,YEAR(TbRegistroEntradas[[#This Row],[Data da Competência]])) -> 2024 | M18: =IF(TbRegistroEntradas[[#This Row],[Data do Caixa Previsto]]="",0,MONTH(TbRegistroEntradas[[#This Row],[Data do Caixa Previsto]])) -> 10 | N18: =IF(TbRegistroEntradas[[#This Row],[Data do Caixa Previsto]]="",0,YEAR(TbRegistroEntradas[[#This Row],[Data do Caixa Previsto]])) -> 2024 | O18: =IF(AND(TbRegistroEntradas[[#This Row],[Data do Caixa Previsto]]<TODAY(),TbRegistroEntradas[[#This Row],[Data do Caixa Realizado]]=""),"Vencida","Não Vencida") -> Não Vencida | P18: =IF(TbRegistroEntradas[[#This Row],[Data da Competência]]=TbRegistroEntradas[[#This Row],[Data do Caixa Previsto]],"Vista","Prazo") -> Prazo | Q18: =IF(TbRegistroEntradas[[#This Row],[Data do Caixa Realizado]]<>"", IF(TbRegistroEntradas[[#This Row],[Data do Caixa Realizado]]>TbRegistroEntradas[[#This Row],[Data do Caixa Previsto]], TbRegistroEntradas[[#This Row],[Data do Caixa Realizado]]-TbRegistroEntradas[[#This Row],[Data do Caixa Previsto]], 0 ), IF(TODAY()>TbRegistroEntradas[[#This Row],[Data do Caixa Previsto]], TODAY()-TbRegistroEntradas[[#This Row],[Data do Caixa Previsto]], 0 ) ) -> 15
B19: 45576 | C19: 45565 | D19: 45576 | E19: Vendas de mercadorias | F19: Livros | G19: NF3966 | H19: 919 | I19: =IF(TbRegistroEntradas[[#This Row],[Data do Caixa Realizado]]="",0,MONTH(TbRegistroEntradas[[#This Row],[Data do Caixa Previsto]])) -> 10 | J19: =IF(TbRegistroEntradas[[#This Row],[Data do Caixa Realizado]]="",0,YEAR(TbRegistroEntradas[[#This Row],[Data do Caixa Realizado]])) -> 2024 | K19: =IF(TbRegistroEntradas[[#This Row],[Data da Competência]]="",0,MONTH(TbRegistroEntradas[[#This Row],[Data da Competência]])) -> 9 | L19: =IF(TbRegistroEntradas[[#This Row],[Data da Competência]]="",0,YEAR(TbRegistroEntradas[[#This Row],[Data da Competência]])) -> 2024 | M19: =IF(TbRegistroEntradas[[#This Row],[Data do Caixa Previsto]]="",0,MONTH(TbRegistroEntradas[[#This Row],[Data do Caixa Previsto]])) -> 10 | N19: =IF(TbRegistroEntradas[[#This Row],[Data do Caixa Previsto]]="",0,YEAR(TbRegistroEntradas[[#This Row],[Data do Caixa Previsto]])) -> 2024 | O19: =IF(AND(TbRegistroEntradas[[#This Row],[Data do Caixa Previsto]]<TODAY(),TbRegistroEntradas[[#This Row],[Data do Caixa Realizado]]=""),"Vencida","Não Vencida") -> Não Vencida | P19: =IF(TbRegistroEntradas[[#This Row],[Data da Competência]]=TbRegistroEntradas[[#This Row],[Data do Caixa Previsto]],"Vista","Prazo") -> Prazo | Q19: =IF(TbRegistroEntradas[[#This Row],[Data do Caixa Realizado]]<>"", IF(TbRegistroEntradas[[#This Row],[Data do Caixa Realizado]]>TbRegistroEntradas[[#This Row],[Data do Caixa Previsto]], TbRegistroEntradas[[#This Row],[Data do Caixa Realizado]]-TbRegistroEntradas[[#This Row],[Data do Caixa Previsto]], 0 ), IF(TODAY()>TbRegistroEntradas[[#This Row],[Data do Caixa Previsto]], TODAY()-TbRegistroEntradas[[#This Row],[Data do Caixa Previsto]], 0 ) ) -> 0
B20: 45582 | C20: 45569 | D20: 45582 | E20: Vendas de mercadorias | F20: Som e imagem | G20: NF6107 | H20: 4590 | I20: =IF(TbRegistroEntradas[[#This Row],[Data do Caixa Realizado]]="",0,MONTH(TbRegistroEntradas[[#This Row],[Data do Caixa Previsto]])) -> 10 | J20: =IF(TbRegistroEntradas[[#This Row],[Data do Caixa Realizado]]="",0,YEAR(TbRegistroEntradas[[#This Row],[Data do Caixa Realizado]])) -> 2024 | K20: =IF(TbRegistroEntradas[[#This Row],[Data da Competência]]="",0,MONTH(TbRegistroEntradas[[#This Row],[Data da Competência]])) -> 10 | L20: =IF(TbRegistroEntradas[[#This Row],[Data da Competência]]="",0,YEAR(TbRegistroEntradas[[#This Row],[Data da Competência]])) -> 2024 | M20: =IF(TbRegistroEntradas[[#This Row],[Data do Caixa Previsto]]="",0,MONTH(TbRegistroEntradas[[#This Row],[Data do Caixa Previsto]])) -> 10 | N20: =IF(TbRegistroEntradas[[#This Row],[Data do Caixa Previsto]]="",0,YEAR(TbRegistroEntradas[[#This Row],[Data do Caixa Previsto]])) -> 2024 | O20: =IF(AND(TbRegistroEntradas[[#This Row],[Data do Caixa Previsto]]<TODAY(),TbRegistroEntradas[[#This Row],[Data do Caixa Realizado]]=""),"Vencida","Não Vencida") -> Não Vencida | P20: =IF(TbRegistroEntradas[[#This Row],[Data da Competência]]=TbRegistroEntradas[[#This Row],[Data do Caixa Previsto]],"Vista","Prazo") -> Prazo | Q20: =IF(TbRegistroEntradas[[#This Row],[Data do Caixa Realizado]]<>"", IF(TbRegistroEntradas[[#This Row],[Data do Caixa Realizado]]>TbRegistroEntradas[[#This Row],[Data do Caixa Previsto]], TbRegistroEntradas[[#This Row],[Data do Caixa Realizado]]-TbRegistroEntradas[[#This Row],[Data do Caixa Previsto]], 0 ), IF(TODAY()>TbRegistroEntradas[[#This Row],[Data do Caixa Previsto]], TODAY()-TbRegistroEntradas[[#This Row],[Data do Caixa Previsto]], 0 ) ) -> 0
B21: 45609 | C21: 45572 | D21: 45609 | E21: Vendas de mercadorias | F21: Eletrodomésticos | G21: NF4832 | H21: 1958 | I21: =IF(TbRegistroEntradas[[#This Row],[Data do Caixa Realizado]]="",0,MONTH(TbRegistroEntradas[[#This Row],[Data do Caixa Previsto]])) -> 11 | J21: =IF(TbRegistroEntradas[[#This Row],[Data do Caixa Realizado]]="",0,YEAR(TbRegistroEntradas[[#This Row],[Data do Caixa Realizado]])) -> 2024 | K21: =IF(TbRegistroEntradas[[#This Row],[Data da Competência]]="",0,MONTH(TbRegistroEntradas[[#This Row],[Data da Competência]])) -> 10 | L21: =IF(TbRegistroEntradas[[#This Row],[Data da Competência]]="",0,YEAR(TbRegistroEntradas[[#This Row],[Data da Competência]])) -> 2024 | M21: =IF(TbRegistroEntradas[[#This Row],[Data do Caixa Previsto]]="",0,MONTH(TbRegistroEntradas[[#This Row],[Data do Caixa Previsto]])) -> 11 | N21: =IF(TbRegistroEntradas[[#This Row],[Data do Caixa Previsto]]="",0,YEAR(TbRegistroEntradas[[#This Row],[Data do Caixa Previsto]])) -> 2024 | O21: =IF(AND(TbRegistroEntradas[[#This Row],[Data do Caixa Previsto]]<TODAY(),TbRegistroEntradas[[#This Row],[Data do Caixa Realizado]]=""),"Vencida","Não Vencida") -> Não Vencida | P21: =IF(TbRegistroEntradas[[#This Row],[Data da Competência]]=TbRegistroEntradas[[#This Row],[Data do Caixa Previsto]],"Vista","Prazo") -> Prazo | Q21: =IF(TbRegistroEntradas[[#This Row],[Data do Caixa Realizado]]<>"", IF(TbRegistroEntradas[[#This Row],[Data do Caixa Realizado]]>TbRegistroEntradas[[#This Row],[Data do Caixa Previsto]], TbRegistroEntradas[[#This Row],[Data do Caixa Realizado]]-TbRegistroEntradas[[#This Row],[Data do Caixa Previsto]], 0 ), IF(TODAY()>TbRegistroEntradas[[#This Row],[Data do Caixa Previsto]], TODAY()-TbRegistroEntradas[[#This Row],[Data do Caixa Previsto]], 0 ) ) -> 0
C22: 45574 | D22: 45600 | E22: Vendas de mercadorias | F22: Informática | G22: NF5012 | H22: 1171 | I22: =IF(TbRegistroEntradas[[#This Row],[Data do Caixa Realizado]]="",0,MONTH(TbRegistroEntradas[[#This Row],[Data do Caixa Previsto]])) -> 0 | J22: =IF(TbRegistroEntradas[[#This Row],[Data do Caixa Realizado]]="",0,YEAR(TbRegistroEntradas[[#This Row],[Data do Caixa Realizado]])) -> 0 | K22: =IF(TbRegistroEntradas[[#This Row],[Data da Competência]]="",0,MONTH(TbRegistroEntradas[[#This Row],[Data da Competência]])) -> 10 | L22: =IF(TbRegistroEntradas[[#This Row],[Data da Competência]]="",0,YEAR(TbRegistroEntradas[[#This Row],[Data da Competência]])) -> 2024 | M22: =IF(TbRegistroEntradas[[#This Row],[Data do Caixa Previsto]]="",0,MONTH(TbRegistroEntradas[[#This Row],[Data do Caixa Previsto]])) -> 11 | N22: =IF(TbRegistroEntradas[[#This Row],[Data do Caixa Previsto]]="",0,YEAR(TbRegistroEntradas[[#This Row],[Data do Caixa Previsto]])) -> 2024 | O22: =IF(AND(TbRegistroEntradas[[#This Row],[Data do Caixa Previsto]]<TODAY(),TbRegistroEntradas[[#This Row],[Data do Caixa Realizado]]=""),"Vencida","Não Vencida") -> Vencida | P22: =IF(TbRegistroEntradas[[#This Row],[Data da Competência]]=TbRegistroEntradas[[#This Row],[Data do Caixa Previsto]],"Vista","Prazo") -> Prazo | Q22: =IF(TbRegistroEntradas[[#This Row],[Data do Caixa Realizado]]<>"", IF(TbRegistroEntradas[[#This Row],[Data do Caixa Realizado]]>TbRegistroEntradas[[#This Row],[Data do Caixa Previsto]], TbRegistroEntradas[[#This Row],[Data do Caixa Realizado]]-TbRegistroEntradas[[#This Row],[Data do Caixa Previsto]], 0 ), IF(TODAY()>TbRegistroEntradas[[#This Row],[Data do Caixa Previsto]], TODAY()-TbRegistroEntradas[[#This Row],[Data do Caixa Previsto]], 0 ) ) -> 609
B23: 45691 | C23: 45576 | D23: 45617 | E23: Vendas de mercadorias | F23: Móveis | G23: NF7669 | H23: 2587 | I23: =IF(TbRegistroEntradas[[#This Row],[Data do Caixa Realizado]]="",0,MONTH(TbRegistroEntradas[[#This Row],[Data do Caixa Previsto]])) -> 11 | J23: =IF(TbRegistroEntradas[[#This Row],[Data do Caixa Realizado]]="",0,YEAR(TbRegistroEntradas[[#This Row],[Data do Caixa Realizado]])) -> 2025 | K23: =IF(TbRegistroEntradas[[#This Row],[Data da Competência]]="",0,MONTH(TbRegistroEntradas[[#This Row],[Data da Competência]])) -> 10 | L23: =IF(TbRegistroEntradas[[#This Row],[Data da Competência]]="",0,YEAR(TbRegistroEntradas[[#This Row],[Data da Competência]])) -> 2024 | M23: =IF(TbRegistroEntradas[[#This Row],[Data do Caixa Previsto]]="",0,MONTH(TbRegistroEntradas[[#This Row],[Data do Caixa Previsto]])) -> 11 | N23: =IF(TbRegistroEntradas[[#This Row],[Data do Caixa Previsto]]="",0,YEAR(TbRegistroEntradas[[#This Row],[Data do Caixa Previsto]])) -> 2024 | O23: =IF(AND(TbRegistroEntradas[[#This Row],[Data do Caixa Previsto]]<TODAY(),TbRegistroEntradas[[#This Row],[Data do Caixa Realizado]]=""),"Vencida","Não Vencida") -> Não Vencida | P23: =IF(TbRegistroEntradas[[#This Row],[Data da Competência]]=TbRegistroEntradas[[#This Row],[Data do Caixa Previsto]],"Vista","Prazo") -> Prazo | Q23: =IF(TbRegistroEntradas[[#This Row],[Data do Caixa Realizado]]<>"", IF(TbRegistroEntradas[[#This Row],[Data do Caixa Realizado]]>TbRegistroEntradas[[#This Row],[Data do Caixa Previsto]], TbRegistroEntradas[[#This Row],[Data do Caixa Realizado]]-TbRegistroEntradas[[#This Row],[Data do Caixa Previsto]], 0 ), IF(TODAY()>TbRegistroEntradas[[#This Row],[Data do Caixa Previsto]], TODAY()-TbRegistroEntradas[[#This Row],[Data do Caixa Previsto]], 0 ) ) -> 74
B24: 45602 | C24: 45580 | D24: 45602 | E24: Vendas de mercadorias | F24: Móveis | G24: NF7663 | H24: 3425 | I24: =IF(TbRegistroEntradas[[#This Row],[Data do Caixa Realizado]]="",0,MONTH(TbRegistroEntradas[[#This Row],[Data do Caixa Previsto]])) -> 11 | J24: =IF(TbRegistroEntradas[[#This Row],[Data do Caixa Realizado]]="",0,YEAR(TbRegistroEntradas[[#This Row],[Data do Caixa Realizado]])) -> 2024 | K24: =IF(TbRegistroEntradas[[#This Row],[Data da Competência]]="",0,MONTH(TbRegistroEntradas[[#This Row],[Data da Competência]])) -> 10 | L24: =IF(TbRegistroEntradas[[#This Row],[Data da Competência]]="",0,YEAR(TbRegistroEntradas[[#This Row],[Data da Competência]])) -> 2024 | M24: =IF(TbRegistroEntradas[[#This Row],[Data do Caixa Previsto]]="",0,MONTH(TbRegistroEntradas[[#This Row],[Data do Caixa Previsto]])) -> 11 | N24: =IF(TbRegistroEntradas[[#This Row],[Data do Caixa Previsto]]="",0,YEAR(TbRegistroEntradas[[#This Row],[Data do Caixa Previsto]])) -> 2024 | O24: =IF(AND(TbRegistroEntradas[[#This Row],[Data do Caixa Previsto]]<TODAY(),TbRegistroEntradas[[#This Row],[Data do Caixa Realizado]]=""),"Vencida","Não Vencida") -> Não Vencida | P24: =IF(TbRegistroEntradas[[#This Row],[Data da Competência]]=TbRegistroEntradas[[#This Row],[Data do Caixa Previsto]],"Vista","Prazo") -> Prazo | Q24: =IF(TbRegistroEntradas[[#This Row],[Data do Caixa Realizado]]<>"", IF(TbRegistroEntradas[[#This Row],[Data do Caixa Realizado]]>TbRegistroEntradas[[#This Row],[Data do Caixa Previsto]], TbRegistroEntradas[[#This Row],[Data do Caixa Realizado]]-TbRegistroEntradas[[#This Row],[Data do Caixa Previsto]], 0 ), IF(TODAY()>TbRegistroEntradas[[#This Row],[Data do Caixa Previsto]], TODAY()-TbRegistroEntradas[[#This Row],[Data do Caixa Previsto]], 0 ) ) -> 0
B25: 45614 | C25: 45583 | D25: 45614 | E25: Vendas de mercadorias | F25: Som e imagem | G25: NF4063 | H25: 4454 | I25: =IF(TbRegistroEntradas[[#This Row],[Data do Caixa Realizado]]="",0,MONTH(TbRegistroEntradas[[#This Row],[Data do Caixa Previsto]])) -> 11 | J25: =IF(TbRegistroEntradas[[#This Row],[Data do Caixa Realizado]]="",0,YEAR(TbRegistroEntradas[[#This Row],[Data do Caixa Realizado]])) -> 2024 | K25: =IF(TbRegistroEntradas[[#This Row],[Data da Competência]]="",0,MONTH(TbRegistroEntradas[[#This Row],[Data da Competência]])) -> 10 | L25: =IF(TbRegistroEntradas[[#This Row],[Data da Competência]]="",0,YEAR(TbRegistroEntradas[[#This Row],[Data da Competência]])) -> 2024 | M25: =IF(TbRegistroEntradas[[#This Row],[Data do Caixa Previsto]]="",0,MONTH(TbRegistroEntradas[[#This Row],[Data do Caixa Previsto]])) -> 11 | N25: =IF(TbRegistroEntradas[[#This Row],[Data do Caixa Previsto]]="",0,YEAR(TbRegistroEntradas[[#This Row],[Data do Caixa Previsto]])) -> 2024 | O25: =IF(AND(TbRegistroEntradas[[#This Row],[Data do Caixa Previsto]]<TODAY(),TbRegistroEntradas[[#This Row],[Data do Caixa Realizado]]=""),"Vencida","Não Vencida") -> Não Vencida | P25: =IF(TbRegistroEntradas[[#This Row],[Data da Competência]]=TbRegistroEntradas[[#This Row],[Data do Caixa Previsto]],"Vista","Prazo") -> Prazo | Q25: =IF(TbRegistroEntradas[[#This Row],[Data do Caixa Realizado]]<>"", IF(TbRegistroEntradas[[#This Row],[Data do Caixa Realizado]]>TbRegistroEntradas[[#This Row],[Data do Caixa Previsto]], TbRegistroEntradas[[#This Row],[Data do Caixa Realizado]]-TbRegistroEntradas[[#This Row],[Data do Caixa Previsto]], 0 ), IF(TODAY()>TbRegistroEntradas[[#This Row],[Data do Caixa Previsto]], TODAY()-TbRegistroEntradas[[#This Row],[Data do Caixa Previsto]], 0 ) ) -> 0
B26: 45594 | C26: 45587 | D26: 45594 | E26: Vendas de mercadorias | F26: Informática | G26: NF4290 | H26: 2134 | I26: =IF(TbRegistroEntradas[[#This Row],[Data do Caixa Realizado]]="",0,MONTH(TbRegistroEntradas[[#This Row],[Data do Caixa Previsto]])) -> 10 | J26: =IF(TbRegistroEntradas[[#This Row],[Data do Caixa Realizado]]="",0,YEAR(TbRegistroEntradas[[#This Row],[Data do Caixa Realizado]])) -> 2024 | K26: =IF(TbRegistroEntradas[[#This Row],[Data da Competência]]="",0,MONTH(TbRegistroEntradas[[#This Row],[Data da Competência]])) -> 10 | L26: =IF(TbRegistroEntradas[[#This Row],[Data da Competência]]="",0,YEAR(TbRegistroEntradas[[#This Row],[Data da Competência]])) -> 2024 | M26: =IF(TbRegistroEntradas[[#This Row],[Data do Caixa Previsto]]="",0,MONTH(TbRegistroEntradas[[#This Row],[Data do Caixa Previsto]])) -> 10 | N26: =IF(TbRegistroEntradas[[#This Row],[Data do Caixa Previsto]]="",0,YEAR(TbRegistroEntradas[[#This Row],[Data do Caixa Previsto]])) -> 2024 | O26: =IF(AND(TbRegistroEntradas[[#This Row],[Data do Caixa Previsto]]<TODAY(),TbRegistroEntradas[[#This Row],[Data do Caixa Realizado]]=""),"Vencida","Não Vencida") -> Não Vencida | P26: =IF(TbRegistroEntradas[[#This Row],[Data da Competência]]=TbRegistroEntradas[[#This Row],[Data do Caixa Previsto]],"Vista","Prazo") -> Prazo | Q26: =IF(TbRegistroEntradas[[#This Row],[Data do Caixa Realizado]]<>"", IF(TbRegistroEntradas[[#This Row],[Data do Caixa Realizado]]>TbRegistroEntradas[[#This Row],[Data do Caixa Previsto]], TbRegistroEntradas[[#This Row],[Data do Caixa Realizado]]-TbRegistroEntradas[[#This Row],[Data do Caixa Previsto]], 0 ), IF(TODAY()>TbRegistroEntradas[[#This Row],[Data do Caixa Previsto]], TODAY()-TbRegistroEntradas[[#This Row],[Data do Caixa Previsto]], 0 ) ) -> 0
B27: 45643 | C27: 45589 | D27: 45615 | E27: Vendas de mercadorias | F27: Eletrodomésticos | G27: NF7319 | H27: 257 | I27: =IF(TbRegistroEntradas[[#This Row],[Data do Caixa Realizado]]="",0,MONTH(TbRegistroEntradas[[#This Row],[Data do Caixa Previsto]])) -> 11 | J27: =IF(TbRegistroEntradas[[#This Row],[Data do Caixa Realizado]]="",0,YEAR(TbRegistroEntradas[[#This Row],[Data do Caixa Realizado]])) -> 2024 | K27: =IF(TbRegistroEntradas[[#This Row],[Data da Competência]]="",0,MONTH(TbRegistroEntradas[[#This Row],[Data da Competência]])) -> 10 | L27: =IF(TbRegistroEntradas[[#This Row],[Data da Competência]]="",0,YEAR(TbRegistroEntradas[[#This Row],[Data da Competência]])) -> 2024 | M27: =IF(TbRegistroEntradas[[#This Row],[Data do Caixa Previsto]]="",0,MONTH(TbRegistroEntradas[[#This Row],[Data do Caixa Previsto]])) -> 11 | N27: =IF(TbRegistroEntradas[[#This Row],[Data do Caixa Previsto]]="",0,YEAR(TbRegistroEntradas[[#This Row],[Data do Caixa Previsto]])) -> 2024 | O27: =IF(AND(TbRegistroEntradas[[#This Row],[Data do Caixa Previsto]]<TODAY(),TbRegistroEntradas[[#This Row],[Data do Caixa Realizado]]=""),"Vencida","Não Vencida") -> Não Vencida | P27: =IF(TbRegistroEntradas[[#This Row],[Data da Competência]]=TbRegistroEntradas[[#This Row],[Data do Caixa Previsto]],"Vista","Prazo") -> Prazo | Q27: =IF(TbRegistroEntradas[[#This Row],[Data do Caixa Realizado]]<>"", IF(TbRegistroEntradas[[#This Row],[Data do Caixa Realizado]]>TbRegistroEntradas[[#This Row],[Data do Caixa Previsto]], TbRegistroEntradas[[#This Row],[Data do Caixa Realizado]]-TbRegistroEntradas[[#This Row],[Data do Caixa Previsto]], 0 ), IF(TODAY()>TbRegistroEntradas[[#This Row],[Data do Caixa Previsto]], TODAY()-TbRegistroEntradas[[#This Row],[Data do Caixa Previsto]], 0 ) ) -> 28
B28: 45625 | C28: 45589 | D28: 45625 | E28: Vendas de mercadorias | F28: Livros | G28: NF7020 | H28: 2019 | I28: =IF(TbRegistroEntradas[[#This Row],[Data do Caixa Realizado]]="",0,MONTH(TbRegistroEntradas[[#This Row],[Data do Caixa Previsto]])) -> 11 | J28: =IF(TbRegistroEntradas[[#This Row],[Data do Caixa Realizado]]="",0,YEAR(TbRegistroEntradas[[#This Row],[Data do Caixa Realizado]])) -> 2024 | K28: =IF(TbRegistroEntradas[[#This Row],[Data da Competência]]="",0,MONTH(TbRegistroEntradas[[#This Row],[Data da Competência]])) -> 10 | L28: =IF(TbRegistroEntradas[[#This Row],[Data da Competência]]="",0,YEAR(TbRegistroEntradas[[#This Row],[Data da Competência]])) -> 2024 | M28: =IF(TbRegistroEntradas[[#This Row],[Data do Caixa Previsto]]="",0,MONTH(TbRegistroEntradas[[#This Row],[Data do Caixa Previsto]])) -> 11 | N28: =IF(TbRegistroEntradas[[#This Row],[Data do Caixa Previsto]]="",0,YEAR(TbRegistroEntradas[[#This Row],[Data do Caixa Previsto]])) -> 2024 | O28: =IF(AND(TbRegistroEntradas[[#This Row],[Data do Caixa Previsto]]<TODAY(),TbRegistroEntradas[[#This Row],[Data do Caixa Realizado]]=""),"Vencida","Não Vencida") -> Não Vencida | P28: =IF(TbRegistroEntradas[[#This Row],[Data da Competência]]=TbRegistroEntradas[[#This Row],[Data do Caixa Previsto]],"Vista","Prazo") -> Prazo | Q28: =IF(TbRegistroEntradas[[#This Row],[Data do Caixa Realizado]]<>"", IF(TbRegistroEntradas[[#This Row],[Data do Caixa Realizado]]>TbRegistroEntradas[[#This Row],[Data do Caixa Previsto]], TbRegistroEntradas[[#This Row],[Data do Caixa Realizado]]-TbRegistroEntradas[[#This Row],[Data do Caixa Previsto]], 0 ), IF(TODAY()>TbRegistroEntradas[[#This Row],[Data do Caixa Previsto]], TODAY()-TbRegistroEntradas[[#This Row],[Data do Caixa Previsto]], 0 ) ) -> 0
B29: 45648 | C29: 45591 | D29: 45648 | E29: Vendas de mercadorias | F29: Móveis | G29: NF7221 | H29: 3696 | I29: =IF(TbRegistroEntradas[[#This Row],[Data do Caixa Realizado]]="",0,MONTH(TbRegistroEntradas[[#This Row],[Data do Caixa Previsto]])) -> 12 | J29: =IF(TbRegistroEntradas[[#This Row],[Data do Caixa Realizado]]="",0,YEAR(TbRegistroEntradas[[#This Row],[Data do Caixa Realizado]])) -> 2024 | K29: =IF(TbRegistroEntradas[[#This Row],[Data da Competência]]="",0,MONTH(TbRegistroEntradas[[#This Row],[Data da Competência]])) -> 10 | L29: =IF(TbRegistroEntradas[[#This Row],[Data da Competência]]="",0,YEAR(TbRegistroEntradas[[#This Row],[Data da Competência]])) -> 2024 | M29: =IF(TbRegistroEntradas[[#This Row],[Data do Caixa Previsto]]="",0,MONTH(TbRegistroEntradas[[#This Row],[Data do Caixa Previsto]])) -> 12 | N29: =IF(TbRegistroEntradas[[#This Row],[Data do Caixa Previsto]]="",0,YEAR(TbRegistroEntradas[[#This Row],[Data do Caixa Previsto]])) -> 2024 | O29: =IF(AND(TbRegistroEntradas[[#This Row],[Data do Caixa Previsto]]<TODAY(),TbRegistroEntradas[[#This Row],[Data do Caixa Realizado]]=""),"Vencida","Não Vencida") -> Não Vencida | P29: =IF(TbRegistroEntradas[[#This Row],[Data da Competência]]=TbRegistroEntradas[[#This Row],[Data do Caixa Previsto]],"Vista","Prazo") -> Prazo | Q29: =IF(TbRegistroEntradas[[#This Row],[Data do Caixa Realizado]]<>"", IF(TbRegistroEntradas[[#This Row],[Data do Caixa Realizado]]>TbRegistroEntradas[[#This Row],[Data do Caixa Previsto]], TbRegistroEntradas[[#This Row],[Data do Caixa Realizado]]-TbRegistroEntradas[[#This Row],[Data do Caixa Previsto]], 0 ), IF(TODAY()>TbRegistroEntradas[[#This Row],[Data do Caixa Previsto]], TODAY()-TbRegistroEntradas[[#This Row],[Data do Caixa Previsto]], 0 ) ) -> 0
B30: 45609 | C30: 45595 | D30: 45609 | E30: Vendas de mercadorias | F30: Livros | G30: NF5004 | H30: 4446 | I30: =IF(TbRegistroEntradas[[#This Row],[Data do Caixa Realizado]]="",0,MONTH(TbRegistroEntradas[[#This Row],[Data do Caixa Previsto]])) -> 11 | J30: =IF(TbRegistroEntradas[[#This Row],[Data do Caixa Realizado]]="",0,YEAR(TbRegistroEntradas[[#This Row],[Data do Caixa Realizado]])) -> 2024 | K30: =IF(TbRegistroEntradas[[#This Row],[Data da Competência]]="",0,MONTH(TbRegistroEntradas[[#This Row],[Data da Competência]])) -> 10 | L30: =IF(TbRegistroEntradas[[#This Row],[Data da Competência]]="",0,YEAR(TbRegistroEntradas[[#This Row],[Data da Competência]])) -> 2024 | M30: =IF(TbRegistroEntradas[[#This Row],[Data do Caixa Previsto]]="",0,MONTH(TbRegistroEntradas[[#This Row],[Data do Caixa Previsto]])) -> 11 | N30: =IF(TbRegistroEntradas[[#This Row],[Data do Caixa Previsto]]="",0,YEAR(TbRegistroEntradas[[#This Row],[Data do Caixa Previsto]])) -> 2024 | O30: =IF(AND(TbRegistroEntradas[[#This Row],[Data do Caixa Previsto]]<TODAY(),TbRegistroEntradas[[#This Row],[Data do Caixa Realizado]]=""),"Vencida","Não Vencida") -> Não Vencida | P30: =IF(TbRegistroEntradas[[#This Row],[Data da Competência]]=TbRegistroEntradas[[#This Row],[Data do Caixa Previsto]],"Vista","Prazo") -> Prazo | Q30: =IF(TbRegistroEntradas[[#This Row],[Data do Caixa Realizado]]<>"", IF(TbRegistroEntradas[[#This Row],[Data do Caixa Realizado]]>TbRegistroEntradas[[#This Row],[Data do Caixa Previsto]], TbRegistroEntradas[[#This Row],[Data do Caixa Realizado]]-TbRegistroEntradas[[#This Row],[Data do Caixa Previsto]], 0 ), IF(TODAY()>TbRegistroEntradas[[#This Row],[Data do Caixa Previsto]], TODAY()-TbRegistroEntradas[[#This Row],[Data do Caixa Previsto]], 0 ) ) -> 0
B31: 45614 | C31: 45597 | D31: 45614 | E31: Vendas de mercadorias | F31: Livros | G31: NF8690 | H31: 1445 | I31: =IF(TbRegistroEntradas[[#This Row],[Data do Caixa Realizado]]="",0,MONTH(TbRegistroEntradas[[#This Row],[Data do Caixa Previsto]])) -> 11 | J31: =IF(TbRegistroEntradas[[#This Row],[Data do Caixa Realizado]]="",0,YEAR(TbRegistroEntradas[[#This Row],[Data do Caixa Realizado]])) -> 2024 | K31: =IF(TbRegistroEntradas[[#This Row],[Data da Competência]]="",0,MONTH(TbRegistroEntradas[[#This Row],[Data da Competência]])) -> 11 | L31: =IF(TbRegistroEntradas[[#This Row],[Data da Competência]]="",0,YEAR(TbRegistroEntradas[[#This Row],[Data da Competência]])) -> 2024 | M31: =IF(TbRegistroEntradas[[#This Row],[Data do Caixa Previsto]]="",0,MONTH(TbRegistroEntradas[[#This Row],[Data do Caixa Previsto]])) -> 11 | N31: =IF(TbRegistroEntradas[[#This Row],[Data do Caixa Previsto]]="",0,YEAR(TbRegistroEntradas[[#This Row],[Data do Caixa Previsto]])) -> 2024 | O31: =IF(AND(TbRegistroEntradas[[#This Row],[Data do Caixa Previsto]]<TODAY(),TbRegistroEntradas[[#This Row],[Data do Caixa Realizado]]=""),"Vencida","Não Vencida") -> Não Vencida | P31: =IF(TbRegistroEntradas[[#This Row],[Data da Competência]]=TbRegistroEntradas[[#This Row],[Data do Caixa Previsto]],"Vista","Prazo") -> Prazo | Q31: =IF(TbRegistroEntradas[[#This Row],[Data do Caixa Realizado]]<>"", IF(TbRegistroEntradas[[#This Row],[Data do Caixa Realizado]]>TbRegistroEntradas[[#This Row],[Data do Caixa Previsto]], TbRegistroEntradas[[#This Row],[Data do Caixa Realizado]]-TbRegistroEntradas[[#This Row],[Data do Caixa Previsto]], 0 ), IF(TODAY()>TbRegistroEntradas[[#This Row],[Data do Caixa Previsto]], TODAY()-TbRegistroEntradas[[#This Row],[Data do Caixa Previsto]], 0 ) ) -> 0
B32: 45639 | C32: 45600 | D32: 45625 | E32: Vendas de mercadorias | F32: Informática | G32: NF3424 | H32: 3559 | I32: =IF(TbRegistroEntradas[[#This Row],[Data do Caixa Realizado]]="",0,MONTH(TbRegistroEntradas[[#This Row],[Data do Caixa Previsto]])) -> 11 | J32: =IF(TbRegistroEntradas[[#This Row],[Data do Caixa Realizado]]="",0,YEAR(TbRegistroEntradas[[#This Row],[Data do Caixa Realizado]])) -> 2024 | K32: =IF(TbRegistroEntradas[[#This Row],[Data da Competência]]="",0,MONTH(TbRegistroEntradas[[#This Row],[Data da Competência]])) -> 11 | L32: =IF(TbRegistroEntradas[[#This Row],[Data da Competência]]="",0,YEAR(TbRegistroEntradas[[#This Row],[Data da Competência]])) -> 2024 | M32: =IF(TbRegistroEntradas[[#This Row],[Data do Caixa Previsto]]="",0,MONTH(TbRegistroEntradas[[#This Row],[Data do Caixa Previsto]])) -> 11 | N32: =IF(TbRegistroEntradas[[#This Row],[Data do Caixa Previsto]]="",0,YEAR(TbRegistroEntradas[[#This Row],[Data do Caixa Previsto]])) -> 2024 | O32: =IF(AND(TbRegistroEntradas[[#This Row],[Data do Caixa Previsto]]<TODAY(),TbRegistroEntradas[[#This Row],[Data do Caixa Realizado]]=""),"Vencida","Não Vencida") -> Não Vencida | P32: =IF(TbRegistroEntradas[[#This Row],[Data da Competência]]=TbRegistroEntradas[[#This Row],[Data do Caixa Previsto]],"Vista","Prazo") -> Prazo | Q32: =IF(TbRegistroEntradas[[#This Row],[Data do Caixa Realizado]]<>"", IF(TbRegistroEntradas[[#This Row],[Data do Caixa Realizado]]>TbRegistroEntradas[[#This Row],[Data do Caixa Previsto]], TbRegistroEntradas[[#This Row],[Data do Caixa Realizado]]-TbRegistroEntradas[[#This Row],[Data do Caixa Previsto]], 0 ), IF(TODAY()>TbRegistroEntradas[[#This Row],[Data do Caixa Previsto]], TODAY()-TbRegistroEntradas[[#This Row],[Data do Caixa Previsto]], 0 ) ) -> 14
B33: 45630 | C33: 45604 | D33: 45610 | E33: Vendas de mercadorias | F33: Móveis | G33: NF5808 | H33: 547 | I33: =IF(TbRegistroEntradas[[#This Row],[Data do Caixa Realizado]]="",0,MONTH(TbRegistroEntradas[[#This Row],[Data do Caixa Previsto]])) -> 11 | J33: =IF(TbRegistroEntradas[[#This Row],[Data do Caixa Realizado]]="",0,YEAR(TbRegistroEntradas[[#This Row],[Data do Caixa Realizado]])) -> 2024 | K33: =IF(TbRegistroEntradas[[#This Row],[Data da Competência]]="",0,MONTH(TbRegistroEntradas[[#This Row],[Data da Competência]])) -> 11 | L33: =IF(TbRegistroEntradas[[#This Row],[Data da Competência]]="",0,YEAR(TbRegistroEntradas[[#This Row],[Data da Competência]])) -> 2024 | M33: =IF(TbRegistroEntradas[[#This Row],[Data do Caixa Previsto]]="",0,MONTH(TbRegistroEntradas[[#This Row],[Data do Caixa Previsto]])) -> 11 | N33: =IF(TbRegistroEntradas[[#This Row],[Data do Caixa Previsto]]="",0,YEAR(TbRegistroEntradas[[#This Row],[Data do Caixa Previsto]])) -> 2024 | O33: =IF(AND(TbRegistroEntradas[[#This Row],[Data do Caixa Previsto]]<TODAY(),TbRegistroEntradas[[#This Row],[Data do Caixa Realizado]]=""),"Vencida","Não Vencida") -> Não Vencida | P33: =IF(TbRegistroEntradas[[#This Row],[Data da Competência]]=TbRegistroEntradas[[#This Row],[Data do Caixa Previsto]],"Vista","Prazo") -> Prazo | Q33: =IF(TbRegistroEntradas[[#This Row],[Data do Caixa Realizado]]<>"", IF(TbRegistroEntradas[[#This Row],[Data do Caixa Realizado]]>TbRegistroEntradas[[#This Row],[Data do Caixa Previsto]], TbRegistroEntradas[[#This Row],[Data do Caixa Realizado]]-TbRegistroEntradas[[#This Row],[Data do Caixa Previsto]], 0 ), IF(TODAY()>TbRegistroEntradas[[#This Row],[Data do Caixa Previsto]], TODAY()-TbRegistroEntradas[[#This Row],[Data do Caixa Previsto]], 0 ) ) -> 20
B34: 45647 | C34: 45608 | D34: 45647 | E34: Vendas de mercadorias | F34: Móveis | G34: NF2852 | H34: 1221 | I34: =IF(TbRegistroEntradas[[#This Row],[Data do Caixa Realizado]]="",0,MONTH(TbRegistroEntradas[[#This Row],[Data do Caixa Previsto]])) -> 12 | J34: =IF(TbRegistroEntradas[[#This Row],[Data do Caixa Realizado]]="",0,YEAR(TbRegistroEntradas[[#This Row],[Data do Caixa Realizado]])) -> 2024 | K34: =IF(TbRegistroEntradas[[#This Row],[Data da Competência]]="",0,MONTH(TbRegistroEntradas[[#This Row],[Data da Competência]])) -> 11 | L34: =IF(TbRegistroEntradas[[#This Row],[Data da Competência]]="",0,YEAR(TbRegistroEntradas[[#This Row],[Data da Competência]])) -> 2024 | M34: =IF(TbRegistroEntradas[[#This Row],[Data do Caixa Previsto]]="",0,MONTH(TbRegistroEntradas[[#This Row],[Data do Caixa Previsto]])) -> 12 | N34: =IF(TbRegistroEntradas[[#This Row],[Data do Caixa Previsto]]="",0,YEAR(TbRegistroEntradas[[#This Row],[Data do Caixa Previsto]])) -> 2024 | O34: =IF(AND(TbRegistroEntradas[[#This Row],[Data do Caixa Previsto]]<TODAY(),TbRegistroEntradas[[#This Row],[Data do Caixa Realizado]]=""),"Vencida","Não Vencida") -> Não Vencida | P34: =IF(TbRegistroEntradas[[#This Row],[Data da Competência]]=TbRegistroEntradas[[#This Row],[Data do Caixa Previsto]],"Vista","Prazo") -> Prazo | Q34: =IF(TbRegistroEntradas[[#This Row],[Data do Caixa Realizado]]<>"", IF(TbRegistroEntradas[[#This Row],[Data do Caixa Realizado]]>TbRegistroEntradas[[#This Row],[Data do Caixa Previsto]], TbRegistroEntradas[[#This Row],[Data do Caixa Realizado]]-TbRegistroEntradas[[#This Row],[Data do Caixa Previsto]], 0 ), IF(TODAY()>TbRegistroEntradas[[#This Row],[Data do Caixa Previsto]], TODAY()-TbRegistroEntradas[[#This Row],[Data do Caixa Previsto]], 0 ) ) -> 0
... B40: 45679 | C40: 45620 | D40: 45679 | E40: Vendas de mercadorias | F40: Informática | G40: NF6190 | H40: 3992 | I40: =IF(TbRegistroEntradas[[#This Row],[Data do Caixa Realizado]]="",0,MONTH(TbRegistroEntradas[[#This Row],[Data do Caixa Previsto]])) -> 1 | J40: =IF(TbRegistroEntradas[[#This Row],[Data do Caixa Realizado]]="",0,YEAR(TbRegistroEntradas[[#This Row],[Data do Caixa Realizado]])) -> 2025 | K40: =IF(TbRegistroEntradas[[#This Row],[Data da Competência]]="",0,MONTH(TbRegistroEntradas[[#This Row],[Data da Competência]])) -> 11 | L40: =IF(TbRegistroEntradas[[#This Row],[Data da Competência]]="",0,YEAR(TbRegistroEntradas[[#This Row],[Data da Competência]])) -> 2024 | M40: =IF(TbRegistroEntradas[[#This Row],[Data do Caixa Previsto]]="",0,MONTH(TbRegistroEntradas[[#This Row],[Data do Caixa Previsto]])) -> 1 | N40: =IF(TbRegistroEntradas[[#This Row],[Data do Caixa Previsto]]="",0,YEAR(TbRegistroEntradas[[#This Row],[Data do Caixa Previsto]])) -> 2025 | O40: =IF(AND(TbRegistroEntradas[[#This Row],[Data do Caixa Previsto]]<TODAY(),TbRegistroEntradas[[#This Row],[Data do Caixa Realizado]]=""),"Vencida","Não Vencida") -> Não Vencida | P40: =IF(TbRegistroEntradas[[#This Row],[Data da Competência]]=TbRegistroEntradas[[#This Row],[Data do Caixa Previsto]],"Vista","Prazo") -> Prazo | Q40: =IF(TbRegistroEntradas[[#This Row],[Data do Caixa Realizado]]<>"", IF(TbRegistroEntradas[[#This Row],[Data do Caixa Realizado]]>TbRegistroEntradas[[#This Row],[Data do Caixa Previsto]], TbRegistroEntradas[[#This Row],[Data do Caixa Realizado]]-TbRegistroEntradas[[#This Row],[Data do Caixa Previsto]], 0 ), IF(TODAY()>TbRegistroEntradas[[#This Row],[Data do Caixa Previsto]], TODAY()-TbRegistroEntradas[[#This Row],[Data do Caixa Previsto]], 0 ) ) -> 0
C41: 45625 | D41: 45683 | E41: Vendas de mercadorias | F41: Eletrodomésticos | G41: NF4129 | H41: 1284 | I41: =IF(TbRegistroEntradas[[#This Row],[Data do Caixa Realizado]]="",0,MONTH(TbRegistroEntradas[[#This Row],[Data do Caixa Previsto]])) -> 0 | J41: =IF(TbRegistroEntradas[[#This Row],[Data do Caixa Realizado]]="",0,YEAR(TbRegistroEntradas[[#This Row],[Data do Caixa Realizado]])) -> 0 | K41: =IF(TbRegistroEntradas[[#This Row],[Data da Competência]]="",0,MONTH(TbRegistroEntradas[[#This Row],[Data da Competência]])) -> 11 | L41: =IF(TbRegistroEntradas[[#This Row],[Data da Competência]]="",0,YEAR(TbRegistroEntradas[[#This Row],[Data da Competência]])) -> 2024 | M41: =IF(TbRegistroEntradas[[#This Row],[Data do Caixa Previsto]]="",0,MONTH(TbRegistroEntradas[[#This Row],[Data do Caixa Previsto]])) -> 1 | N41: =IF(TbRegistroEntradas[[#This Row],[Data do Caixa Previsto]]="",0,YEAR(TbRegistroEntradas[[#This Row],[Data do Caixa Previsto]])) -> 2025 | O41: =IF(AND(TbRegistroEntradas[[#This Row],[Data do Caixa Previsto]]<TODAY(),TbRegistroEntradas[[#This Row],[Data do Caixa Realizado]]=""),"Vencida","Não Vencida") -> Vencida | P41: =IF(TbRegistroEntradas[[#This Row],[Data da Competência]]=TbRegistroEntradas[[#This Row],[Data do Caixa Previsto]],"Vista","Prazo") -> Prazo | Q41: =IF(TbRegistroEntradas[[#This Row],[Data do Caixa Realizado]]<>"", IF(TbRegistroEntradas[[#This Row],[Data do Caixa Realizado]]>TbRegistroEntradas[[#This Row],[Data do Caixa Previsto]], TbRegistroEntradas[[#This Row],[Data do Caixa Realizado]]-TbRegistroEntradas[[#This Row],[Data do Caixa Previsto]], 0 ), IF(TODAY()>TbRegistroEntradas[[#This Row],[Data do Caixa Previsto]], TODAY()-TbRegistroEntradas[[#This Row],[Data do Caixa Previsto]], 0 ) ) -> 526
B42: 45678 | C42: 45630 | D42: 45678 | E42: Vendas de mercadorias | F42: Informática | G42: NF6811 | H42: 4073 | I42: =IF(TbRegistroEntradas[[#This Row],[Data do Caixa Realizado]]="",0,MONTH(TbRegistroEntradas[[#This Row],[Data do Caixa Previsto]])) -> 1 | J42: =IF(TbRegistroEntradas[[#This Row],[Data do Caixa Realizado]]="",0,YEAR(TbRegistroEntradas[[#This Row],[Data do Caixa Realizado]])) -> 2025 | K42: =IF(TbRegistroEntradas[[#This Row],[Data da Competência]]="",0,MONTH(TbRegistroEntradas[[#This Row],[Data da Competência]])) -> 12 | L42: =IF(TbRegistroEntradas[[#This Row],[Data da Competência]]="",0,YEAR(TbRegistroEntradas[[#This Row],[Data da Competência]])) -> 2024 | M42: =IF(TbRegistroEntradas[[#This Row],[Data do Caixa Previsto]]="",0,MONTH(TbRegistroEntradas[[#This Row],[Data do Caixa Previsto]])) -> 1 | N42: =IF(TbRegistroEntradas[[#This Row],[Data do Caixa Previsto]]="",0,YEAR(TbRegistroEntradas[[#This Row],[Data do Caixa Previsto]])) -> 2025 | O42: =IF(AND(TbRegistroEntradas[[#This Row],[Data do Caixa Previsto]]<TODAY(),TbRegistroEntradas[[#This Row],[Data do Caixa Realizado]]=""),"Vencida","Não Vencida") -> Não Vencida | P42: =IF(TbRegistroEntradas[[#This Row],[Data da Competência]]=TbRegistroEntradas[[#This Row],[Data do Caixa Previsto]],"Vista","Prazo") -> Prazo | Q42: =IF(TbRegistroEntradas[[#This Row],[Data do Caixa Realizado]]<>"", IF(TbRegistroEntradas[[#This Row],[Data do Caixa Realizado]]>TbRegistroEntradas[[#This Row],[Data do Caixa Previsto]], TbRegistroEntradas[[#This Row],[Data do Caixa Realizado]]-TbRegistroEntradas[[#This Row],[Data do Caixa Previsto]], 0 ), IF(TODAY()>TbRegistroEntradas[[#This Row],[Data do Caixa Previsto]], TODAY()-TbRegistroEntradas[[#This Row],[Data do Caixa Previsto]], 0 ) ) -> 0
B43: 45641 | C43: 45630 | D43: 45641 | E43: Vendas de mercadorias | F43: Eletrodomésticos | G43: NF1550 | H43: 3008 | I43: =IF(TbRegistroEntradas[[#This Row],[Data do Caixa Realizado]]="",0,MONTH(TbRegistroEntradas[[#This Row],[Data do Caixa Previsto]])) -> 12 | J43: =IF(TbRegistroEntradas[[#This Row],[Data do Caixa Realizado]]="",0,YEAR(TbRegistroEntradas[[#This Row],[Data do Caixa Realizado]])) -> 2024 | K43: =IF(TbRegistroEntradas[[#This Row],[Data da Competência]]="",0,MONTH(TbRegistroEntradas[[#This Row],[Data da Competência]])) -> 12 | L43: =IF(TbRegistroEntradas[[#This Row],[Data da Competência]]="",0,YEAR(TbRegistroEntradas[[#This Row],[Data da Competência]])) -> 2024 | M43: =IF(TbRegistroEntradas[[#This Row],[Data do Caixa Previsto]]="",0,MONTH(TbRegistroEntradas[[#This Row],[Data do Caixa Previsto]])) -> 12 | N43: =IF(TbRegistroEntradas[[#This Row],[Data do Caixa Previsto]]="",0,YEAR(TbRegistroEntradas[[#This Row],[Data do Caixa Previsto]])) -> 2024 | O43: =IF(AND(TbRegistroEntradas[[#This Row],[Data do Caixa Previsto]]<TODAY(),TbRegistroEntradas[[#This Row],[Data do Caixa Realizado]]=""),"Vencida","Não Vencida") -> Não Vencida | P43: =IF(TbRegistroEntradas[[#This Row],[Data da Competência]]=TbRegistroEntradas[[#This Row],[Data do Caixa Previsto]],"Vista","Prazo") -> Prazo | Q43: =IF(TbRegistroEntradas[[#This Row],[Data do Caixa Realizado]]<>"", IF(TbRegistroEntradas[[#This Row],[Data do Caixa Realizado]]>TbRegistroEntradas[[#This Row],[Data do Caixa Previsto]], TbRegistroEntradas[[#This Row],[Data do Caixa Realizado]]-TbRegistroEntradas[[#This Row],[Data do Caixa Previsto]], 0 ), IF(TODAY()>TbRegistroEntradas[[#This Row],[Data do Caixa Previsto]], TODAY()-TbRegistroEntradas[[#This Row],[Data do Caixa Previsto]], 0 ) ) -> 0
B44: 45688 | C44: 45637 | D44: 45688 | E44: Vendas de mercadorias | F44: Eletrodomésticos | G44: NF7213 | H44: 1267 | I44: =IF(TbRegistroEntradas[[#This Row],[Data do Caixa Realizado]]="",0,MONTH(TbRegistroEntradas[[#This Row],[Data do Caixa Previsto]])) -> 1 | J44: =IF(TbRegistroEntradas[[#This Row],[Data do Caixa Realizado]]="",0,YEAR(TbRegistroEntradas[[#This Row],[Data do Caixa Realizado]])) -> 2025 | K44: =IF(TbRegistroEntradas[[#This Row],[Data da Competência]]="",0,MONTH(TbRegistroEntradas[[#This Row],[Data da Competência]])) -> 12 | L44: =IF(TbRegistroEntradas[[#This Row],[Data da Competência]]="",0,YEAR(TbRegistroEntradas[[#This Row],[Data da Competência]])) -> 2024 | M44: =IF(TbRegistroEntradas[[#This Row],[Data do Caixa Previsto]]="",0,MONTH(TbRegistroEntradas[[#This Row],[Data do Caixa Previsto]])) -> 1 | N44: =IF(TbRegistroEntradas[[#This Row],[Data do Caixa Previsto]]="",0,YEAR(TbRegistroEntradas[[#This Row],[Data do Caixa Previsto]])) -> 2025 | O44: =IF(AND(TbRegistroEntradas[[#This Row],[Data do Caixa Previsto]]<TODAY(),TbRegistroEntradas[[#This Row],[Data do Caixa Realizado]]=""),"Vencida","Não Vencida") -> Não Vencida | P44: =IF(TbRegistroEntradas[[#This Row],[Data da Competência]]=TbRegistroEntradas[[#This Row],[Data do Caixa Previsto]],"Vista","Prazo") -> Prazo | Q44: =IF(TbRegistroEntradas[[#This Row],[Data do Caixa Realizado]]<>"", IF(TbRegistroEntradas[[#This Row],[Data do Caixa Realizado]]>TbRegistroEntradas[[#This Row],[Data do Caixa Previsto]], TbRegistroEntradas[[#This Row],[Data do Caixa Realizado]]-TbRegistroEntradas[[#This Row],[Data do Caixa Previsto]], 0 ), IF(TODAY()>TbRegistroEntradas[[#This Row],[Data do Caixa Previsto]], TODAY()-TbRegistroEntradas[[#This Row],[Data do Caixa Previsto]], 0 ) ) -> 0
B45: 45660 | C45: 45639 | D45: 45660 | E45: Vendas de mercadorias | F45: Eletrodomésticos | G45: NF8396 | H45: 284 | I45: =IF(TbRegistroEntradas[[#This Row],[Data do Caixa Realizado]]="",0,MONTH(TbRegistroEntradas[[#This Row],[Data do Caixa Previsto]])) -> 1 | J45: =IF(TbRegistroEntradas[[#This Row],[Data do Caixa Realizado]]="",0,YEAR(TbRegistroEntradas[[#This Row],[Data do Caixa Realizado]])) -> 2025 | K45: =IF(TbRegistroEntradas[[#This Row],[Data da Competência]]="",0,MONTH(TbRegistroEntradas[[#This Row],[Data da Competência]])) -> 12 | L45: =IF(TbRegistroEntradas[[#This Row],[Data da Competência]]="",0,YEAR(TbRegistroEntradas[[#This Row],[Data da Competência]])) -> 2024 | M45: =IF(TbRegistroEntradas[[#This Row],[Data do Caixa Previsto]]="",0,MONTH(TbRegistroEntradas[[#This Row],[Data do Caixa Previsto]])) -> 1 | N45: =IF(TbRegistroEntradas[[#This Row],[Data do Caixa Previsto]]="",0,YEAR(TbRegistroEntradas[[#This Row],[Data do Caixa Previsto]])) -> 2025 | O45: =IF(AND(TbRegistroEntradas[[#This Row],[Data do Caixa Previsto]]<TODAY(),TbRegistroEntradas[[#This Row],[Data do Caixa Realizado]]=""),"Vencida","Não Vencida") -> Não Vencida | P45: =IF(TbRegistroEntradas[[#This Row],[Data da Competência]]=TbRegistroEntradas[[#This Row],[Data do Caixa Previsto]],"Vista","Prazo") -> Prazo | Q45: =IF(TbRegistroEntradas[[#This Row],[Data do Caixa Realizado]]<>"", IF(TbRegistroEntradas[[#This Row],[Data do Caixa Realizado]]>TbRegistroEntradas[[#This Row],[Data do Caixa Previsto]], TbRegistroEntradas[[#This Row],[Data do Caixa Realizado]]-TbRegistroEntradas[[#This Row],[Data do Caixa Previsto]], 0 ), IF(TODAY()>TbRegistroEntradas[[#This Row],[Data do Caixa Previsto]], TODAY()-TbRegistroEntradas[[#This Row],[Data do Caixa Previsto]], 0 ) ) -> 0
B46: 45643 | C46: 45640 | D46: 45643 | E46: Vendas de mercadorias | F46: Móveis | G46: NF2432 | H46: 2046 | I46: =IF(TbRegistroEntradas[[#This Row],[Data do Caixa Realizado]]="",0,MONTH(TbRegistroEntradas[[#This Row],[Data do Caixa Previsto]])) -> 12 | J46: =IF(TbRegistroEntradas[[#This Row],[Data do Caixa Realizado]]="",0,YEAR(TbRegistroEntradas[[#This Row],[Data do Caixa Realizado]])) -> 2024 | K46: =IF(TbRegistroEntradas[[#This Row],[Data da Competência]]="",0,MONTH(TbRegistroEntradas[[#This Row],[Data da Competência]])) -> 12 | L46: =IF(TbRegistroEntradas[[#This Row],[Data da Competência]]="",0,YEAR(TbRegistroEntradas[[#This Row],[Data da Competência]])) -> 2024 | M46: =IF(TbRegistroEntradas[[#This Row],[Data do Caixa Previsto]]="",0,MONTH(TbRegistroEntradas[[#This Row],[Data do Caixa Previsto]])) -> 12 | N46: =IF(TbRegistroEntradas[[#This Row],[Data do Caixa Previsto]]="",0,YEAR(TbRegistroEntradas[[#This Row],[Data do Caixa Previsto]])) -> 2024 | O46: =IF(AND(TbRegistroEntradas[[#This Row],[Data do Caixa Previsto]]<TODAY(),TbRegistroEntradas[[#This Row],[Data do Caixa Realizado]]=""),"Vencida","Não Vencida") -> Não Vencida | P46: =IF(TbRegistroEntradas[[#This Row],[Data da Competência]]=TbRegistroEntradas[[#This Row],[Data do Caixa Previsto]],"Vista","Prazo") -> Prazo | Q46: =IF(TbRegistroEntradas[[#This Row],[Data do Caixa Realizado]]<>"", IF(TbRegistroEntradas[[#This Row],[Data do Caixa Realizado]]>TbRegistroEntradas[[#This Row],[Data do Caixa Previsto]], TbRegistroEntradas[[#This Row],[Data do Caixa Realizado]]-TbRegistroEntradas[[#This Row],[Data do Caixa Previsto]], 0 ), IF(TODAY()>TbRegistroEntradas[[#This Row],[Data do Caixa Previsto]], TODAY()-TbRegistroEntradas[[#This Row],[Data do Caixa Previsto]], 0 ) ) -> 0
B47: 45692 | C47: 45642 | D47: 45679 | E47: Vendas de mercadorias | F47: Informática | G47: NF4722 | H47: 3880 | I47: =IF(TbRegistroEntradas[[#This Row],[Data do Caixa Realizado]]="",0,MONTH(TbRegistroEntradas[[#This Row],[Data do Caixa Previsto]])) -> 1 | J47: =IF(TbRegistroEntradas[[#This Row],[Data do Caixa Realizado]]="",0,YEAR(TbRegistroEntradas[[#This Row],[Data do Caixa Realizado]])) -> 2025 | K47: =IF(TbRegistroEntradas[[#This Row],[Data da Competência]]="",0,MONTH(TbRegistroEntradas[[#This Row],[Data da Competência]])) -> 12 | L47: =IF(TbRegistroEntradas[[#This Row],[Data da Competência]]="",0,YEAR(TbRegistroEntradas[[#This Row],[Data da Competência]])) -> 2024 | M47: =IF(TbRegistroEntradas[[#This Row],[Data do Caixa Previsto]]="",0,MONTH(TbRegistroEntradas[[#This Row],[Data do Caixa Previsto]])) -> 1 | N47: =IF(TbRegistroEntradas[[#This Row],[Data do Caixa Previsto]]="",0,YEAR(TbRegistroEntradas[[#This Row],[Data do Caixa Previsto]])) -> 2025 | O47: =IF(AND(TbRegistroEntradas[[#This Row],[Data do Caixa Previsto]]<TODAY(),TbRegistroEntradas[[#This Row],[Data do Caixa Realizado]]=""),"Vencida","Não Vencida") -> Não Vencida | P47: =IF(TbRegistroEntradas[[#This Row],[Data da Competência]]=TbRegistroEntradas[[#This Row],[Data do Caixa Previsto]],"Vista","Prazo") -> Prazo | Q47: =IF(TbRegistroEntradas[[#This Row],[Data do Caixa Realizado]]<>"", IF(TbRegistroEntradas[[#This Row],[Data do Caixa Realizado]]>TbRegistroEntradas[[#This Row],[Data do Caixa Previsto]], TbRegistroEntradas[[#This Row],[Data do Caixa Realizado]]-TbRegistroEntradas[[#This Row],[Data do Caixa Previsto]], 0 ), IF(TODAY()>TbRegistroEntradas[[#This Row],[Data do Caixa Previsto]], TODAY()-TbRegistroEntradas[[#This Row],[Data do Caixa Previsto]], 0 ) ) -> 13
B48: 45680 | C48: 45643 | D48: 45680 | E48: Vendas de mercadorias | F48: Informática | G48: NF8944 | H48: 3149 | I48: =IF(TbRegistroEntradas[[#This Row],[Data do Caixa Realizado]]="",0,MONTH(TbRegistroEntradas[[#This Row],[Data do Caixa Previsto]])) -> 1 | J48: =IF(TbRegistroEntradas[[#This Row],[Data do Caixa Realizado]]="",0,YEAR(TbRegistroEntradas[[#This Row],[Data do Caixa Realizado]])) -> 2025 | K48: =IF(TbRegistroEntradas[[#This Row],[Data da Competência]]="",0,MONTH(TbRegistroEntradas[[#This Row],[Data da Competência]])) -> 12 | L48: =IF(TbRegistroEntradas[[#This Row],[Data da Competência]]="",0,YEAR(TbRegistroEntradas[[#This Row],[Data da Competência]])) -> 2024 | M48: =IF(TbRegistroEntradas[[#This Row],[Data do Caixa Previsto]]="",0,MONTH(TbRegistroEntradas[[#This Row],[Data do Caixa Previsto]])) -> 1 | N48: =IF(TbRegistroEntradas[[#This Row],[Data do Caixa Previsto]]="",0,YEAR(TbRegistroEntradas[[#This Row],[Data do Caixa Previsto]])) -> 2025 | O48: =IF(AND(TbRegistroEntradas[[#This Row],[Data do Caixa Previsto]]<TODAY(),TbRegistroEntradas[[#This Row],[Data do Caixa Realizado]]=""),"Vencida","Não Vencida") -> Não Vencida | P48: =IF(TbRegistroEntradas[[#This Row],[Data da Competência]]=TbRegistroEntradas[[#This Row],[Data do Caixa Previsto]],"Vista","Prazo") -> Prazo | Q48: =IF(TbRegistroEntradas[[#This Row],[Data do Caixa Realizado]]<>"", IF(TbRegistroEntradas[[#This Row],[Data do Caixa Realizado]]>TbRegistroEntradas[[#This Row],[Data do Caixa Previsto]], TbRegistroEntradas[[#This Row],[Data do Caixa Realizado]]-TbRegistroEntradas[[#This Row],[Data do Caixa Previsto]], 0 ), IF(TODAY()>TbRegistroEntradas[[#This Row],[Data do Caixa Previsto]], TODAY()-TbRegistroEntradas[[#This Row],[Data do Caixa Previsto]], 0 ) ) -> 0
B49: 45682 | C49: 45645 | D49: 45682 | E49: Vendas de mercadorias | F49: Móveis | G49: NF2816 | H49: 668 | I49: =IF(TbRegistroEntradas[[#This Row],[Data do Caixa Realizado]]="",0,MONTH(TbRegistroEntradas[[#This Row],[Data do Caixa Previsto]])) -> 1 | J49: =IF(TbRegistroEntradas[[#This Row],[Data do Caixa Realizado]]="",0,YEAR(TbRegistroEntradas[[#This Row],[Data do Caixa Realizado]])) -> 2025 | K49: =IF(TbRegistroEntradas[[#This Row],[Data da Competência]]="",0,MONTH(TbRegistroEntradas[[#This Row],[Data da Competência]])) -> 12 | L49: =IF(TbRegistroEntradas[[#This Row],[Data da Competência]]="",0,YEAR(TbRegistroEntradas[[#This Row],[Data da Competência]])) -> 2024 | M49: =IF(TbRegistroEntradas[[#This Row],[Data do Caixa Previsto]]="",0,MONTH(TbRegistroEntradas[[#This Row],[Data do Caixa Previsto]])) -> 1 | N49: =IF(TbRegistroEntradas[[#This Row],[Data do Caixa Previsto]]="",0,YEAR(TbRegistroEntradas[[#This Row],[Data do Caixa Previsto]])) -> 2025 | O49: =IF(AND(TbRegistroEntradas[[#This Row],[Data do Caixa Previsto]]<TODAY(),TbRegistroEntradas[[#This Row],[Data do Caixa Realizado]]=""),"Vencida","Não Vencida") -> Não Vencida | P49: =IF(TbRegistroEntradas[[#This Row],[Data da Competência]]=TbRegistroEntradas[[#This Row],[Data do Caixa Previsto]],"Vista","Prazo") -> Prazo | Q49: =IF(TbRegistroEntradas[[#This Row],[Data do Caixa Realizado]]<>"", IF(TbRegistroEntradas[[#This Row],[Data do Caixa Realizado]]>TbRegistroEntradas[[#This Row],[Data do Caixa Previsto]], TbRegistroEntradas[[#This Row],[Data do Caixa Realizado]]-TbRegistroEntradas[[#This Row],[Data do Caixa Previsto]], 0 ), IF(TODAY()>TbRegistroEntradas[[#This Row],[Data do Caixa Previsto]], TODAY()-TbRegistroEntradas[[#This Row],[Data do Caixa Previsto]], 0 ) ) -> 0
B50: 45674 | C50: 45646 | D50: 45674 | E50: Vendas de mercadorias | F50: Som e imagem | G50: NF6358 | H50: 3721 | I50: =IF(TbRegistroEntradas[[#This Row],[Data do Caixa Realizado]]="",0,MONTH(TbRegistroEntradas[[#This Row],[Data do Caixa Previsto]])) -> 1 | J50: =IF(TbRegistroEntradas[[#This Row],[Data do Caixa Realizado]]="",0,YEAR(TbRegistroEntradas[[#This Row],[Data do Caixa Realizado]])) -> 2025 | K50: =IF(TbRegistroEntradas[[#This Row],[Data da Competência]]="",0,MONTH(TbRegistroEntradas[[#This Row],[Data da Competência]])) -> 12 | L50: =IF(TbRegistroEntradas[[#This Row],[Data da Competência]]="",0,YEAR(TbRegistroEntradas[[#This Row],[Data da Competência]])) -> 2024 | M50: =IF(TbRegistroEntradas[[#This Row],[Data do Caixa Previsto]]="",0,MONTH(TbRegistroEntradas[[#This Row],[Data do Caixa Previsto]])) -> 1 | N50: =IF(TbRegistroEntradas[[#This Row],[Data do Caixa Previsto]]="",0,YEAR(TbRegistroEntradas[[#This Row],[Data do Caixa Previsto]])) -> 2025 | O50: =IF(AND(TbRegistroEntradas[[#This Row],[Data do Caixa Previsto]]<TODAY(),TbRegistroEntradas[[#This Row],[Data do Caixa Realizado]]=""),"Vencida","Não Vencida") -> Não Vencida | P50: =IF(TbRegistroEntradas[[#This Row],[Data da Competência]]=TbRegistroEntradas[[#This Row],[Data do Caixa Previsto]],"Vista","Prazo") -> Prazo | Q50: =IF(TbRegistroEntradas[[#This Row],[Data do Caixa Realizado]]<>"", IF(TbRegistroEntradas[[#This Row],[Data do Caixa Realizado]]>TbRegistroEntradas[[#This Row],[Data do Caixa Previsto]], TbRegistroEntradas[[#This Row],[Data do Caixa Realizado]]-TbRegistroEntradas[[#This Row],[Data do Caixa Previsto]], 0 ), IF(TODAY()>TbRegistroEntradas[[#This Row],[Data do Caixa Previsto]], TODAY()-TbRegistroEntradas[[#This Row],[Data do Caixa Previsto]], 0 ) ) -> 0
B51: 45779 | C51: 45648 | D51: 45690 | E51: Vendas de mercadorias | F51: Informática | G51: NF8459 | H51: 3114 | I51: =IF(TbRegistroEntradas[[#This Row],[Data do Caixa Realizado]]="",0,MONTH(TbRegistroEntradas[[#This Row],[Data do Caixa Previsto]])) -> 2 | J51: =IF(TbRegistroEntradas[[#This Row],[Data do Caixa Realizado]]="",0,YEAR(TbRegistroEntradas[[#This Row],[Data do Caixa Realizado]])) -> 2025 | K51: =IF(TbRegistroEntradas[[#This Row],[Data da Competência]]="",0,MONTH(TbRegistroEntradas[[#This Row],[Data da Competência]])) -> 12 | L51: =IF(TbRegistroEntradas[[#This Row],[Data da Competência]]="",0,YEAR(TbRegistroEntradas[[#This Row],[Data da Competência]])) -> 2024 | M51: =IF(TbRegistroEntradas[[#This Row],[Data do Caixa Previsto]]="",0,MONTH(TbRegistroEntradas[[#This Row],[Data do Caixa Previsto]])) -> 2 | N51: =IF(TbRegistroEntradas[[#This Row],[Data do Caixa Previsto]]="",0,YEAR(TbRegistroEntradas[[#This Row],[Data do Caixa Previsto]])) -> 2025 | O51: =IF(AND(TbRegistroEntradas[[#This Row],[Data do Caixa Previsto]]<TODAY(),TbRegistroEntradas[[#This Row],[Data do Caixa Realizado]]=""),"Vencida","Não Vencida") -> Não Vencida | P51: =IF(TbRegistroEntradas[[#This Row],[Data da Competência]]=TbRegistroEntradas[[#This Row],[Data do Caixa Previsto]],"Vista","Prazo") -> Prazo | Q51: =IF(TbRegistroEntradas[[#This Row],[Data do Caixa Realizado]]<>"", IF(TbRegistroEntradas[[#This Row],[Data do Caixa Realizado]]>TbRegistroEntradas[[#This Row],[Data do Caixa Previsto]], TbRegistroEntradas[[#This Row],[Data do Caixa Realizado]]-TbRegistroEntradas[[#This Row],[Data do Caixa Previsto]], 0 ), IF(TODAY()>TbRegistroEntradas[[#This Row],[Data do Caixa Previsto]], TODAY()-TbRegistroEntradas[[#This Row],[Data do Caixa Previsto]], 0 ) ) -> 89
B52: 45728 | C52: 45652 | D52: 45707 | E52: Vendas de mercadorias | F52: Móveis | G52: NF5737 | H52: 1436 | I52: =IF(TbRegistroEntradas[[#This Row],[Data do Caixa Realizado]]="",0,MONTH(TbRegistroEntradas[[#This Row],[Data do Caixa Previsto]])) -> 2 | J52: =IF(TbRegistroEntradas[[#This Row],[Data do Caixa Realizado]]="",0,YEAR(TbRegistroEntradas[[#This Row],[Data do Caixa Realizado]])) -> 2025 | K52: =IF(TbRegistroEntradas[[#This Row],[Data da Competência]]="",0,MONTH(TbRegistroEntradas[[#This Row],[Data da Competência]])) -> 12 | L52: =IF(TbRegistroEntradas[[#This Row],[Data da Competência]]="",0,YEAR(TbRegistroEntradas[[#This Row],[Data da Competência]])) -> 2024 | M52: =IF(TbRegistroEntradas[[#This Row],[Data do Caixa Previsto]]="",0,MONTH(TbRegistroEntradas[[#This Row],[Data do Caixa Previsto]])) -> 2 | N52: =IF(TbRegistroEntradas[[#This Row],[Data do Caixa Previsto]]="",0,YEAR(TbRegistroEntradas[[#This Row],[Data do Caixa Previsto]])) -> 2025 | O52: =IF(AND(TbRegistroEntradas[[#This Row],[Data do Caixa Previsto]]<TODAY(),TbRegistroEntradas[[#This Row],[Data do Caixa Realizado]]=""),"Vencida","Não Vencida") -> Não Vencida | P52: =IF(TbRegistroEntradas[[#This Row],[Data da Competência]]=TbRegistroEntradas[[#This Row],[Data do Caixa Previsto]],"Vista","Prazo") -> Prazo | Q52: =IF(TbRegistroEntradas[[#This Row],[Data do Caixa Realizado]]<>"", IF(TbRegistroEntradas[[#This Row],[Data do Caixa Realizado]]>TbRegistroEntradas[[#This Row],[Data do Caixa Previsto]], TbRegistroEntradas[[#This Row],[Data do Caixa Realizado]]-TbRegistroEntradas[[#This Row],[Data do Caixa Previsto]], 0 ), IF(TODAY()>TbRegistroEntradas[[#This Row],[Data do Caixa Previsto]], TODAY()-TbRegistroEntradas[[#This Row],[Data do Caixa Previsto]], 0 ) ) -> 21
B53: 45658 | C53: 45656 | D53: 45658 | E53: Vendas de mercadorias | F53: Móveis | G53: NF8895 | H53: 3192 | I53: =IF(TbRegistroEntradas[[#This Row],[Data do Caixa Realizado]]="",0,MONTH(TbRegistroEntradas[[#This Row],[Data do Caixa Previsto]])) -> 1 | J53: =IF(TbRegistroEntradas[[#This Row],[Data do Caixa Realizado]]="",0,YEAR(TbRegistroEntradas[[#This Row],[Data do Caixa Realizado]])) -> 2025 | K53: =IF(TbRegistroEntradas[[#This Row],[Data da Competência]]="",0,MONTH(TbRegistroEntradas[[#This Row],[Data da Competência]])) -> 12 | L53: =IF(TbRegistroEntradas[[#This Row],[Data da Competência]]="",0,YEAR(TbRegistroEntradas[[#This Row],[Data da Competência]])) -> 2024 | M53: =IF(TbRegistroEntradas[[#This Row],[Data do Caixa Previsto]]="",0,MONTH(TbRegistroEntradas[[#This Row],[Data do Caixa Previsto]])) -> 1 | N53: =IF(TbRegistroEntradas[[#This Row],[Data do Caixa Previsto]]="",0,YEAR(TbRegistroEntradas[[#This Row],[Data do Caixa Previsto]])) -> 2025 | O53: =IF(AND(TbRegistroEntradas[[#This Row],[Data do Caixa Previsto]]<TODAY(),TbRegistroEntradas[[#This Row],[Data do Caixa Realizado]]=""),"Vencida","Não Vencida") -> Não Vencida | P53: =IF(TbRegistroEntradas[[#This Row],[Data da Competência]]=TbRegistroEntradas[[#This Row],[Data do Caixa Previsto]],"Vista","Prazo") -> Prazo | Q53: =IF(TbRegistroEntradas[[#This Row],[Data do Caixa Realizado]]<>"", IF(TbRegistroEntradas[[#This Row],[Data do Caixa Realizado]]>TbRegistroEntradas[[#This Row],[Data do Caixa Previsto]], TbRegistroEntradas[[#This Row],[Data do Caixa Realizado]]-TbRegistroEntradas[[#This Row],[Data do Caixa Previsto]], 0 ), IF(TODAY()>TbRegistroEntradas[[#This Row],[Data do Caixa Previsto]], TODAY()-TbRegistroEntradas[[#This Row],[Data do Caixa Previsto]], 0 ) ) -> 0
... B82: 45777 | C82: 45737 | D82: 45777 | E82: Vendas de mercadorias | F82: Móveis | G82: NF7119 | H82: 4606 | I82: =IF(TbRegistroEntradas[[#This Row],[Data do Caixa Realizado]]="",0,MONTH(TbRegistroEntradas[[#This Row],[Data do Caixa Previsto]])) -> 4 | J82: =IF(TbRegistroEntradas[[#This Row],[Data do Caixa Realizado]]="",0,YEAR(TbRegistroEntradas[[#This Row],[Data do Caixa Realizado]])) -> 2025 | K82: =IF(TbRegistroEntradas[[#This Row],[Data da Competência]]="",0,MONTH(TbRegistroEntradas[[#This Row],[Data da Competência]])) -> 3 | L82: =IF(TbRegistroEntradas[[#This Row],[Data da Competência]]="",0,YEAR(TbRegistroEntradas[[#This Row],[Data da Competência]])) -> 2025 | M82: =IF(TbRegistroEntradas[[#This Row],[Data do Caixa Previsto]]="",0,MONTH(TbRegistroEntradas[[#This Row],[Data do Caixa Previsto]])) -> 4 | N82: =IF(TbRegistroEntradas[[#This Row],[Data do Caixa Previsto]]="",0,YEAR(TbRegistroEntradas[[#This Row],[Data do Caixa Previsto]])) -> 2025 | O82: =IF(AND(TbRegistroEntradas[[#This Row],[Data do Caixa Previsto]]<TODAY(),TbRegistroEntradas[[#This Row],[Data do Caixa Realizado]]=""),"Vencida","Não Vencida") -> Não Vencida | P82: =IF(TbRegistroEntradas[[#This Row],[Data da Competência]]=TbRegistroEntradas[[#This Row],[Data do Caixa Previsto]],"Vista","Prazo") -> Prazo | Q82: =IF(TbRegistroEntradas[[#This Row],[Data do Caixa Realizado]]<>"", IF(TbRegistroEntradas[[#This Row],[Data do Caixa Realizado]]>TbRegistroEntradas[[#This Row],[Data do Caixa Previsto]], TbRegistroEntradas[[#This Row],[Data do Caixa Realizado]]-TbRegistroEntradas[[#This Row],[Data do Caixa Previsto]], 0 ), IF(TODAY()>TbRegistroEntradas[[#This Row],[Data do Caixa Previsto]], TODAY()-TbRegistroEntradas[[#This Row],[Data do Caixa Previsto]], 0 ) ) -> 0
C83: 45739 | D83: 45756 | E83: Vendas de mercadorias | F83: Informática | G83: NF2814 | H83: 2388 | I83: =IF(TbRegistroEntradas[[#This Row],[Data do Caixa Realizado]]="",0,MONTH(TbRegistroEntradas[[#This Row],[Data do Caixa Previsto]])) -> 0 | J83: =IF(TbRegistroEntradas[[#This Row],[Data do Caixa Realizado]]="",0,YEAR(TbRegistroEntradas[[#This Row],[Data do Caixa Realizado]])) -> 0 | K83: =IF(TbRegistroEntradas[[#This Row],[Data da Competência]]="",0,MONTH(TbRegistroEntradas[[#This Row],[Data da Competência]])) -> 3 | L83: =IF(TbRegistroEntradas[[#This Row],[Data da Competência]]="",0,YEAR(TbRegistroEntradas[[#This Row],[Data da Competência]])) -> 2025 | M83: =IF(TbRegistroEntradas[[#This Row],[Data do Caixa Previsto]]="",0,MONTH(TbRegistroEntradas[[#This Row],[Data do Caixa Previsto]])) -> 4 | N83: =IF(TbRegistroEntradas[[#This Row],[Data do Caixa Previsto]]="",0,YEAR(TbRegistroEntradas[[#This Row],[Data do Caixa Previsto]])) -> 2025 | O83: =IF(AND(TbRegistroEntradas[[#This Row],[Data do Caixa Previsto]]<TODAY(),TbRegistroEntradas[[#This Row],[Data do Caixa Realizado]]=""),"Vencida","Não Vencida") -> Vencida | P83: =IF(TbRegistroEntradas[[#This Row],[Data da Competência]]=TbRegistroEntradas[[#This Row],[Data do Caixa Previsto]],"Vista","Prazo") -> Prazo | Q83: =IF(TbRegistroEntradas[[#This Row],[Data do Caixa Realizado]]<>"", IF(TbRegistroEntradas[[#This Row],[Data do Caixa Realizado]]>TbRegistroEntradas[[#This Row],[Data do Caixa Previsto]], TbRegistroEntradas[[#This Row],[Data do Caixa Realizado]]-TbRegistroEntradas[[#This Row],[Data do Caixa Previsto]], 0 ), IF(TODAY()>TbRegistroEntradas[[#This Row],[Data do Caixa Previsto]], TODAY()-TbRegistroEntradas[[#This Row],[Data do Caixa Previsto]], 0 ) ) -> 453
B84: 45744 | C84: 45741 | D84: 45744 | E84: Vendas de mercadorias | F84: Eletrodomésticos | G84: NF5963 | H84: 2303 | I84: =IF(TbRegistroEntradas[[#This Row],[Data do Caixa Realizado]]="",0,MONTH(TbRegistroEntradas[[#This Row],[Data do Caixa Previsto]])) -> 3 | J84: =IF(TbRegistroEntradas[[#This Row],[Data do Caixa Realizado]]="",0,YEAR(TbRegistroEntradas[[#This Row],[Data do Caixa Realizado]])) -> 2025 | K84: =IF(TbRegistroEntradas[[#This Row],[Data da Competência]]="",0,MONTH(TbRegistroEntradas[[#This Row],[Data da Competência]])) -> 3 | L84: =IF(TbRegistroEntradas[[#This Row],[Data da Competência]]="",0,YEAR(TbRegistroEntradas[[#This Row],[Data da Competência]])) -> 2025 | M84: =IF(TbRegistroEntradas[[#This Row],[Data do Caixa Previsto]]="",0,MONTH(TbRegistroEntradas[[#This Row],[Data do Caixa Previsto]])) -> 3 | N84: =IF(TbRegistroEntradas[[#This Row],[Data do Caixa Previsto]]="",0,YEAR(TbRegistroEntradas[[#This Row],[Data do Caixa Previsto]])) -> 2025 | O84: =IF(AND(TbRegistroEntradas[[#This Row],[Data do Caixa Previsto]]<TODAY(),TbRegistroEntradas[[#This Row],[Data do Caixa Realizado]]=""),"Vencida","Não Vencida") -> Não Vencida | P84: =IF(TbRegistroEntradas[[#This Row],[Data da Competência]]=TbRegistroEntradas[[#This Row],[Data do Caixa Previsto]],"Vista","Prazo") -> Prazo | Q84: =IF(TbRegistroEntradas[[#This Row],[Data do Caixa Realizado]]<>"", IF(TbRegistroEntradas[[#This Row],[Data do Caixa Realizado]]>TbRegistroEntradas[[#This Row],[Data do Caixa Previsto]], TbRegistroEntradas[[#This Row],[Data do Caixa Realizado]]-TbRegistroEntradas[[#This Row],[Data do Caixa Previsto]], 0 ), IF(TODAY()>TbRegistroEntradas[[#This Row],[Data do Caixa Previsto]], TODAY()-TbRegistroEntradas[[#This Row],[Data do Caixa Previsto]], 0 ) ) -> 0
B85: 45762 | C85: 45744 | D85: 45762 | E85: Vendas de mercadorias | F85: Som e imagem | G85: NF3293 | H85: 1662 | I85: =IF(TbRegistroEntradas[[#This Row],[Data do Caixa Realizado]]="",0,MONTH(TbRegistroEntradas[[#This Row],[Data do Caixa Previsto]])) -> 4 | J85: =IF(TbRegistroEntradas[[#This Row],[Data do Caixa Realizado]]="",0,YEAR(TbRegistroEntradas[[#This Row],[Data do Caixa Realizado]])) -> 2025 | K85: =IF(TbRegistroEntradas[[#This Row],[Data da Competência]]="",0,MONTH(TbRegistroEntradas[[#This Row],[Data da Competência]])) -> 3 | L85: =IF(TbRegistroEntradas[[#This Row],[Data da Competência]]="",0,YEAR(TbRegistroEntradas[[#This Row],[Data da Competência]])) -> 2025 | M85: =IF(TbRegistroEntradas[[#This Row],[Data do Caixa Previsto]]="",0,MONTH(TbRegistroEntradas[[#This Row],[Data do Caixa Previsto]])) -> 4 | N85: =IF(TbRegistroEntradas[[#This Row],[Data do Caixa Previsto]]="",0,YEAR(TbRegistroEntradas[[#This Row],[Data do Caixa Previsto]])) -> 2025 | O85: =IF(AND(TbRegistroEntradas[[#This Row],[Data do Caixa Previsto]]<TODAY(),TbRegistroEntradas[[#This Row],[Data do Caixa Realizado]]=""),"Vencida","Não Vencida") -> Não Vencida | P85: =IF(TbRegistroEntradas[[#This Row],[Data da Competência]]=TbRegistroEntradas[[#This Row],[Data do Caixa Previsto]],"Vista","Prazo") -> Prazo | Q85: =IF(TbRegistroEntradas[[#This Row],[Data do Caixa Realizado]]<>"", IF(TbRegistroEntradas[[#This Row],[Data do Caixa Realizado]]>TbRegistroEntradas[[#This Row],[Data do Caixa Previsto]], TbRegistroEntradas[[#This Row],[Data do Caixa Realizado]]-TbRegistroEntradas[[#This Row],[Data do Caixa Previsto]], 0 ), IF(TODAY()>TbRegistroEntradas[[#This Row],[Data do Caixa Previsto]], TODAY()-TbRegistroEntradas[[#This Row],[Data do Caixa Previsto]], 0 ) ) -> 0
B86: 45785 | C86: 45746 | D86: 45785 | E86: Vendas de mercadorias | F86: Informática | G86: NF8254 | H86: 3241 | I86: =IF(TbRegistroEntradas[[#This Row],[Data do Caixa Realizado]]="",0,MONTH(TbRegistroEntradas[[#This Row],[Data do Caixa Previsto]])) -> 5 | J86: =IF(TbRegistroEntradas[[#This Row],[Data do Caixa Realizado]]="",0,YEAR(TbRegistroEntradas[[#This Row],[Data do Caixa Realizado]])) -> 2025 | K86: =IF(TbRegistroEntradas[[#This Row],[Data da Competência]]="",0,MONTH(TbRegistroEntradas[[#This Row],[Data da Competência]])) -> 3 | L86: =IF(TbRegistroEntradas[[#This Row],[Data da Competência]]="",0,YEAR(TbRegistroEntradas[[#This Row],[Data da Competência]])) -> 2025 | M86: =IF(TbRegistroEntradas[[#This Row],[Data do Caixa Previsto]]="",0,MONTH(TbRegistroEntradas[[#This Row],[Data do Caixa Previsto]])) -> 5 | N86: =IF(TbRegistroEntradas[[#This Row],[Data do Caixa Previsto]]="",0,YEAR(TbRegistroEntradas[[#This Row],[Data do Caixa Previsto]])) -> 2025 | O86: =IF(AND(TbRegistroEntradas[[#This Row],[Data do Caixa Previsto]]<TODAY(),TbRegistroEntradas[[#This Row],[Data do Caixa Realizado]]=""),"Vencida","Não Vencida") -> Não Vencida | P86: =IF(TbRegistroEntradas[[#This Row],[Data da Competência]]=TbRegistroEntradas[[#This Row],[Data do Caixa Previsto]],"Vista","Prazo") -> Prazo | Q86: =IF(TbRegistroEntradas[[#This Row],[Data do Caixa Realizado]]<>"", IF(TbRegistroEntradas[[#This Row],[Data do Caixa Realizado]]>TbRegistroEntradas[[#This Row],[Data do Caixa Previsto]], TbRegistroEntradas[[#This Row],[Data do Caixa Realizado]]-TbRegistroEntradas[[#This Row],[Data do Caixa Previsto]], 0 ), IF(TODAY()>TbRegistroEntradas[[#This Row],[Data do Caixa Previsto]], TODAY()-TbRegistroEntradas[[#This Row],[Data do Caixa Previsto]], 0 ) ) -> 0
B87: 45785 | C87: 45747 | D87: 45785 | E87: Vendas de mercadorias | F87: Som e imagem | G87: NF4303 | H87: 4017 | I87: =IF(TbRegistroEntradas[[#This Row],[Data do Caixa Realizado]]="",0,MONTH(TbRegistroEntradas[[#This Row],[Data do Caixa Previsto]])) -> 5 | J87: =IF(TbRegistroEntradas[[#This Row],[Data do Caixa Realizado]]="",0,YEAR(TbRegistroEntradas[[#This Row],[Data do Caixa Realizado]])) -> 2025 | K87: =IF(TbRegistroEntradas[[#This Row],[Data da Competência]]="",0,MONTH(TbRegistroEntradas[[#This Row],[Data da Competência]])) -> 3 | L87: =IF(TbRegistroEntradas[[#This Row],[Data da Competência]]="",0,YEAR(TbRegistroEntradas[[#This Row],[Data da Competência]])) -> 2025 | M87: =IF(TbRegistroEntradas[[#This Row],[Data do Caixa Previsto]]="",0,MONTH(TbRegistroEntradas[[#This Row],[Data do Caixa Previsto]])) -> 5 | N87: =IF(TbRegistroEntradas[[#This Row],[Data do Caixa Previsto]]="",0,YEAR(TbRegistroEntradas[[#This Row],[Data do Caixa Previsto]])) -> 2025 | O87: =IF(AND(TbRegistroEntradas[[#This Row],[Data do Caixa Previsto]]<TODAY(),TbRegistroEntradas[[#This Row],[Data do Caixa Realizado]]=""),"Vencida","Não Vencida") -> Não Vencida | P87: =IF(TbRegistroEntradas[[#This Row],[Data da Competência]]=TbRegistroEntradas[[#This Row],[Data do Caixa Previsto]],"Vista","Prazo") -> Prazo | Q87: =IF(TbRegistroEntradas[[#This Row],[Data do Caixa Realizado]]<>"", IF(TbRegistroEntradas[[#This Row],[Data do Caixa Realizado]]>TbRegistroEntradas[[#This Row],[Data do Caixa Previsto]], TbRegistroEntradas[[#This Row],[Data do Caixa Realizado]]-TbRegistroEntradas[[#This Row],[Data do Caixa Previsto]], 0 ), IF(TODAY()>TbRegistroEntradas[[#This Row],[Data do Caixa Previsto]], TODAY()-TbRegistroEntradas[[#This Row],[Data do Caixa Previsto]], 0 ) ) -> 0
B88: 45846 | C88: 45750 | D88: 45808 | E88: Vendas de mercadorias | F88: Móveis | G88: NF2605 | H88: 3586 | I88: =IF(TbRegistroEntradas[[#This Row],[Data do Caixa Realizado]]="",0,MONTH(TbRegistroEntradas[[#This Row],[Data do Caixa Previsto]])) -> 5 | J88: =IF(TbRegistroEntradas[[#This Row],[Data do Caixa Realizado]]="",0,YEAR(TbRegistroEntradas[[#This Row],[Data do Caixa Realizado]])) -> 2025 | K88: =IF(TbRegistroEntradas[[#This Row],[Data da Competência]]="",0,MONTH(TbRegistroEntradas[[#This Row],[Data da Competência]])) -> 4 | L88: =IF(TbRegistroEntradas[[#This Row],[Data da Competência]]="",0,YEAR(TbRegistroEntradas[[#This Row],[Data da Competência]])) -> 2025 | M88: =IF(TbRegistroEntradas[[#This Row],[Data do Caixa Previsto]]="",0,MONTH(TbRegistroEntradas[[#This Row],[Data do Caixa Previsto]])) -> 5 | N88: =IF(TbRegistroEntradas[[#This Row],[Data do Caixa Previsto]]="",0,YEAR(TbRegistroEntradas[[#This Row],[Data do Caixa Previsto]])) -> 2025 | O88: =IF(AND(TbRegistroEntradas[[#This Row],[Data do Caixa Previsto]]<TODAY(),TbRegistroEntradas[[#This Row],[Data do Caixa Realizado]]=""),"Vencida","Não Vencida") -> Não Vencida | P88: =IF(TbRegistroEntradas[[#This Row],[Data da Competência]]=TbRegistroEntradas[[#This Row],[Data do Caixa Previsto]],"Vista","Prazo") -> Prazo | Q88: =IF(TbRegistroEntradas[[#This Row],[Data do Caixa Realizado]]<>"", IF(TbRegistroEntradas[[#This Row],[Data do Caixa Realizado]]>TbRegistroEntradas[[#This Row],[Data do Caixa Previsto]], TbRegistroEntradas[[#This Row],[Data do Caixa Realizado]]-TbRegistroEntradas[[#This Row],[Data do Caixa Previsto]], 0 ), IF(TODAY()>TbRegistroEntradas[[#This Row],[Data do Caixa Previsto]], TODAY()-TbRegistroEntradas[[#This Row],[Data do Caixa Previsto]], 0 ) ) -> 38
B89: 45778 | C89: 45753 | D89: 45778 | E89: Vendas de mercadorias | F89: Informática | G89: NF8043 | H89: 4467 | I89: =IF(TbRegistroEntradas[[#This Row],[Data do Caixa Realizado]]="",0,MONTH(TbRegistroEntradas[[#This Row],[Data do Caixa Previsto]])) -> 5 | J89: =IF(TbRegistroEntradas[[#This Row],[Data do Caixa Realizado]]="",0,YEAR(TbRegistroEntradas[[#This Row],[Data do Caixa Realizado]])) -> 2025 | K89: =IF(TbRegistroEntradas[[#This Row],[Data da Competência]]="",0,MONTH(TbRegistroEntradas[[#This Row],[Data da Competência]])) -> 4 | L89: =IF(TbRegistroEntradas[[#This Row],[Data da Competência]]="",0,YEAR(TbRegistroEntradas[[#This Row],[Data da Competência]])) -> 2025 | M89: =IF(TbRegistroEntradas[[#This Row],[Data do Caixa Previsto]]="",0,MONTH(TbRegistroEntradas[[#This Row],[Data do Caixa Previsto]])) -> 5 | N89: =IF(TbRegistroEntradas[[#This Row],[Data do Caixa Previsto]]="",0,YEAR(TbRegistroEntradas[[#This Row],[Data do Caixa Previsto]])) -> 2025 | O89: =IF(AND(TbRegistroEntradas[[#This Row],[Data do Caixa Previsto]]<TODAY(),TbRegistroEntradas[[#This Row],[Data do Caixa Realizado]]=""),"Vencida","Não Vencida") -> Não Vencida | P89: =IF(TbRegistroEntradas[[#This Row],[Data da Competência]]=TbRegistroEntradas[[#This Row],[Data do Caixa Previsto]],"Vista","Prazo") -> Prazo | Q89: =IF(TbRegistroEntradas[[#This Row],[Data do Caixa Realizado]]<>"", IF(TbRegistroEntradas[[#This Row],[Data do Caixa Realizado]]>TbRegistroEntradas[[#This Row],[Data do Caixa Previsto]], TbRegistroEntradas[[#This Row],[Data do Caixa Realizado]]-TbRegistroEntradas[[#This Row],[Data do Caixa Previsto]], 0 ), IF(TODAY()>TbRegistroEntradas[[#This Row],[Data do Caixa Previsto]], TODAY()-TbRegistroEntradas[[#This Row],[Data do Caixa Previsto]], 0 ) ) -> 0
B90: 45808 | C90: 45756 | D90: 45808 | E90: Vendas de mercadorias | F90: Móveis | G90: NF6697 | H90: 4262 | I90: =IF(TbRegistroEntradas[[#This Row],[Data do Caixa Realizado]]="",0,MONTH(TbRegistroEntradas[[#This Row],[Data do Caixa Previsto]])) -> 5 | J90: =IF(TbRegistroEntradas[[#This Row],[Data do Caixa Realizado]]="",0,YEAR(TbRegistroEntradas[[#This Row],[Data do Caixa Realizado]])) -> 2025 | K90: =IF(TbRegistroEntradas[[#This Row],[Data da Competência]]="",0,MONTH(TbRegistroEntradas[[#This Row],[Data da Competência]])) -> 4 | L90: =IF(TbRegistroEntradas[[#This Row],[Data da Competência]]="",0,YEAR(TbRegistroEntradas[[#This Row],[Data da Competência]])) -> 2025 | M90: =IF(TbRegistroEntradas[[#This Row],[Data do Caixa Previsto]]="",0,MONTH(TbRegistroEntradas[[#This Row],[Data do Caixa Previsto]])) -> 5 | N90: =IF(TbRegistroEntradas[[#This Row],[Data do Caixa Previsto]]="",0,YEAR(TbRegistroEntradas[[#This Row],[Data do Caixa Previsto]])) -> 2025 | O90: =IF(AND(TbRegistroEntradas[[#This Row],[Data do Caixa Previsto]]<TODAY(),TbRegistroEntradas[[#This Row],[Data do Caixa Realizado]]=""),"Vencida","Não Vencida") -> Não Vencida | P90: =IF(TbRegistroEntradas[[#This Row],[Data da Competência]]=TbRegistroEntradas[[#This Row],[Data do Caixa Previsto]],"Vista","Prazo") -> Prazo | Q90: =IF(TbRegistroEntradas[[#This Row],[Data do Caixa Realizado]]<>"", IF(TbRegistroEntradas[[#This Row],[Data do Caixa Realizado]]>TbRegistroEntradas[[#This Row],[Data do Caixa Previsto]], TbRegistroEntradas[[#This Row],[Data do Caixa Realizado]]-TbRegistroEntradas[[#This Row],[Data do Caixa Previsto]], 0 ), IF(TODAY()>TbRegistroEntradas[[#This Row],[Data do Caixa Previsto]], TODAY()-TbRegistroEntradas[[#This Row],[Data do Caixa Previsto]], 0 ) ) -> 0
B91: 45821 | C91: 45758 | D91: 45817 | E91: Vendas de mercadorias | F91: Móveis | G91: NF5208 | H91: 2593 | I91: =IF(TbRegistroEntradas[[#This Row],[Data do Caixa Realizado]]="",0,MONTH(TbRegistroEntradas[[#This Row],[Data do Caixa Previsto]])) -> 6 | J91: =IF(TbRegistroEntradas[[#This Row],[Data do Caixa Realizado]]="",0,YEAR(TbRegistroEntradas[[#This Row],[Data do Caixa Realizado]])) -> 2025 | K91: =IF(TbRegistroEntradas[[#This Row],[Data da Competência]]="",0,MONTH(TbRegistroEntradas[[#This Row],[Data da Competência]])) -> 4 | L91: =IF(TbRegistroEntradas[[#This Row],[Data da Competência]]="",0,YEAR(TbRegistroEntradas[[#This Row],[Data da Competência]])) -> 2025 | M91: =IF(TbRegistroEntradas[[#This Row],[Data do Caixa Previsto]]="",0,MONTH(TbRegistroEntradas[[#This Row],[Data do Caixa Previsto]])) -> 6 | N91: =IF(TbRegistroEntradas[[#This Row],[Data do Caixa Previsto]]="",0,YEAR(TbRegistroEntradas[[#This Row],[Data do Caixa Previsto]])) -> 2025 | O91: =IF(AND(TbRegistroEntradas[[#This Row],[Data do Caixa Previsto]]<TODAY(),TbRegistroEntradas[[#This Row],[Data do Caixa Realizado]]=""),"Vencida","Não Vencida") -> Não Vencida | P91: =IF(TbRegistroEntradas[[#This Row],[Data da Competência]]=TbRegistroEntradas[[#This Row],[Data do Caixa Previsto]],"Vista","Prazo") -> Prazo | Q91: =IF(TbRegistroEntradas[[#This Row],[Data do Caixa Realizado]]<>"", IF(TbRegistroEntradas[[#This Row],[Data do Caixa Realizado]]>TbRegistroEntradas[[#This Row],[Data do Caixa Previsto]], TbRegistroEntradas[[#This Row],[Data do Caixa Realizado]]-TbRegistroEntradas[[#This Row],[Data do Caixa Previsto]], 0 ), IF(TODAY()>TbRegistroEntradas[[#This Row],[Data do Caixa Previsto]], TODAY()-TbRegistroEntradas[[#This Row],[Data do Caixa Previsto]], 0 ) ) -> 4
B92: 45781 | C92: 45761 | D92: 45781 | E92: Vendas de mercadorias | F92: Móveis | G92: NF2907 | H92: 1885 | I92: =IF(TbRegistroEntradas[[#This Row],[Data do Caixa Realizado]]="",0,MONTH(TbRegistroEntradas[[#This Row],[Data do Caixa Previsto]])) -> 5 | J92: =IF(TbRegistroEntradas[[#This Row],[Data do Caixa Realizado]]="",0,YEAR(TbRegistroEntradas[[#This Row],[Data do Caixa Realizado]])) -> 2025 | K92: =IF(TbRegistroEntradas[[#This Row],[Data da Competência]]="",0,MONTH(TbRegistroEntradas[[#This Row],[Data da Competência]])) -> 4 | L92: =IF(TbRegistroEntradas[[#This Row],[Data da Competência]]="",0,YEAR(TbRegistroEntradas[[#This Row],[Data da Competência]])) -> 2025 | M92: =IF(TbRegistroEntradas[[#This Row],[Data do Caixa Previsto]]="",0,MONTH(TbRegistroEntradas[[#This Row],[Data do Caixa Previsto]])) -> 5 | N92: =IF(TbRegistroEntradas[[#This Row],[Data do Caixa Previsto]]="",0,YEAR(TbRegistroEntradas[[#This Row],[Data do Caixa Previsto]])) -> 2025 | O92: =IF(AND(TbRegistroEntradas[[#This Row],[Data do Caixa Previsto]]<TODAY(),TbRegistroEntradas[[#This Row],[Data do Caixa Realizado]]=""),"Vencida","Não Vencida") -> Não Vencida | P92: =IF(TbRegistroEntradas[[#This Row],[Data da Competência]]=TbRegistroEntradas[[#This Row],[Data do Caixa Previsto]],"Vista","Prazo") -> Prazo | Q92: =IF(TbRegistroEntradas[[#This Row],[Data do Caixa Realizado]]<>"", IF(TbRegistroEntradas[[#This Row],[Data do Caixa Realizado]]>TbRegistroEntradas[[#This Row],[Data do Caixa Previsto]], TbRegistroEntradas[[#This Row],[Data do Caixa Realizado]]-TbRegistroEntradas[[#This Row],[Data do Caixa Previsto]], 0 ), IF(TODAY()>TbRegistroEntradas[[#This Row],[Data do Caixa Previsto]], TODAY()-TbRegistroEntradas[[#This Row],[Data do Caixa Previsto]], 0 ) ) -> 0
C93: 45766 | D93: 45823 | E93: Vendas de mercadorias | F93: Móveis | G93: NF9381 | H93: 2224 | I93: =IF(TbRegistroEntradas[[#This Row],[Data do Caixa Realizado]]="",0,MONTH(TbRegistroEntradas[[#This Row],[Data do Caixa Previsto]])) -> 0 | J93: =IF(TbRegistroEntradas[[#This Row],[Data do Caixa Realizado]]="",0,YEAR(TbRegistroEntradas[[#This Row],[Data do Caixa Realizado]])) -> 0 | K93: =IF(TbRegistroEntradas[[#This Row],[Data da Competência]]="",0,MONTH(TbRegistroEntradas[[#This Row],[Data da Competência]])) -> 4 | L93: =IF(TbRegistroEntradas[[#This Row],[Data da Competência]]="",0,YEAR(TbRegistroEntradas[[#This Row],[Data da Competência]])) -> 2025 | M93: =IF(TbRegistroEntradas[[#This Row],[Data do Caixa Previsto]]="",0,MONTH(TbRegistroEntradas[[#This Row],[Data do Caixa Previsto]])) -> 6 | N93: =IF(TbRegistroEntradas[[#This Row],[Data do Caixa Previsto]]="",0,YEAR(TbRegistroEntradas[[#This Row],[Data do Caixa Previsto]])) -> 2025 | O93: =IF(AND(TbRegistroEntradas[[#This Row],[Data do Caixa Previsto]]<TODAY(),TbRegistroEntradas[[#This Row],[Data do Caixa Realizado]]=""),"Vencida","Não Vencida") -> Vencida | P93: =IF(TbRegistroEntradas[[#This Row],[Data da Competência]]=TbRegistroEntradas[[#This Row],[Data do Caixa Previsto]],"Vista","Prazo") -> Prazo | Q93: =IF(TbRegistroEntradas[[#This Row],[Data do Caixa Realizado]]<>"", IF(TbRegistroEntradas[[#This Row],[Data do Caixa Realizado]]>TbRegistroEntradas[[#This Row],[Data do Caixa Previsto]], TbRegistroEntradas[[#This Row],[Data do Caixa Realizado]]-TbRegistroEntradas[[#This Row],[Data do Caixa Previsto]], 0 ), IF(TODAY()>TbRegistroEntradas[[#This Row],[Data do Caixa Previsto]], TODAY()-TbRegistroEntradas[[#This Row],[Data do Caixa Previsto]], 0 ) ) -> 386
B94: 45859 | C94: 45770 | D94: 45791 | E94: Vendas de mercadorias | F94: Móveis | G94: NF3247 | H94: 3223 | I94: =IF(TbRegistroEntradas[[#This Row],[Data do Caixa Realizado]]="",0,MONTH(TbRegistroEntradas[[#This Row],[Data do Caixa Previsto]])) -> 5 | J94: =IF(TbRegistroEntradas[[#This Row],[Data do Caixa Realizado]]="",0,YEAR(TbRegistroEntradas[[#This Row],[Data do Caixa Realizado]])) -> 2025 | K94: =IF(TbRegistroEntradas[[#This Row],[Data da Competência]]="",0,MONTH(TbRegistroEntradas[[#This Row],[Data da Competência]])) -> 4 | L94: =IF(TbRegistroEntradas[[#This Row],[Data da Competência]]="",0,YEAR(TbRegistroEntradas[[#This Row],[Data da Competência]])) -> 2025 | M94: =IF(TbRegistroEntradas[[#This Row],[Data do Caixa Previsto]]="",0,MONTH(TbRegistroEntradas[[#This Row],[Data do Caixa Previsto]])) -> 5 | N94: =IF(TbRegistroEntradas[[#This Row],[Data do Caixa Previsto]]="",0,YEAR(TbRegistroEntradas[[#This Row],[Data do Caixa Previsto]])) -> 2025 | O94: =IF(AND(TbRegistroEntradas[[#This Row],[Data do Caixa Previsto]]<TODAY(),TbRegistroEntradas[[#This Row],[Data do Caixa Realizado]]=""),"Vencida","Não Vencida") -> Não Vencida | P94: =IF(TbRegistroEntradas[[#This Row],[Data da Competência]]=TbRegistroEntradas[[#This Row],[Data do Caixa Previsto]],"Vista","Prazo") -> Prazo | Q94: =IF(TbRegistroEntradas[[#This Row],[Data do Caixa Realizado]]<>"", IF(TbRegistroEntradas[[#This Row],[Data do Caixa Realizado]]>TbRegistroEntradas[[#This Row],[Data do Caixa Previsto]], TbRegistroEntradas[[#This Row],[Data do Caixa Realizado]]-TbRegistroEntradas[[#This Row],[Data do Caixa Previsto]], 0 ), IF(TODAY()>TbRegistroEntradas[[#This Row],[Data do Caixa Previsto]], TODAY()-TbRegistroEntradas[[#This Row],[Data do Caixa Previsto]], 0 ) ) -> 68
B95: 45856 | C95: 45773 | D95: 45822 | E95: Vendas de mercadorias | F95: Livros | G95: NF4377 | H95: 3446 | I95: =IF(TbRegistroEntradas[[#This Row],[Data do Caixa Realizado]]="",0,MONTH(TbRegistroEntradas[[#This Row],[Data do Caixa Previsto]])) -> 6 | J95: =IF(TbRegistroEntradas[[#This Row],[Data do Caixa Realizado]]="",0,YEAR(TbRegistroEntradas[[#This Row],[Data do Caixa Realizado]])) -> 2025 | K95: =IF(TbRegistroEntradas[[#This Row],[Data da Competência]]="",0,MONTH(TbRegistroEntradas[[#This Row],[Data da Competência]])) -> 4 | L95: =IF(TbRegistroEntradas[[#This Row],[Data da Competência]]="",0,YEAR(TbRegistroEntradas[[#This Row],[Data da Competência]])) -> 2025 | M95: =IF(TbRegistroEntradas[[#This Row],[Data do Caixa Previsto]]="",0,MONTH(TbRegistroEntradas[[#This Row],[Data do Caixa Previsto]])) -> 6 | N95: =IF(TbRegistroEntradas[[#This Row],[Data do Caixa Previsto]]="",0,YEAR(TbRegistroEntradas[[#This Row],[Data do Caixa Previsto]])) -> 2025 | O95: =IF(AND(TbRegistroEntradas[[#This Row],[Data do Caixa Previsto]]<TODAY(),TbRegistroEntradas[[#This Row],[Data do Caixa Realizado]]=""),"Vencida","Não Vencida") -> Não Vencida | P95: =IF(TbRegistroEntradas[[#This Row],[Data da Competência]]=TbRegistroEntradas[[#This Row],[Data do Caixa Previsto]],"Vista","Prazo") -> Prazo | Q95: =IF(TbRegistroEntradas[[#This Row],[Data do Caixa Realizado]]<>"", IF(TbRegistroEntradas[[#This Row],[Data do Caixa Realizado]]>TbRegistroEntradas[[#This Row],[Data do Caixa Previsto]], TbRegistroEntradas[[#This Row],[Data do Caixa Realizado]]-TbRegistroEntradas[[#This Row],[Data do Caixa Previsto]], 0 ), IF(TODAY()>TbRegistroEntradas[[#This Row],[Data do Caixa Previsto]], TODAY()-TbRegistroEntradas[[#This Row],[Data do Caixa Previsto]], 0 ) ) -> 34
B96: 45822 | C96: 45777 | D96: 45822 | E96: Vendas de mercadorias | F96: Móveis | G96: NF2988 | H96: 4540 | I96: =IF(TbRegistroEntradas[[#This Row],[Data do Caixa Realizado]]="",0,MONTH(TbRegistroEntradas[[#This Row],[Data do Caixa Previsto]])) -> 6 | J96: =IF(TbRegistroEntradas[[#This Row],[Data do Caixa Realizado]]="",0,YEAR(TbRegistroEntradas[[#This Row],[Data do Caixa Realizado]])) -> 2025 | K96: =IF(TbRegistroEntradas[[#This Row],[Data da Competência]]="",0,MONTH(TbRegistroEntradas[[#This Row],[Data da Competência]])) -> 4 | L96: =IF(TbRegistroEntradas[[#This Row],[Data da Competência]]="",0,YEAR(TbRegistroEntradas[[#This Row],[Data da Competência]])) -> 2025 | M96: =IF(TbRegistroEntradas[[#This Row],[Data do Caixa Previsto]]="",0,MONTH(TbRegistroEntradas[[#This Row],[Data do Caixa Previsto]])) -> 6 | N96: =IF(TbRegistroEntradas[[#This Row],[Data do Caixa Previsto]]="",0,YEAR(TbRegistroEntradas[[#This Row],[Data do Caixa Previsto]])) -> 2025 | O96: =IF(AND(TbRegistroEntradas[[#This Row],[Data do Caixa Previsto]]<TODAY(),TbRegistroEntradas[[#This Row],[Data do Caixa Realizado]]=""),"Vencida","Não Vencida") -> Não Vencida | P96: =IF(TbRegistroEntradas[[#This Row],[Data da Competência]]=TbRegistroEntradas[[#This Row],[Data do Caixa Previsto]],"Vista","Prazo") -> Prazo | Q96: =IF(TbRegistroEntradas[[#This Row],[Data do Caixa Realizado]]<>"", IF(TbRegistroEntradas[[#This Row],[Data do Caixa Realizado]]>TbRegistroEntradas[[#This Row],[Data do Caixa Previsto]], TbRegistroEntradas[[#This Row],[Data do Caixa Realizado]]-TbRegistroEntradas[[#This Row],[Data do Caixa Previsto]], 0 ), IF(TODAY()>TbRegistroEntradas[[#This Row],[Data do Caixa Previsto]], TODAY()-TbRegistroEntradas[[#This Row],[Data do Caixa Previsto]], 0 ) ) -> 0
B97: 45887 | C97: 45785 | D97: 45840 | E97: Vendas de mercadorias | F97: Som e imagem | G97: NF4912 | H97: 3862 | I97: =IF(TbRegistroEntradas[[#This Row],[Data do Caixa Realizado]]="",0,MONTH(TbRegistroEntradas[[#This Row],[Data do Caixa Previsto]])) -> 7 | J97: =IF(TbRegistroEntradas[[#This Row],[Data do Caixa Realizado]]="",0,YEAR(TbRegistroEntradas[[#This Row],[Data do Caixa Realizado]])) -> 2025 | K97: =IF(TbRegistroEntradas[[#This Row],[Data da Competência]]="",0,MONTH(TbRegistroEntradas[[#This Row],[Data da Competência]])) -> 5 | L97: =IF(TbRegistroEntradas[[#This Row],[Data da Competência]]="",0,YEAR(TbRegistroEntradas[[#This Row],[Data da Competência]])) -> 2025 | M97: =IF(TbRegistroEntradas[[#This Row],[Data do Caixa Previsto]]="",0,MONTH(TbRegistroEntradas[[#This Row],[Data do Caixa Previsto]])) -> 7 | N97: =IF(TbRegistroEntradas[[#This Row],[Data do Caixa Previsto]]="",0,YEAR(TbRegistroEntradas[[#This Row],[Data do Caixa Previsto]])) -> 2025 | O97: =IF(AND(TbRegistroEntradas[[#This Row],[Data do Caixa Previsto]]<TODAY(),TbRegistroEntradas[[#This Row],[Data do Caixa Realizado]]=""),"Vencida","Não Vencida") -> Não Vencida | P97: =IF(TbRegistroEntradas[[#This Row],[Data da Competência]]=TbRegistroEntradas[[#This Row],[Data do Caixa Previsto]],"Vista","Prazo") -> Prazo | Q97: =IF(TbRegistroEntradas[[#This Row],[Data do Caixa Realizado]]<>"", IF(TbRegistroEntradas[[#This Row],[Data do Caixa Realizado]]>TbRegistroEntradas[[#This Row],[Data do Caixa Previsto]], TbRegistroEntradas[[#This Row],[Data do Caixa Realizado]]-TbRegistroEntradas[[#This Row],[Data do Caixa Previsto]], 0 ), IF(TODAY()>TbRegistroEntradas[[#This Row],[Data do Caixa Previsto]], TODAY()-TbRegistroEntradas[[#This Row],[Data do Caixa Previsto]], 0 ) ) -> 47
B98: 45836 | C98: 45788 | D98: 45836 | E98: Vendas de mercadorias | F98: Livros | G98: NF7104 | H98: 611 | I98: =IF(TbRegistroEntradas[[#This Row],[Data do Caixa Realizado]]="",0,MONTH(TbRegistroEntradas[[#This Row],[Data do Caixa Previsto]])) -> 6 | J98: =IF(TbRegistroEntradas[[#This Row],[Data do Caixa Realizado]]="",0,YEAR(TbRegistroEntradas[[#This Row],[Data do Caixa Realizado]])) -> 2025 | K98: =IF(TbRegistroEntradas[[#This Row],[Data da Competência]]="",0,MONTH(TbRegistroEntradas[[#This Row],[Data da Competência]])) -> 5 | L98: =IF(TbRegistroEntradas[[#This Row],[Data da Competência]]="",0,YEAR(TbRegistroEntradas[[#This Row],[Data da Competência]])) -> 2025 | M98: =IF(TbRegistroEntradas[[#This Row],[Data do Caixa Previsto]]="",0,MONTH(TbRegistroEntradas[[#This Row],[Data do Caixa Previsto]])) -> 6 | N98: =IF(TbRegistroEntradas[[#This Row],[Data do Caixa Previsto]]="",0,YEAR(TbRegistroEntradas[[#This Row],[Data do Caixa Previsto]])) -> 2025 | O98: =IF(AND(TbRegistroEntradas[[#This Row],[Data do Caixa Previsto]]<TODAY(),TbRegistroEntradas[[#This Row],[Data do Caixa Realizado]]=""),"Vencida","Não Vencida") -> Não Vencida | P98: =IF(TbRegistroEntradas[[#This Row],[Data da Competência]]=TbRegistroEntradas[[#This Row],[Data do Caixa Previsto]],"Vista","Prazo") -> Prazo | Q98: =IF(TbRegistroEntradas[[#This Row],[Data do Caixa Realizado]]<>"", IF(TbRegistroEntradas[[#This Row],[Data do Caixa Realizado]]>TbRegistroEntradas[[#This Row],[Data do Caixa Previsto]], TbRegistroEntradas[[#This Row],[Data do Caixa Realizado]]-TbRegistroEntradas[[#This Row],[Data do Caixa Previsto]], 0 ), IF(TODAY()>TbRegistroEntradas[[#This Row],[Data do Caixa Previsto]], TODAY()-TbRegistroEntradas[[#This Row],[Data do Caixa Previsto]], 0 ) ) -> 0
B99: 45842 | C99: 45790 | D99: 45842 | E99: Vendas de mercadorias | F99: Eletrodomésticos | G99: NF6700 | H99: 1486 | I99: =IF(TbRegistroEntradas[[#This Row],[Data do Caixa Realizado]]="",0,MONTH(TbRegistroEntradas[[#This Row],[Data do Caixa Previsto]])) -> 7 | J99: =IF(TbRegistroEntradas[[#This Row],[Data do Caixa Realizado]]="",0,YEAR(TbRegistroEntradas[[#This Row],[Data do Caixa Realizado]])) -> 2025 | K99: =IF(TbRegistroEntradas[[#This Row],[Data da Competência]]="",0,MONTH(TbRegistroEntradas[[#This Row],[Data da Competência]])) -> 5 | L99: =IF(TbRegistroEntradas[[#This Row],[Data da Competência]]="",0,YEAR(TbRegistroEntradas[[#This Row],[Data da Competência]])) -> 2025 | M99: =IF(TbRegistroEntradas[[#This Row],[Data do Caixa Previsto]]="",0,MONTH(TbRegistroEntradas[[#This Row],[Data do Caixa Previsto]])) -> 7 | N99: =IF(TbRegistroEntradas[[#This Row],[Data do Caixa Previsto]]="",0,YEAR(TbRegistroEntradas[[#This Row],[Data do Caixa Previsto]])) -> 2025 | O99: =IF(AND(TbRegistroEntradas[[#This Row],[Data do Caixa Previsto]]<TODAY(),TbRegistroEntradas[[#This Row],[Data do Caixa Realizado]]=""),"Vencida","Não Vencida") -> Não Vencida | P99: =IF(TbRegistroEntradas[[#This Row],[Data da Competência]]=TbRegistroEntradas[[#This Row],[Data do Caixa Previsto]],"Vista","Prazo") -> Prazo | Q99: =IF(TbRegistroEntradas[[#This Row],[Data do Caixa Realizado]]<>"", IF(TbRegistroEntradas[[#This Row],[Data do Caixa Realizado]]>TbRegistroEntradas[[#This Row],[Data do Caixa Previsto]], TbRegistroEntradas[[#This Row],[Data do Caixa Realizado]]-TbRegistroEntradas[[#This Row],[Data do Caixa Previsto]], 0 ), IF(TODAY()>TbRegistroEntradas[[#This Row],[Data do Caixa Previsto]], TODAY()-TbRegistroEntradas[[#This Row],[Data do Caixa Previsto]], 0 ) ) -> 0
B100: 45809 | C100: 45798 | D100: 45809 | E100: Vendas de mercadorias | F100: Móveis | G100: NF7947 | H100: 4850 | I100: =IF(TbRegistroEntradas[[#This Row],[Data do Caixa Realizado]]="",0,MONTH(TbRegistroEntradas[[#This Row],[Data do Caixa Previsto]])) -> 6 | J100: =IF(TbRegistroEntradas[[#This Row],[Data do Caixa Realizado]]="",0,YEAR(TbRegistroEntradas[[#This Row],[Data do Caixa Realizado]])) -> 2025 | K100: =IF(TbRegistroEntradas[[#This Row],[Data da Competência]]="",0,MONTH(TbRegistroEntradas[[#This Row],[Data da Competência]])) -> 5 | L100: =IF(TbRegistroEntradas[[#This Row],[Data da Competência]]="",0,YEAR(TbRegistroEntradas[[#This Row],[Data da Competência]])) -> 2025 | M100: =IF(TbRegistroEntradas[[#This Row],[Data do Caixa Previsto]]="",0,MONTH(TbRegistroEntradas[[#This Row],[Data do Caixa Previsto]])) -> 6 | N100: =IF(TbRegistroEntradas[[#This Row],[Data do Caixa Previsto]]="",0,YEAR(TbRegistroEntradas[[#This Row],[Data do Caixa Previsto]])) -> 2025 | O100: =IF(AND(TbRegistroEntradas[[#This Row],[Data do Caixa Previsto]]<TODAY(),TbRegistroEntradas[[#This Row],[Data do Caixa Realizado]]=""),"Vencida","Não Vencida") -> Não Vencida | P100: =IF(TbRegistroEntradas[[#This Row],[Data da Competência]]=TbRegistroEntradas[[#This Row],[Data do Caixa Previsto]],"Vista","Prazo") -> Prazo | Q100: =IF(TbRegistroEntradas[[#This Row],[Data do Caixa Realizado]]<>"", IF(TbRegistroEntradas[[#This Row],[Data do Caixa Realizado]]>TbRegistroEntradas[[#This Row],[Data do Caixa Previsto]], TbRegistroEntradas[[#This Row],[Data do Caixa Realizado]]-TbRegistroEntradas[[#This Row],[Data do Caixa Previsto]], 0 ), IF(TODAY()>TbRegistroEntradas[[#This Row],[Data do Caixa Previsto]], TODAY()-TbRegistroEntradas[[#This Row],[Data do Caixa Previsto]], 0 ) ) -> 0
C101: 45801 | D101: 45832 | E101: Vendas de mercadorias | F101: Eletrodomésticos | G101: NF7741 | H101: 3878 | I101: =IF(TbRegistroEntradas[[#This Row],[Data do Caixa Realizado]]="",0,MONTH(TbRegistroEntradas[[#This Row],[Data do Caixa Previsto]])) -> 0 | J101: =IF(TbRegistroEntradas[[#This Row],[Data do Caixa Realizado]]="",0,YEAR(TbRegistroEntradas[[#This Row],[Data do Caixa Realizado]])) -> 0 | K101: =IF(TbRegistroEntradas[[#This Row],[Data da Competência]]="",0,MONTH(TbRegistroEntradas[[#This Row],[Data da Competência]])) -> 5 | L101: =IF(TbRegistroEntradas[[#This Row],[Data da Competência]]="",0,YEAR(TbRegistroEntradas[[#This Row],[Data da Competência]])) -> 2025 | M101: =IF(TbRegistroEntradas[[#This Row],[Data do Caixa Previsto]]="",0,MONTH(TbRegistroEntradas[[#This Row],[Data do Caixa Previsto]])) -> 6 | N101: =IF(TbRegistroEntradas[[#This Row],[Data do Caixa Previsto]]="",0,YEAR(TbRegistroEntradas[[#This Row],[Data do Caixa Previsto]])) -> 2025 | O101: =IF(AND(TbRegistroEntradas[[#This Row],[Data do Caixa Previsto]]<TODAY(),TbRegistroEntradas[[#This Row],[Data do Caixa Realizado]]=""),"Vencida","Não Vencida") -> Vencida | P101: =IF(TbRegistroEntradas[[#This Row],[Data da Competência]]=TbRegistroEntradas[[#This Row],[Data do Caixa Previsto]],"Vista","Prazo") -> Prazo | Q101: =IF(TbRegistroEntradas[[#This Row],[Data do Caixa Realizado]]<>"", IF(TbRegistroEntradas[[#This Row],[Data do Caixa Realizado]]>TbRegistroEntradas[[#This Row],[Data do Caixa Previsto]], TbRegistroEntradas[[#This Row],[Data do Caixa Realizado]]-TbRegistroEntradas[[#This Row],[Data do Caixa Previsto]], 0 ), IF(TODAY()>TbRegistroEntradas[[#This Row],[Data do Caixa Previsto]], TODAY()-TbRegistroEntradas[[#This Row],[Data do Caixa Previsto]], 0 ) ) -> 377
B102: 45832 | C102: 45806 | D102: 45832 | E102: Vendas de mercadorias | F102: Eletrodomésticos | G102: NF3255 | H102: 976 | I102: =IF(TbRegistroEntradas[[#This Row],[Data do Caixa Realizado]]="",0,MONTH(TbRegistroEntradas[[#This Row],[Data do Caixa Previsto]])) -> 6 | J102: =IF(TbRegistroEntradas[[#This Row],[Data do Caixa Realizado]]="",0,YEAR(TbRegistroEntradas[[#This Row],[Data do Caixa Realizado]])) -> 2025 | K102: =IF(TbRegistroEntradas[[#This Row],[Data da Competência]]="",0,MONTH(TbRegistroEntradas[[#This Row],[Data da Competência]])) -> 5 | L102: =IF(TbRegistroEntradas[[#This Row],[Data da Competência]]="",0,YEAR(TbRegistroEntradas[[#This Row],[Data da Competência]])) -> 2025 | M102: =IF(TbRegistroEntradas[[#This Row],[Data do Caixa Previsto]]="",0,MONTH(TbRegistroEntradas[[#This Row],[Data do Caixa Previsto]])) -> 6 | N102: =IF(TbRegistroEntradas[[#This Row],[Data do Caixa Previsto]]="",0,YEAR(TbRegistroEntradas[[#This Row],[Data do Caixa Previsto]])) -> 2025 | O102: =IF(AND(TbRegistroEntradas[[#This Row],[Data do Caixa Previsto]]<TODAY(),TbRegistroEntradas[[#This Row],[Data do Caixa Realizado]]=""),"Vencida","Não Vencida") -> Não Vencida | P102: =IF(TbRegistroEntradas[[#This Row],[Data da Competência]]=TbRegistroEntradas[[#This Row],[Data do Caixa Previsto]],"Vista","Prazo") -> Prazo | Q102: =IF(TbRegistroEntradas[[#This Row],[Data do Caixa Realizado]]<>"", IF(TbRegistroEntradas[[#This Row],[Data do Caixa Realizado]]>TbRegistroEntradas[[#This Row],[Data do Caixa Previsto]], TbRegistroEntradas[[#This Row],[Data do Caixa Realizado]]-TbRegistroEntradas[[#This Row],[Data do Caixa Previsto]], 0 ), IF(TODAY()>TbRegistroEntradas[[#This Row],[Data do Caixa Previsto]], TODAY()-TbRegistroEntradas[[#This Row],[Data do Caixa Previsto]], 0 ) ) -> 0
B103: 45822 | C103: 45807 | D103: 45822 | E103: Vendas de mercadorias | F103: Som e imagem | G103: NF7106 | H103: 3346 | I103: =IF(TbRegistroEntradas[[#This Row],[Data do Caixa Realizado]]="",0,MONTH(TbRegistroEntradas[[#This Row],[Data do Caixa Previsto]])) -> 6 | J103: =IF(TbRegistroEntradas[[#This Row],[Data do Caixa Realizado]]="",0,YEAR(TbRegistroEntradas[[#This Row],[Data do Caixa Realizado]])) -> 2025 | K103: =IF(TbRegistroEntradas[[#This Row],[Data da Competência]]="",0,MONTH(TbRegistroEntradas[[#This Row],[Data da Competência]])) -> 5 | L103: =IF(TbRegistroEntradas[[#This Row],[Data da Competência]]="",0,YEAR(TbRegistroEntradas[[#This Row],[Data da Competência]])) -> 2025 | M103: =IF(TbRegistroEntradas[[#This Row],[Data do Caixa Previsto]]="",0,MONTH(TbRegistroEntradas[[#This Row],[Data do Caixa Previsto]])) -> 6 | N103: =IF(TbRegistroEntradas[[#This Row],[Data do Caixa Previsto]]="",0,YEAR(TbRegistroEntradas[[#This Row],[Data do Caixa Previsto]])) -> 2025 | O103: =IF(AND(TbRegistroEntradas[[#This Row],[Data do Caixa Previsto]]<TODAY(),TbRegistroEntradas[[#This Row],[Data do Caixa Realizado]]=""),"Vencida","Não Vencida") -> Não Vencida | P103: =IF(TbRegistroEntradas[[#This Row],[Data da Competência]]=TbRegistroEntradas[[#This Row],[Data do Caixa Previsto]],"Vista","Prazo") -> Prazo | Q103: =IF(TbRegistroEntradas[[#This Row],[Data do Caixa Realizado]]<>"", IF(TbRegistroEntradas[[#This Row],[Data do Caixa Realizado]]>TbRegistroEntradas[[#This Row],[Data do Caixa Previsto]], TbRegistroEntradas[[#This Row],[Data do Caixa Realizado]]-TbRegistroEntradas[[#This Row],[Data do Caixa Previsto]], 0 ), IF(TODAY()>TbRegistroEntradas[[#This Row],[Data do Caixa Previsto]], TODAY()-TbRegistroEntradas[[#This Row],[Data do Caixa Previsto]], 0 ) ) -> 0
B104: 45870 | C104: 45811 | D104: 45870 | E104: Vendas de mercadorias | F104: Livros | G104: NF1835 | H104: 443 | I104: =IF(TbRegistroEntradas[[#This Row],[Data do Caixa Realizado]]="",0,MONTH(TbRegistroEntradas[[#This Row],[Data do Caixa Previsto]])) -> 8 | J104: =IF(TbRegistroEntradas[[#This Row],[Data do Caixa Realizado]]="",0,YEAR(TbRegistroEntradas[[#This Row],[Data do Caixa Realizado]])) -> 2025 | K104: =IF(TbRegistroEntradas[[#This Row],[Data da Competência]]="",0,MONTH(TbRegistroEntradas[[#This Row],[Data da Competência]])) -> 6 | L104: =IF(TbRegistroEntradas[[#This Row],[Data da Competência]]="",0,YEAR(TbRegistroEntradas[[#This Row],[Data da Competência]])) -> 2025 | M104: =IF(TbRegistroEntradas[[#This Row],[Data do Caixa Previsto]]="",0,MONTH(TbRegistroEntradas[[#This Row],[Data do Caixa Previsto]])) -> 8 | N104: =IF(TbRegistroEntradas[[#This Row],[Data do Caixa Previsto]]="",0,YEAR(TbRegistroEntradas[[#This Row],[Data do Caixa Previsto]])) -> 2025 | O104: =IF(AND(TbRegistroEntradas[[#This Row],[Data do Caixa Previsto]]<TODAY(),TbRegistroEntradas[[#This Row],[Data do Caixa Realizado]]=""),"Vencida","Não Vencida") -> Não Vencida | P104: =IF(TbRegistroEntradas[[#This Row],[Data da Competência]]=TbRegistroEntradas[[#This Row],[Data do Caixa Previsto]],"Vista","Prazo") -> Prazo | Q104: =IF(TbRegistroEntradas[[#This Row],[Data do Caixa Realizado]]<>"", IF(TbRegistroEntradas[[#This Row],[Data do Caixa Realizado]]>TbRegistroEntradas[[#This Row],[Data do Caixa Previsto]], TbRegistroEntradas[[#This Row],[Data do Caixa Realizado]]-TbRegistroEntradas[[#This Row],[Data do Caixa Previsto]], 0 ), IF(TODAY()>TbRegistroEntradas[[#This Row],[Data do Caixa Previsto]], TODAY()-TbRegistroEntradas[[#This Row],[Data do Caixa Previsto]], 0 ) ) -> 0
B105: 45866 | C105: 45812 | D105: 45866 | E105: Vendas de mercadorias | F105: Livros | G105: NF7322 | H105: 2781 | I105: =IF(TbRegistroEntradas[[#This Row],[Data do Caixa Realizado]]="",0,MONTH(TbRegistroEntradas[[#This Row],[Data do Caixa Previsto]])) -> 7 | J105: =IF(TbRegistroEntradas[[#This Row],[Data do Caixa Realizado]]="",0,YEAR(TbRegistroEntradas[[#This Row],[Data do Caixa Realizado]])) -> 2025 | K105: =IF(TbRegistroEntradas[[#This Row],[Data da Competência]]="",0,MONTH(TbRegistroEntradas[[#This Row],[Data da Competência]])) -> 6 | L105: =IF(TbRegistroEntradas[[#This Row],[Data da Competência]]="",0,YEAR(TbRegistroEntradas[[#This Row],[Data da Competência]])) -> 2025 | M105: =IF(TbRegistroEntradas[[#This Row],[Data do Caixa Previsto]]="",0,MONTH(TbRegistroEntradas[[#This Row],[Data do Caixa Previsto]])) -> 7 | N105: =IF(TbRegistroEntradas[[#This Row],[Data do Caixa Previsto]]="",0,YEAR(TbRegistroEntradas[[#This Row],[Data do Caixa Previsto]])) -> 2025 | O105: =IF(AND(TbRegistroEntradas[[#This Row],[Data do Caixa Previsto]]<TODAY(),TbRegistroEntradas[[#This Row],[Data do Caixa Realizado]]=""),"Vencida","Não Vencida") -> Não Vencida | P105: =IF(TbRegistroEntradas[[#This Row],[Data da Competência]]=TbRegistroEntradas[[#This Row],[Data do Caixa Previsto]],"Vista","Prazo") -> Prazo | Q105: =IF(TbRegistroEntradas[[#This Row],[Data do Caixa Realizado]]<>"", IF(TbRegistroEntradas[[#This Row],[Data do Caixa Realizado]]>TbRegistroEntradas[[#This Row],[Data do Caixa Previsto]], TbRegistroEntradas[[#This Row],[Data do Caixa Realizado]]-TbRegistroEntradas[[#This Row],[Data do Caixa Previsto]], 0 ), IF(TODAY()>TbRegistroEntradas[[#This Row],[Data do Caixa Previsto]], TODAY()-TbRegistroEntradas[[#This Row],[Data do Caixa Previsto]], 0 ) ) -> 0
B106: 45824 | C106: 45813 | D106: 45824 | E106: Vendas de mercadorias | F106: Eletrodomésticos | G106: NF3899 | H106: 1875 | I106: =IF(TbRegistroEntradas[[#This Row],[Data do Caixa Realizado]]="",0,MONTH(TbRegistroEntradas[[#This Row],[Data do Caixa Previsto]])) -> 6 | J106: =IF(TbRegistroEntradas[[#This Row],[Data do Caixa Realizado]]="",0,YEAR(TbRegistroEntradas[[#This Row],[Data do Caixa Realizado]])) -> 2025 | K106: =IF(TbRegistroEntradas[[#This Row],[Data da Competência]]="",0,MONTH(TbRegistroEntradas[[#This Row],[Data da Competência]])) -> 6 | L106: =IF(TbRegistroEntradas[[#This Row],[Data da Competência]]="",0,YEAR(TbRegistroEntradas[[#This Row],[Data da Competência]])) -> 2025 | M106: =IF(TbRegistroEntradas[[#This Row],[Data do Caixa Previsto]]="",0,MONTH(TbRegistroEntradas[[#This Row],[Data do Caixa Previsto]])) -> 6 | N106: =IF(TbRegistroEntradas[[#This Row],[Data do Caixa Previsto]]="",0,YEAR(TbRegistroEntradas[[#This Row],[Data do Caixa Previsto]])) -> 2025 | O106: =IF(AND(TbRegistroEntradas[[#This Row],[Data do Caixa Previsto]]<TODAY(),TbRegistroEntradas[[#This Row],[Data do Caixa Realizado]]=""),"Vencida","Não Vencida") -> Não Vencida | P106: =IF(TbRegistroEntradas[[#This Row],[Data da Competência]]=TbRegistroEntradas[[#This Row],[Data do Caixa Previsto]],"Vista","Prazo") -> Prazo | Q106: =IF(TbRegistroEntradas[[#This Row],[Data do Caixa Realizado]]<>"", IF(TbRegistroEntradas[[#This Row],[Data do Caixa Realizado]]>TbRegistroEntradas[[#This Row],[Data do Caixa Previsto]], TbRegistroEntradas[[#This Row],[Data do Caixa Realizado]]-TbRegistroEntradas[[#This Row],[Data do Caixa Previsto]], 0 ), IF(TODAY()>TbRegistroEntradas[[#This Row],[Data do Caixa Previsto]], TODAY()-TbRegistroEntradas[[#This Row],[Data do Caixa Previsto]], 0 ) ) -> 0
B107: 45852 | C107: 45816 | D107: 45852 | E107: Vendas de mercadorias | F107: Móveis | G107: NF5496 | H107: 3134 | I107: =IF(TbRegistroEntradas[[#This Row],[Data do Caixa Realizado]]="",0,MONTH(TbRegistroEntradas[[#This Row],[Data do Caixa Previsto]])) -> 7 | J107: =IF(TbRegistroEntradas[[#This Row],[Data do Caixa Realizado]]="",0,YEAR(TbRegistroEntradas[[#This Row],[Data do Caixa Realizado]])) -> 2025 | K107: =IF(TbRegistroEntradas[[#This Row],[Data da Competência]]="",0,MONTH(TbRegistroEntradas[[#This Row],[Data da Competência]])) -> 6 | L107: =IF(TbRegistroEntradas[[#This Row],[Data da Competência]]="",0,YEAR(TbRegistroEntradas[[#This Row],[Data da Competência]])) -> 2025 | M107: =IF(TbRegistroEntradas[[#This Row],[Data do Caixa Previsto]]="",0,MONTH(TbRegistroEntradas[[#This Row],[Data do Caixa Previsto]])) -> 7 | N107: =IF(TbRegistroEntradas[[#This Row],[Data do Caixa Previsto]]="",0,YEAR(TbRegistroEntradas[[#This Row],[Data do Caixa Previsto]])) -> 2025 | O107: =IF(AND(TbRegistroEntradas[[#This Row],[Data do Caixa Previsto]]<TODAY(),TbRegistroEntradas[[#This Row],[Data do Caixa Realizado]]=""),"Vencida","Não Vencida") -> Não Vencida | P107: =IF(TbRegistroEntradas[[#This Row],[Data da Competência]]=TbRegistroEntradas[[#This Row],[Data do Caixa Previsto]],"Vista","Prazo") -> Prazo | Q107: =IF(TbRegistroEntradas[[#This Row],[Data do Caixa Realizado]]<>"", IF(TbRegistroEntradas[[#This Row],[Data do Caixa Realizado]]>TbRegistroEntradas[[#This Row],[Data do Caixa Previsto]], TbRegistroEntradas[[#This Row],[Data do Caixa Realizado]]-TbRegistroEntradas[[#This Row],[Data do Caixa Previsto]], 0 ), IF(TODAY()>TbRegistroEntradas[[#This Row],[Data do Caixa Previsto]], TODAY()-TbRegistroEntradas[[#This Row],[Data do Caixa Previsto]], 0 ) ) -> 0
B108: 45833 | C108: 45818 | D108: 45833 | E108: Vendas de mercadorias | F108: Informática | G108: NF4824 | H108: 2114 | I108: =IF(TbRegistroEntradas[[#This Row],[Data do Caixa Realizado]]="",0,MONTH(TbRegistroEntradas[[#This Row],[Data do Caixa Previsto]])) -> 6 | J108: =IF(TbRegistroEntradas[[#This Row],[Data do Caixa Realizado]]="",0,YEAR(TbRegistroEntradas[[#This Row],[Data do Caixa Realizado]])) -> 2025 | K108: =IF(TbRegistroEntradas[[#This Row],[Data da Competência]]="",0,MONTH(TbRegistroEntradas[[#This Row],[Data da Competência]])) -> 6 | L108: =IF(TbRegistroEntradas[[#This Row],[Data da Competência]]="",0,YEAR(TbRegistroEntradas[[#This Row],[Data da Competência]])) -> 2025 | M108: =IF(TbRegistroEntradas[[#This Row],[Data do Caixa Previsto]]="",0,MONTH(TbRegistroEntradas[[#This Row],[Data do Caixa Previsto]])) -> 6 | N108: =IF(TbRegistroEntradas[[#This Row],[Data do Caixa Previsto]]="",0,YEAR(TbRegistroEntradas[[#This Row],[Data do Caixa Previsto]])) -> 2025 | O108: =IF(AND(TbRegistroEntradas[[#This Row],[Data do Caixa Previsto]]<TODAY(),TbRegistroEntradas[[#This Row],[Data do Caixa Realizado]]=""),"Vencida","Não Vencida") -> Não Vencida | P108: =IF(TbRegistroEntradas[[#This Row],[Data da Competência]]=TbRegistroEntradas[[#This Row],[Data do Caixa Previsto]],"Vista","Prazo") -> Prazo | Q108: =IF(TbRegistroEntradas[[#This Row],[Data do Caixa Realizado]]<>"", IF(TbRegistroEntradas[[#This Row],[Data do Caixa Realizado]]>TbRegistroEntradas[[#This Row],[Data do Caixa Previsto]], TbRegistroEntradas[[#This Row],[Data do Caixa Realizado]]-TbRegistroEntradas[[#This Row],[Data do Caixa Previsto]], 0 ), IF(TODAY()>TbRegistroEntradas[[#This Row],[Data do Caixa Previsto]], TODAY()-TbRegistroEntradas[[#This Row],[Data do Caixa Previsto]], 0 ) ) -> 0
B109: 45877 | C109: 45821 | D109: 45877 | E109: Vendas de mercadorias | F109: Eletrodomésticos | G109: NF2022 | H109: 4961 | I109: =IF(TbRegistroEntradas[[#This Row],[Data do Caixa Realizado]]="",0,MONTH(TbRegistroEntradas[[#This Row],[Data do Caixa Previsto]])) -> 8 | J109: =IF(TbRegistroEntradas[[#This Row],[Data do Caixa Realizado]]="",0,YEAR(TbRegistroEntradas[[#This Row],[Data do Caixa Realizado]])) -> 2025 | K109: =IF(TbRegistroEntradas[[#This Row],[Data da Competência]]="",0,MONTH(TbRegistroEntradas[[#This Row],[Data da Competência]])) -> 6 | L109: =IF(TbRegistroEntradas[[#This Row],[Data da Competência]]="",0,YEAR(TbRegistroEntradas[[#This Row],[Data da Competência]])) -> 2025 | M109: =IF(TbRegistroEntradas[[#This Row],[Data do Caixa Previsto]]="",0,MONTH(TbRegistroEntradas[[#This Row],[Data do Caixa Previsto]])) -> 8 | N109: =IF(TbRegistroEntradas[[#This Row],[Data do Caixa Previsto]]="",0,YEAR(TbRegistroEntradas[[#This Row],[Data do Caixa Previsto]])) -> 2025 | O109: =IF(AND(TbRegistroEntradas[[#This Row],[Data do Caixa Previsto]]<TODAY(),TbRegistroEntradas[[#This Row],[Data do Caixa Realizado]]=""),"Vencida","Não Vencida") -> Não Vencida | P109: =IF(TbRegistroEntradas[[#This Row],[Data da Competência]]=TbRegistroEntradas[[#This Row],[Data do Caixa Previsto]],"Vista","Prazo") -> Prazo | Q109: =IF(TbRegistroEntradas[[#This Row],[Data do Caixa Realizado]]<>"", IF(TbRegistroEntradas[[#This Row],[Data do Caixa Realizado]]>TbRegistroEntradas[[#This Row],[Data do Caixa Previsto]], TbRegistroEntradas[[#This Row],[Data do Caixa Realizado]]-TbRegistroEntradas[[#This Row],[Data do Caixa Previsto]], 0 ), IF(TODAY()>TbRegistroEntradas[[#This Row],[Data do Caixa Previsto]], TODAY()-TbRegistroEntradas[[#This Row],[Data do Caixa Previsto]], 0 ) ) -> 0
B110: 45860 | C110: 45822 | D110: 45860 | E110: Vendas de mercadorias | F110: Móveis | G110: NF8075 | H110: 909 | I110: =IF(TbRegistroEntradas[[#This Row],[Data do Caixa Realizado]]="",0,MONTH(TbRegistroEntradas[[#This Row],[Data do Caixa Previsto]])) -> 7 | J110: =IF(TbRegistroEntradas[[#This Row],[Data do Caixa Realizado]]="",0,YEAR(TbRegistroEntradas[[#This Row],[Data do Caixa Realizado]])) -> 2025 | K110: =IF(TbRegistroEntradas[[#This Row],[Data da Competência]]="",0,MONTH(TbRegistroEntradas[[#This Row],[Data da Competência]])) -> 6 | L110: =IF(TbRegistroEntradas[[#This Row],[Data da Competência]]="",0,YEAR(TbRegistroEntradas[[#This Row],[Data da Competência]])) -> 2025 | M110: =IF(TbRegistroEntradas[[#This Row],[Data do Caixa Previsto]]="",0,MONTH(TbRegistroEntradas[[#This Row],[Data do Caixa Previsto]])) -> 7 | N110: =IF(TbRegistroEntradas[[#This Row],[Data do Caixa Previsto]]="",0,YEAR(TbRegistroEntradas[[#This Row],[Data do Caixa Previsto]])) -> 2025 | O110: =IF(AND(TbRegistroEntradas[[#This Row],[Data do Caixa Previsto]]<TODAY(),TbRegistroEntradas[[#This Row],[Data do Caixa Realizado]]=""),"Vencida","Não Vencida") -> Não Vencida | P110: =IF(TbRegistroEntradas[[#This Row],[Data da Competência]]=TbRegistroEntradas[[#This Row],[Data do Caixa Previsto]],"Vista","Prazo") -> Prazo | Q110: =IF(TbRegistroEntradas[[#This Row],[Data do Caixa Realizado]]<>"", IF(TbRegistroEntradas[[#This Row],[Data do Caixa Realizado]]>TbRegistroEntradas[[#This Row],[Data do Caixa Previsto]], TbRegistroEntradas[[#This Row],[Data do Caixa Realizado]]-TbRegistroEntradas[[#This Row],[Data do Caixa Previsto]], 0 ), IF(TODAY()>TbRegistroEntradas[[#This Row],[Data do Caixa Previsto]], TODAY()-TbRegistroEntradas[[#This Row],[Data do Caixa Previsto]], 0 ) ) -> 0
B111: 45850 | C111: 45823 | D111: 45850 | E111: Vendas de mercadorias | F111: Móveis | G111: NF1137 | H111: 2197 | I111: =IF(TbRegistroEntradas[[#This Row],[Data do Caixa Realizado]]="",0,MONTH(TbRegistroEntradas[[#This Row],[Data do Caixa Previsto]])) -> 7 | J111: =IF(TbRegistroEntradas[[#This Row],[Data do Caixa Realizado]]="",0,YEAR(TbRegistroEntradas[[#This Row],[Data do Caixa Realizado]])) -> 2025 | K111: =IF(TbRegistroEntradas[[#This Row],[Data da Competência]]="",0,MONTH(TbRegistroEntradas[[#This Row],[Data da Competência]])) -> 6 | L111: =IF(TbRegistroEntradas[[#This Row],[Data da Competência]]="",0,YEAR(TbRegistroEntradas[[#This Row],[Data da Competência]])) -> 2025 | M111: =IF(TbRegistroEntradas[[#This Row],[Data do Caixa Previsto]]="",0,MONTH(TbRegistroEntradas[[#This Row],[Data do Caixa Previsto]])) -> 7 | N111: =IF(TbRegistroEntradas[[#This Row],[Data do Caixa Previsto]]="",0,YEAR(TbRegistroEntradas[[#This Row],[Data do Caixa Previsto]])) -> 2025 | O111: =IF(AND(TbRegistroEntradas[[#This Row],[Data do Caixa Previsto]]<TODAY(),TbRegistroEntradas[[#This Row],[Data do Caixa Realizado]]=""),"Vencida","Não Vencida") -> Não Vencida | P111: =IF(TbRegistroEntradas[[#This Row],[Data da Competência]]=TbRegistroEntradas[[#This Row],[Data do Caixa Previsto]],"Vista","Prazo") -> Prazo | Q111: =IF(TbRegistroEntradas[[#This Row],[Data do Caixa Realizado]]<>"", IF(TbRegistroEntradas[[#This Row],[Data do Caixa Realizado]]>TbRegistroEntradas[[#This Row],[Data do Caixa Previsto]], TbRegistroEntradas[[#This Row],[Data do Caixa Realizado]]-TbRegistroEntradas[[#This Row],[Data do Caixa Previsto]], 0 ), IF(TODAY()>TbRegistroEntradas[[#This Row],[Data do Caixa Previsto]], TODAY()-TbRegistroEntradas[[#This Row],[Data do Caixa Previsto]], 0 ) ) -> 0
B112: 45904 | C112: 45825 | D112: 45867 | E112: Vendas de mercadorias | F112: Som e imagem | G112: NF3353 | H112: 3045 | I112: =IF(TbRegistroEntradas[[#This Row],[Data do Caixa Realizado]]="",0,MONTH(TbRegistroEntradas[[#This Row],[Data do Caixa Previsto]])) -> 7 | J112: =IF(TbRegistroEntradas[[#This Row],[Data do Caixa Realizado]]="",0,YEAR(TbRegistroEntradas[[#This Row],[Data do Caixa Realizado]])) -> 2025 | K112: =IF(TbRegistroEntradas[[#This Row],[Data da Competência]]="",0,MONTH(TbRegistroEntradas[[#This Row],[Data da Competência]])) -> 6 | L112: =IF(TbRegistroEntradas[[#This Row],[Data da Competência]]="",0,YEAR(TbRegistroEntradas[[#This Row],[Data da Competência]])) -> 2025 | M112: =IF(TbRegistroEntradas[[#This Row],[Data do Caixa Previsto]]="",0,MONTH(TbRegistroEntradas[[#This Row],[Data do Caixa Previsto]])) -> 7 | N112: =IF(TbRegistroEntradas[[#This Row],[Data do Caixa Previsto]]="",0,YEAR(TbRegistroEntradas[[#This Row],[Data do Caixa Previsto]])) -> 2025 | O112: =IF(AND(TbRegistroEntradas[[#This Row],[Data do Caixa Previsto]]<TODAY(),TbRegistroEntradas[[#This Row],[Data do Caixa Realizado]]=""),"Vencida","Não Vencida") -> Não Vencida | P112: =IF(TbRegistroEntradas[[#This Row],[Data da Competência]]=TbRegistroEntradas[[#This Row],[Data do Caixa Previsto]],"Vista","Prazo") -> Prazo | Q112: =IF(TbRegistroEntradas[[#This Row],[Data do Caixa Realizado]]<>"", IF(TbRegistroEntradas[[#This Row],[Data do Caixa Realizado]]>TbRegistroEntradas[[#This Row],[Data do Caixa Previsto]], TbRegistroEntradas[[#This Row],[Data do Caixa Realizado]]-TbRegistroEntradas[[#This Row],[Data do Caixa Previsto]], 0 ), IF(TODAY()>TbRegistroEntradas[[#This Row],[Data do Caixa Previsto]], TODAY()-TbRegistroEntradas[[#This Row],[Data do Caixa Previsto]], 0 ) ) -> 37
B113: 45885 | C113: 45829 | D113: 45866 | E113: Vendas de mercadorias | F113: Som e imagem | G113: NF5074 | H113: 460 | I113: =IF(TbRegistroEntradas[[#This Row],[Data do Caixa Realizado]]="",0,MONTH(TbRegistroEntradas[[#This Row],[Data do Caixa Previsto]])) -> 7 | J113: =IF(TbRegistroEntradas[[#This Row],[Data do Caixa Realizado]]="",0,YEAR(TbRegistroEntradas[[#This Row],[Data do Caixa Realizado]])) -> 2025 | K113: =IF(TbRegistroEntradas[[#This Row],[Data da Competência]]="",0,MONTH(TbRegistroEntradas[[#This Row],[Data da Competência]])) -> 6 | L113: =IF(TbRegistroEntradas[[#This Row],[Data da Competência]]="",0,YEAR(TbRegistroEntradas[[#This Row],[Data da Competência]])) -> 2025 | M113: =IF(TbRegistroEntradas[[#This Row],[Data do Caixa Previsto]]="",0,MONTH(TbRegistroEntradas[[#This Row],[Data do Caixa Previsto]])) -> 7 | N113: =IF(TbRegistroEntradas[[#This Row],[Data do Caixa Previsto]]="",0,YEAR(TbRegistroEntradas[[#This Row],[Data do Caixa Previsto]])) -> 2025 | O113: =IF(AND(TbRegistroEntradas[[#This Row],[Data do Caixa Previsto]]<TODAY(),TbRegistroEntradas[[#This Row],[Data do Caixa Realizado]]=""),"Vencida","Não Vencida") -> Não Vencida | P113: =IF(TbRegistroEntradas[[#This Row],[Data da Competência]]=TbRegistroEntradas[[#This Row],[Data do Caixa Previsto]],"Vista","Prazo") -> Prazo | Q113: =IF(TbRegistroEntradas[[#This Row],[Data do Caixa Realizado]]<>"", IF(TbRegistroEntradas[[#This Row],[Data do Caixa Realizado]]>TbRegistroEntradas[[#This Row],[Data do Caixa Previsto]], TbRegistroEntradas[[#This Row],[Data do Caixa Realizado]]-TbRegistroEntradas[[#This Row],[Data do Caixa Previsto]], 0 ), IF(TODAY()>TbRegistroEntradas[[#This Row],[Data do Caixa Previsto]], TODAY()-TbRegistroEntradas[[#This Row],[Data do Caixa Previsto]], 0 ) ) -> 19
C114: 45832 | D114: 45870 | E114: Vendas de mercadorias | F114: Som e imagem | G114: NF1725 | H114: 770 | I114: =IF(TbRegistroEntradas[[#This Row],[Data do Caixa Realizado]]="",0,MONTH(TbRegistroEntradas[[#This Row],[Data do Caixa Previsto]])) -> 0 | J114: =IF(TbRegistroEntradas[[#This Row],[Data do Caixa Realizado]]="",0,YEAR(TbRegistroEntradas[[#This Row],[Data do Caixa Realizado]])) -> 0 | K114: =IF(TbRegistroEntradas[[#This Row],[Data da Competência]]="",0,MONTH(TbRegistroEntradas[[#This Row],[Data da Competência]])) -> 6 | L114: =IF(TbRegistroEntradas[[#This Row],[Data da Competência]]="",0,YEAR(TbRegistroEntradas[[#This Row],[Data da Competência]])) -> 2025 | M114: =IF(TbRegistroEntradas[[#This Row],[Data do Caixa Previsto]]="",0,MONTH(TbRegistroEntradas[[#This Row],[Data do Caixa Previsto]])) -> 8 | N114: =IF(TbRegistroEntradas[[#This Row],[Data do Caixa Previsto]]="",0,YEAR(TbRegistroEntradas[[#This Row],[Data do Caixa Previsto]])) -> 2025 | O114: =IF(AND(TbRegistroEntradas[[#This Row],[Data do Caixa Previsto]]<TODAY(),TbRegistroEntradas[[#This Row],[Data do Caixa Realizado]]=""),"Vencida","Não Vencida") -> Vencida | P114: =IF(TbRegistroEntradas[[#This Row],[Data da Competência]]=TbRegistroEntradas[[#This Row],[Data do Caixa Previsto]],"Vista","Prazo") -> Prazo | Q114: =IF(TbRegistroEntradas[[#This Row],[Data do Caixa Realizado]]<>"", IF(TbRegistroEntradas[[#This Row],[Data do Caixa Realizado]]>TbRegistroEntradas[[#This Row],[Data do Caixa Previsto]], TbRegistroEntradas[[#This Row],[Data do Caixa Realizado]]-TbRegistroEntradas[[#This Row],[Data do Caixa Previsto]], 0 ), IF(TODAY()>TbRegistroEntradas[[#This Row],[Data do Caixa Previsto]], TODAY()-TbRegistroEntradas[[#This Row],[Data do Caixa Previsto]], 0 ) ) -> 339
B115: 45878 | C115: 45833 | D115: 45874 | E115: Vendas de mercadorias | F115: Móveis | G115: NF5560 | H115: 3646 | I115: =IF(TbRegistroEntradas[[#This Row],[Data do Caixa Realizado]]="",0,MONTH(TbRegistroEntradas[[#This Row],[Data do Caixa Previsto]])) -> 8 | J115: =IF(TbRegistroEntradas[[#This Row],[Data do Caixa Realizado]]="",0,YEAR(TbRegistroEntradas[[#This Row],[Data do Caixa Realizado]])) -> 2025 | K115: =IF(TbRegistroEntradas[[#This Row],[Data da Competência]]="",0,MONTH(TbRegistroEntradas[[#This Row],[Data da Competência]])) -> 6 | L115: =IF(TbRegistroEntradas[[#This Row],[Data da Competência]]="",0,YEAR(TbRegistroEntradas[[#This Row],[Data da Competência]])) -> 2025 | M115: =IF(TbRegistroEntradas[[#This Row],[Data do Caixa Previsto]]="",0,MONTH(TbRegistroEntradas[[#This Row],[Data do Caixa Previsto]])) -> 8 | N115: =IF(TbRegistroEntradas[[#This Row],[Data do Caixa Previsto]]="",0,YEAR(TbRegistroEntradas[[#This Row],[Data do Caixa Previsto]])) -> 2025 | O115: =IF(AND(TbRegistroEntradas[[#This Row],[Data do Caixa Previsto]]<TODAY(),TbRegistroEntradas[[#This Row],[Data do Caixa Realizado]]=""),"Vencida","Não Vencida") -> Não Vencida | P115: =IF(TbRegistroEntradas[[#This Row],[Data da Competência]]=TbRegistroEntradas[[#This Row],[Data do Caixa Previsto]],"Vista","Prazo") -> Prazo | Q115: =IF(TbRegistroEntradas[[#This Row],[Data do Caixa Realizado]]<>"", IF(TbRegistroEntradas[[#This Row],[Data do Caixa Realizado]]>TbRegistroEntradas[[#This Row],[Data do Caixa Previsto]], TbRegistroEntradas[[#This Row],[Data do Caixa Realizado]]-TbRegistroEntradas[[#This Row],[Data do Caixa Previsto]], 0 ), IF(TODAY()>TbRegistroEntradas[[#This Row],[Data do Caixa Previsto]], TODAY()-TbRegistroEntradas[[#This Row],[Data do Caixa Previsto]], 0 ) ) -> 4
B116: 45885 | C116: 45837 | D116: 45885 | E116: Vendas de mercadorias | F116: Móveis | G116: NF2674 | H116: 2376 | I116: =IF(TbRegistroEntradas[[#This Row],[Data do Caixa Realizado]]="",0,MONTH(TbRegistroEntradas[[#This Row],[Data do Caixa Previsto]])) -> 8 | J116: =IF(TbRegistroEntradas[[#This Row],[Data do Caixa Realizado]]="",0,YEAR(TbRegistroEntradas[[#This Row],[Data do Caixa Realizado]])) -> 2025 | K116: =IF(TbRegistroEntradas[[#This Row],[Data da Competência]]="",0,MONTH(TbRegistroEntradas[[#This Row],[Data da Competência]])) -> 6 | L116: =IF(TbRegistroEntradas[[#This Row],[Data da Competência]]="",0,YEAR(TbRegistroEntradas[[#This Row],[Data da Competência]])) -> 2025 | M116: =IF(TbRegistroEntradas[[#This Row],[Data do Caixa Previsto]]="",0,MONTH(TbRegistroEntradas[[#This Row],[Data do Caixa Previsto]])) -> 8 | N116: =IF(TbRegistroEntradas[[#This Row],[Data do Caixa Previsto]]="",0,YEAR(TbRegistroEntradas[[#This Row],[Data do Caixa Previsto]])) -> 2025 | O116: =IF(AND(TbRegistroEntradas[[#This Row],[Data do Caixa Previsto]]<TODAY(),TbRegistroEntradas[[#This Row],[Data do Caixa Realizado]]=""),"Vencida","Não Vencida") -> Não Vencida | P116: =IF(TbRegistroEntradas[[#This Row],[Data da Competência]]=TbRegistroEntradas[[#This Row],[Data do Caixa Previsto]],"Vista","Prazo") -> Prazo | Q116: =IF(TbRegistroEntradas[[#This Row],[Data do Caixa Realizado]]<>"", IF(TbRegistroEntradas[[#This Row],[Data do Caixa Realizado]]>TbRegistroEntradas[[#This Row],[Data do Caixa Previsto]], TbRegistroEntradas[[#This Row],[Data do Caixa Realizado]]-TbRegistroEntradas[[#This Row],[Data do Caixa Previsto]], 0 ), IF(TODAY()>TbRegistroEntradas[[#This Row],[Data do Caixa Previsto]], TODAY()-TbRegistroEntradas[[#This Row],[Data do Caixa Previsto]], 0 ) ) -> 0
B117: 45867 | C117: 45841 | D117: 45867 | E117: Vendas de mercadorias | F117: Móveis | G117: NF2175 | H117: 3940 | I117: =IF(TbRegistroEntradas[[#This Row],[Data do Caixa Realizado]]="",0,MONTH(TbRegistroEntradas[[#This Row],[Data do Caixa Previsto]])) -> 7 | J117: =IF(TbRegistroEntradas[[#This Row],[Data do Caixa Realizado]]="",0,YEAR(TbRegistroEntradas[[#This Row],[Data do Caixa Realizado]])) -> 2025 | K117: =IF(TbRegistroEntradas[[#This Row],[Data da Competência]]="",0,MONTH(TbRegistroEntradas[[#This Row],[Data da Competência]])) -> 7 | L117: =IF(TbRegistroEntradas[[#This Row],[Data da Competência]]="",0,YEAR(TbRegistroEntradas[[#This Row],[Data da Competência]])) -> 2025 | M117: =IF(TbRegistroEntradas[[#This Row],[Data do Caixa Previsto]]="",0,MONTH(TbRegistroEntradas[[#This Row],[Data do Caixa Previsto]])) -> 7 | N117: =IF(TbRegistroEntradas[[#This Row],[Data do Caixa Previsto]]="",0,YEAR(TbRegistroEntradas[[#This Row],[Data do Caixa Previsto]])) -> 2025 | O117: =IF(AND(TbRegistroEntradas[[#This Row],[Data do Caixa Previsto]]<TODAY(),TbRegistroEntradas[[#This Row],[Data do Caixa Realizado]]=""),"Vencida","Não Vencida") -> Não Vencida | P117: =IF(TbRegistroEntradas[[#This Row],[Data da Competência]]=TbRegistroEntradas[[#This Row],[Data do Caixa Previsto]],"Vista","Prazo") -> Prazo | Q117: =IF(TbRegistroEntradas[[#This Row],[Data do Caixa Realizado]]<>"", IF(TbRegistroEntradas[[#This Row],[Data do Caixa Realizado]]>TbRegistroEntradas[[#This Row],[Data do Caixa Previsto]], TbRegistroEntradas[[#This Row],[Data do Caixa Realizado]]-TbRegistroEntradas[[#This Row],[Data do Caixa Previsto]], 0 ), IF(TODAY()>TbRegistroEntradas[[#This Row],[Data do Caixa Previsto]], TODAY()-TbRegistroEntradas[[#This Row],[Data do Caixa Previsto]], 0 ) ) -> 0
B118: 45900 | C118: 45842 | D118: 45900 | E118: Vendas de mercadorias | F118: Móveis | G118: NF3338 | H118: 1732 | I118: =IF(TbRegistroEntradas[[#This Row],[Data do Caixa Realizado]]="",0,MONTH(TbRegistroEntradas[[#This Row],[Data do Caixa Previsto]])) -> 8 | J118: =IF(TbRegistroEntradas[[#This Row],[Data do Caixa Realizado]]="",0,YEAR(TbRegistroEntradas[[#This Row],[Data do Caixa Realizado]])) -> 2025 | K118: =IF(TbRegistroEntradas[[#This Row],[Data da Competência]]="",0,MONTH(TbRegistroEntradas[[#This Row],[Data da Competência]])) -> 7 | L118: =IF(TbRegistroEntradas[[#This Row],[Data da Competência]]="",0,YEAR(TbRegistroEntradas[[#This Row],[Data da Competência]])) -> 2025 | M118: =IF(TbRegistroEntradas[[#This Row],[Data do Caixa Previsto]]="",0,MONTH(TbRegistroEntradas[[#This Row],[Data do Caixa Previsto]])) -> 8 | N118: =IF(TbRegistroEntradas[[#This Row],[Data do Caixa Previsto]]="",0,YEAR(TbRegistroEntradas[[#This Row],[Data do Caixa Previsto]])) -> 2025 | O118: =IF(AND(TbRegistroEntradas[[#This Row],[Data do Caixa Previsto]]<TODAY(),TbRegistroEntradas[[#This Row],[Data do Caixa Realizado]]=""),"Vencida","Não Vencida") -> Não Vencida | P118: =IF(TbRegistroEntradas[[#This Row],[Data da Competência]]=TbRegistroEntradas[[#This Row],[Data do Caixa Previsto]],"Vista","Prazo") -> Prazo | Q118: =IF(TbRegistroEntradas[[#This Row],[Data do Caixa Realizado]]<>"", IF(TbRegistroEntradas[[#This Row],[Data do Caixa Realizado]]>TbRegistroEntradas[[#This Row],[Data do Caixa Previsto]], TbRegistroEntradas[[#This Row],[Data do Caixa Realizado]]-TbRegistroEntradas[[#This Row],[Data do Caixa Previsto]], 0 ), IF(TODAY()>TbRegistroEntradas[[#This Row],[Data do Caixa Previsto]], TODAY()-TbRegistroEntradas[[#This Row],[Data do Caixa Previsto]], 0 ) ) -> 0
B119: 45873 | C119: 45843 | D119: 45873 | E119: Vendas de mercadorias | F119: Livros | G119: NF7689 | H119: 1306 | I119: =IF(TbRegistroEntradas[[#This Row],[Data do Caixa Realizado]]="",0,MONTH(TbRegistroEntradas[[#This Row],[Data do Caixa Previsto]])) -> 8 | J119: =IF(TbRegistroEntradas[[#This Row],[Data do Caixa Realizado]]="",0,YEAR(TbRegistroEntradas[[#This Row],[Data do Caixa Realizado]])) -> 2025 | K119: =IF(TbRegistroEntradas[[#This Row],[Data da Competência]]="",0,MONTH(TbRegistroEntradas[[#This Row],[Data da Competência]])) -> 7 | L119: =IF(TbRegistroEntradas[[#This Row],[Data da Competência]]="",0,YEAR(TbRegistroEntradas[[#This Row],[Data da Competência]])) -> 2025 | M119: =IF(TbRegistroEntradas[[#This Row],[Data do Caixa Previsto]]="",0,MONTH(TbRegistroEntradas[[#This Row],[Data do Caixa Previsto]])) -> 8 | N119: =IF(TbRegistroEntradas[[#This Row],[Data do Caixa Previsto]]="",0,YEAR(TbRegistroEntradas[[#This Row],[Data do Caixa Previsto]])) -> 2025 | O119: =IF(AND(TbRegistroEntradas[[#This Row],[Data do Caixa Previsto]]<TODAY(),TbRegistroEntradas[[#This Row],[Data do Caixa Realizado]]=""),"Vencida","Não Vencida") -> Não Vencida | P119: =IF(TbRegistroEntradas[[#This Row],[Data da Competência]]=TbRegistroEntradas[[#This Row],[Data do Caixa Previsto]],"Vista","Prazo") -> Prazo | Q119: =IF(TbRegistroEntradas[[#This Row],[Data do Caixa Realizado]]<>"", IF(TbRegistroEntradas[[#This Row],[Data do Caixa Realizado]]>TbRegistroEntradas[[#This Row],[Data do Caixa Previsto]], TbRegistroEntradas[[#This Row],[Data do Caixa Realizado]]-TbRegistroEntradas[[#This Row],[Data do Caixa Previsto]], 0 ), IF(TODAY()>TbRegistroEntradas[[#This Row],[Data do Caixa Previsto]], TODAY()-TbRegistroEntradas[[#This Row],[Data do Caixa Previsto]], 0 ) ) -> 0
B120: 45893 | C120: 45845 | D120: 45893 | E120: Vendas de mercadorias | F120: Informática | G120: NF5938 | H120: 3954 | I120: =IF(TbRegistroEntradas[[#This Row],[Data do Caixa Realizado]]="",0,MONTH(TbRegistroEntradas[[#This Row],[Data do Caixa Previsto]])) -> 8 | J120: =IF(TbRegistroEntradas[[#This Row],[Data do Caixa Realizado]]="",0,YEAR(TbRegistroEntradas[[#This Row],[Data do Caixa Realizado]])) -> 2025 | K120: =IF(TbRegistroEntradas[[#This Row],[Data da Competência]]="",0,MONTH(TbRegistroEntradas[[#This Row],[Data da Competência]])) -> 7 | L120: =IF(TbRegistroEntradas[[#This Row],[Data da Competência]]="",0,YEAR(TbRegistroEntradas[[#This Row],[Data da Competência]])) -> 2025 | M120: =IF(TbRegistroEntradas[[#This Row],[Data do Caixa Previsto]]="",0,MONTH(TbRegistroEntradas[[#This Row],[Data do Caixa Previsto]])) -> 8 | N120: =IF(TbRegistroEntradas[[#This Row],[Data do Caixa Previsto]]="",0,YEAR(TbRegistroEntradas[[#This Row],[Data do Caixa Previsto]])) -> 2025 | O120: =IF(AND(TbRegistroEntradas[[#This Row],[Data do Caixa Previsto]]<TODAY(),TbRegistroEntradas[[#This Row],[Data do Caixa Realizado]]=""),"Vencida","Não Vencida") -> Não Vencida | P120: =IF(TbRegistroEntradas[[#This Row],[Data da Competência]]=TbRegistroEntradas[[#This Row],[Data do Caixa Previsto]],"Vista","Prazo") -> Prazo | Q120: =IF(TbRegistroEntradas[[#This Row],[Data do Caixa Realizado]]<>"", IF(TbRegistroEntradas[[#This Row],[Data do Caixa Realizado]]>TbRegistroEntradas[[#This Row],[Data do Caixa Previsto]], TbRegistroEntradas[[#This Row],[Data do Caixa Realizado]]-TbRegistroEntradas[[#This Row],[Data do Caixa Previsto]], 0 ), IF(TODAY()>TbRegistroEntradas[[#This Row],[Data do Caixa Previsto]], TODAY()-TbRegistroEntradas[[#This Row],[Data do Caixa Previsto]], 0 ) ) -> 0
B121: 45924 | C121: 45849 | D121: 45880 | E121: Vendas de mercadorias | F121: Som e imagem | G121: NF9391 | H121: 4090 | I121: =IF(TbRegistroEntradas[[#This Row],[Data do Caixa Realizado]]="",0,MONTH(TbRegistroEntradas[[#This Row],[Data do Caixa Previsto]])) -> 8 | J121: =IF(TbRegistroEntradas[[#This Row],[Data do Caixa Realizado]]="",0,YEAR(TbRegistroEntradas[[#This Row],[Data do Caixa Realizado]])) -> 2025 | K121: =IF(TbRegistroEntradas[[#This Row],[Data da Competência]]="",0,MONTH(TbRegistroEntradas[[#This Row],[Data da Competência]])) -> 7 | L121: =IF(TbRegistroEntradas[[#This Row],[Data da Competência]]="",0,YEAR(TbRegistroEntradas[[#This Row],[Data da Competência]])) -> 2025 | M121: =IF(TbRegistroEntradas[[#This Row],[Data do Caixa Previsto]]="",0,MONTH(TbRegistroEntradas[[#This Row],[Data do Caixa Previsto]])) -> 8 | N121: =IF(TbRegistroEntradas[[#This Row],[Data do Caixa Previsto]]="",0,YEAR(TbRegistroEntradas[[#This Row],[Data do Caixa Previsto]])) -> 2025 | O121: =IF(AND(TbRegistroEntradas[[#This Row],[Data do Caixa Previsto]]<TODAY(),TbRegistroEntradas[[#This Row],[Data do Caixa Realizado]]=""),"Vencida","Não Vencida") -> Não Vencida | P121: =IF(TbRegistroEntradas[[#This Row],[Data da Competência]]=TbRegistroEntradas[[#This Row],[Data do Caixa Previsto]],"Vista","Prazo") -> Prazo | Q121: =IF(TbRegistroEntradas[[#This Row],[Data do Caixa Realizado]]<>"", IF(TbRegistroEntradas[[#This Row],[Data do Caixa Realizado]]>TbRegistroEntradas[[#This Row],[Data do Caixa Previsto]], TbRegistroEntradas[[#This Row],[Data do Caixa Realizado]]-TbRegistroEntradas[[#This Row],[Data do Caixa Previsto]], 0 ), IF(TODAY()>TbRegistroEntradas[[#This Row],[Data do Caixa Previsto]], TODAY()-TbRegistroEntradas[[#This Row],[Data do Caixa Previsto]], 0 ) ) -> 44
B122: 45868 | C122: 45850 | D122: 45868 | E122: Vendas de mercadorias | F122: Eletrodomésticos | G122: NF6298 | H122: 2713 | I122: =IF(TbRegistroEntradas[[#This Row],[Data do Caixa Realizado]]="",0,MONTH(TbRegistroEntradas[[#This Row],[Data do Caixa Previsto]])) -> 7 | J122: =IF(TbRegistroEntradas[[#This Row],[Data do Caixa Realizado]]="",0,YEAR(TbRegistroEntradas[[#This Row],[Data do Caixa Realizado]])) -> 2025 | K122: =IF(TbRegistroEntradas[[#This Row],[Data da Competência]]="",0,MONTH(TbRegistroEntradas[[#This Row],[Data da Competência]])) -> 7 | L122: =IF(TbRegistroEntradas[[#This Row],[Data da Competência]]="",0,YEAR(TbRegistroEntradas[[#This Row],[Data da Competência]])) -> 2025 | M122: =IF(TbRegistroEntradas[[#This Row],[Data do Caixa Previsto]]="",0,MONTH(TbRegistroEntradas[[#This Row],[Data do Caixa Previsto]])) -> 7 | N122: =IF(TbRegistroEntradas[[#This Row],[Data do Caixa Previsto]]="",0,YEAR(TbRegistroEntradas[[#This Row],[Data do Caixa Previsto]])) -> 2025 | O122: =IF(AND(TbRegistroEntradas[[#This Row],[Data do Caixa Previsto]]<TODAY(),TbRegistroEntradas[[#This Row],[Data do Caixa Realizado]]=""),"Vencida","Não Vencida") -> Não Vencida | P122: =IF(TbRegistroEntradas[[#This Row],[Data da Competência]]=TbRegistroEntradas[[#This Row],[Data do Caixa Previsto]],"Vista","Prazo") -> Prazo | Q122: =IF(TbRegistroEntradas[[#This Row],[Data do Caixa Realizado]]<>"", IF(TbRegistroEntradas[[#This Row],[Data do Caixa Realizado]]>TbRegistroEntradas[[#This Row],[Data do Caixa Previsto]], TbRegistroEntradas[[#This Row],[Data do Caixa Realizado]]-TbRegistroEntradas[[#This Row],[Data do Caixa Previsto]], 0 ), IF(TODAY()>TbRegistroEntradas[[#This Row],[Data do Caixa Previsto]], TODAY()-TbRegistroEntradas[[#This Row],[Data do Caixa Previsto]], 0 ) ) -> 0
B123: 45859 | C123: 45854 | D123: 45859 | E123: Vendas de mercadorias | F123: Móveis | G123: NF7941 | H123: 3482 | I123: =IF(TbRegistroEntradas[[#This Row],[Data do Caixa Realizado]]="",0,MONTH(TbRegistroEntradas[[#This Row],[Data do Caixa Previsto]])) -> 7 | J123: =IF(TbRegistroEntradas[[#This Row],[Data do Caixa Realizado]]="",0,YEAR(TbRegistroEntradas[[#This Row],[Data do Caixa Realizado]])) -> 2025 | K123: =IF(TbRegistroEntradas[[#This Row],[Data da Competência]]="",0,MONTH(TbRegistroEntradas[[#This Row],[Data da Competência]])) -> 7 | L123: =IF(TbRegistroEntradas[[#This Row],[Data da Competência]]="",0,YEAR(TbRegistroEntradas[[#This Row],[Data da Competência]])) -> 2025 | M123: =IF(TbRegistroEntradas[[#This Row],[Data do Caixa Previsto]]="",0,MONTH(TbRegistroEntradas[[#This Row],[Data do Caixa Previsto]])) -> 7 | N123: =IF(TbRegistroEntradas[[#This Row],[Data do Caixa Previsto]]="",0,YEAR(TbRegistroEntradas[[#This Row],[Data do Caixa Previsto]])) -> 2025 | O123: =IF(AND(TbRegistroEntradas[[#This Row],[Data do Caixa Previsto]]<TODAY(),TbRegistroEntradas[[#This Row],[Data do Caixa Realizado]]=""),"Vencida","Não Vencida") -> Não Vencida | P123: =IF(TbRegistroEntradas[[#This Row],[Data da Competência]]=TbRegistroEntradas[[#This Row],[Data do Caixa Previsto]],"Vista","Prazo") -> Prazo | Q123: =IF(TbRegistroEntradas[[#This Row],[Data do Caixa Realizado]]<>"", IF(TbRegistroEntradas[[#This Row],[Data do Caixa Realizado]]>TbRegistroEntradas[[#This Row],[Data do Caixa Previsto]], TbRegistroEntradas[[#This Row],[Data do Caixa Realizado]]-TbRegistroEntradas[[#This Row],[Data do Caixa Previsto]], 0 ), IF(TODAY()>TbRegistroEntradas[[#This Row],[Data do Caixa Previsto]], TODAY()-TbRegistroEntradas[[#This Row],[Data do Caixa Previsto]], 0 ) ) -> 0
B124: 45903 | C124: 45856 | D124: 45903 | E124: Vendas de mercadorias | F124: Móveis | G124: NF3604 | H124: 2071 | I124: =IF(TbRegistroEntradas[[#This Row],[Data do Caixa Realizado]]="",0,MONTH(TbRegistroEntradas[[#This Row],[Data do Caixa Previsto]])) -> 9 | J124: =IF(TbRegistroEntradas[[#This Row],[Data do Caixa Realizado]]="",0,YEAR(TbRegistroEntradas[[#This Row],[Data do Caixa Realizado]])) -> 2025 | K124: =IF(TbRegistroEntradas[[#This Row],[Data da Competência]]="",0,MONTH(TbRegistroEntradas[[#This Row],[Data da Competência]])) -> 7 | L124: =IF(TbRegistroEntradas[[#This Row],[Data da Competência]]="",0,YEAR(TbRegistroEntradas[[#This Row],[Data da Competência]])) -> 2025 | M124: =IF(TbRegistroEntradas[[#This Row],[Data do Caixa Previsto]]="",0,MONTH(TbRegistroEntradas[[#This Row],[Data do Caixa Previsto]])) -> 9 | N124: =IF(TbRegistroEntradas[[#This Row],[Data do Caixa Previsto]]="",0,YEAR(TbRegistroEntradas[[#This Row],[Data do Caixa Previsto]])) -> 2025 | O124: =IF(AND(TbRegistroEntradas[[#This Row],[Data do Caixa Previsto]]<TODAY(),TbRegistroEntradas[[#This Row],[Data do Caixa Realizado]]=""),"Vencida","Não Vencida") -> Não Vencida | P124: =IF(TbRegistroEntradas[[#This Row],[Data da Competência]]=TbRegistroEntradas[[#This Row],[Data do Caixa Previsto]],"Vista","Prazo") -> Prazo | Q124: =IF(TbRegistroEntradas[[#This Row],[Data do Caixa Realizado]]<>"", IF(TbRegistroEntradas[[#This Row],[Data do Caixa Realizado]]>TbRegistroEntradas[[#This Row],[Data do Caixa Previsto]], TbRegistroEntradas[[#This Row],[Data do Caixa Realizado]]-TbRegistroEntradas[[#This Row],[Data do Caixa Previsto]], 0 ), IF(TODAY()>TbRegistroEntradas[[#This Row],[Data do Caixa Previsto]], TODAY()-TbRegistroEntradas[[#This Row],[Data do Caixa Previsto]], 0 ) ) -> 0
B125: 45890 | C125: 45861 | D125: 45890 | E125: Vendas de mercadorias | F125: Som e imagem | G125: NF4605 | H125: 4258 | I125: =IF(TbRegistroEntradas[[#This Row],[Data do Caixa Realizado]]="",0,MONTH(TbRegistroEntradas[[#This Row],[Data do Caixa Previsto]])) -> 8 | J125: =IF(TbRegistroEntradas[[#This Row],[Data do Caixa Realizado]]="",0,YEAR(TbRegistroEntradas[[#This Row],[Data do Caixa Realizado]])) -> 2025 | K125: =IF(TbRegistroEntradas[[#This Row],[Data da Competência]]="",0,MONTH(TbRegistroEntradas[[#This Row],[Data da Competência]])) -> 7 | L125: =IF(TbRegistroEntradas[[#This Row],[Data da Competência]]="",0,YEAR(TbRegistroEntradas[[#This Row],[Data da Competência]])) -> 2025 | M125: =IF(TbRegistroEntradas[[#This Row],[Data do Caixa Previsto]]="",0,MONTH(TbRegistroEntradas[[#This Row],[Data do Caixa Previsto]])) -> 8 | N125: =IF(TbRegistroEntradas[[#This Row],[Data do Caixa Previsto]]="",0,YEAR(TbRegistroEntradas[[#This Row],[Data do Caixa Previsto]])) -> 2025 | O125: =IF(AND(TbRegistroEntradas[[#This Row],[Data do Caixa Previsto]]<TODAY(),TbRegistroEntradas[[#This Row],[Data do Caixa Realizado]]=""),"Vencida","Não Vencida") -> Não Vencida | P125: =IF(TbRegistroEntradas[[#This Row],[Data da Competência]]=TbRegistroEntradas[[#This Row],[Data do Caixa Previsto]],"Vista","Prazo") -> Prazo | Q125: =IF(TbRegistroEntradas[[#This Row],[Data do Caixa Realizado]]<>"", IF(TbRegistroEntradas[[#This Row],[Data do Caixa Realizado]]>TbRegistroEntradas[[#This Row],[Data do Caixa Previsto]], TbRegistroEntradas[[#This Row],[Data do Caixa Realizado]]-TbRegistroEntradas[[#This Row],[Data do Caixa Previsto]], 0 ), IF(TODAY()>TbRegistroEntradas[[#This Row],[Data do Caixa Previsto]], TODAY()-TbRegistroEntradas[[#This Row],[Data do Caixa Previsto]], 0 ) ) -> 0
B126: 45985 | C126: 45863 | D126: 45907 | E126: Vendas de mercadorias | F126: Informática | G126: NF1759 | H126: 4383 | I126: =IF(TbRegistroEntradas[[#This Row],[Data do Caixa Realizado]]="",0,MONTH(TbRegistroEntradas[[#This Row],[Data do Caixa Previsto]])) -> 9 | J126: =IF(TbRegistroEntradas[[#This Row],[Data do Caixa Realizado]]="",0,YEAR(TbRegistroEntradas[[#This Row],[Data do Caixa Realizado]])) -> 2025 | K126: =IF(TbRegistroEntradas[[#This Row],[Data da Competência]]="",0,MONTH(TbRegistroEntradas[[#This Row],[Data da Competência]])) -> 7 | L126: =IF(TbRegistroEntradas[[#This Row],[Data da Competência]]="",0,YEAR(TbRegistroEntradas[[#This Row],[Data da Competência]])) -> 2025 | M126: =IF(TbRegistroEntradas[[#This Row],[Data do Caixa Previsto]]="",0,MONTH(TbRegistroEntradas[[#This Row],[Data do Caixa Previsto]])) -> 9 | N126: =IF(TbRegistroEntradas[[#This Row],[Data do Caixa Previsto]]="",0,YEAR(TbRegistroEntradas[[#This Row],[Data do Caixa Previsto]])) -> 2025 | O126: =IF(AND(TbRegistroEntradas[[#This Row],[Data do Caixa Previsto]]<TODAY(),TbRegistroEntradas[[#This Row],[Data do Caixa Realizado]]=""),"Vencida","Não Vencida") -> Não Vencida | P126: =IF(TbRegistroEntradas[[#This Row],[Data da Competência]]=TbRegistroEntradas[[#This Row],[Data do Caixa Previsto]],"Vista","Prazo") -> Prazo | Q126: =IF(TbRegistroEntradas[[#This Row],[Data do Caixa Realizado]]<>"", IF(TbRegistroEntradas[[#This Row],[Data do Caixa Realizado]]>TbRegistroEntradas[[#This Row],[Data do Caixa Previsto]], TbRegistroEntradas[[#This Row],[Data do Caixa Realizado]]-TbRegistroEntradas[[#This Row],[Data do Caixa Previsto]], 0 ), IF(TODAY()>TbRegistroEntradas[[#This Row],[Data do Caixa Previsto]], TODAY()-TbRegistroEntradas[[#This Row],[Data do Caixa Previsto]], 0 ) ) -> 78
... B137: 45911 | C137: 45900 | D137: 45911 | E137: Vendas de mercadorias | F137: Informática | G137: NF9607 | H137: 2467 | I137: =IF(TbRegistroEntradas[[#This Row],[Data do Caixa Realizado]]="",0,MONTH(TbRegistroEntradas[[#This Row],[Data do Caixa Previsto]])) -> 9 | J137: =IF(TbRegistroEntradas[[#This Row],[Data do Caixa Realizado]]="",0,YEAR(TbRegistroEntradas[[#This Row],[Data do Caixa Realizado]])) -> 2025 | K137: =IF(TbRegistroEntradas[[#This Row],[Data da Competência]]="",0,MONTH(TbRegistroEntradas[[#This Row],[Data da Competência]])) -> 8 | L137: =IF(TbRegistroEntradas[[#This Row],[Data da Competência]]="",0,YEAR(TbRegistroEntradas[[#This Row],[Data da Competência]])) -> 2025 | M137: =IF(TbRegistroEntradas[[#This Row],[Data do Caixa Previsto]]="",0,MONTH(TbRegistroEntradas[[#This Row],[Data do Caixa Previsto]])) -> 9 | N137: =IF(TbRegistroEntradas[[#This Row],[Data do Caixa Previsto]]="",0,YEAR(TbRegistroEntradas[[#This Row],[Data do Caixa Previsto]])) -> 2025 | O137: =IF(AND(TbRegistroEntradas[[#This Row],[Data do Caixa Previsto]]<TODAY(),TbRegistroEntradas[[#This Row],[Data do Caixa Realizado]]=""),"Vencida","Não Vencida") -> Não Vencida | P137: =IF(TbRegistroEntradas[[#This Row],[Data da Competência]]=TbRegistroEntradas[[#This Row],[Data do Caixa Previsto]],"Vista","Prazo") -> Prazo | Q137: =IF(TbRegistroEntradas[[#This Row],[Data do Caixa Realizado]]<>"", IF(TbRegistroEntradas[[#This Row],[Data do Caixa Realizado]]>TbRegistroEntradas[[#This Row],[Data do Caixa Previsto]], TbRegistroEntradas[[#This Row],[Data do Caixa Realizado]]-TbRegistroEntradas[[#This Row],[Data do Caixa Previsto]], 0 ), IF(TODAY()>TbRegistroEntradas[[#This Row],[Data do Caixa Previsto]], TODAY()-TbRegistroEntradas[[#This Row],[Data do Caixa Previsto]], 0 ) ) -> 0
C138: 45901 | D138: 45927 | E138: Vendas de mercadorias | F138: Móveis | G138: NF6643 | H138: 4253 | I138: =IF(TbRegistroEntradas[[#This Row],[Data do Caixa Realizado]]="",0,MONTH(TbRegistroEntradas[[#This Row],[Data do Caixa Previsto]])) -> 0 | J138: =IF(TbRegistroEntradas[[#This Row],[Data do Caixa Realizado]]="",0,YEAR(TbRegistroEntradas[[#This Row],[Data do Caixa Realizado]])) -> 0 | K138: =IF(TbRegistroEntradas[[#This Row],[Data da Competência]]="",0,MONTH(TbRegistroEntradas[[#This Row],[Data da Competência]])) -> 9 | L138: =IF(TbRegistroEntradas[[#This Row],[Data da Competência]]="",0,YEAR(TbRegistroEntradas[[#This Row],[Data da Competência]])) -> 2025 | M138: =IF(TbRegistroEntradas[[#This Row],[Data do Caixa Previsto]]="",0,MONTH(TbRegistroEntradas[[#This Row],[Data do Caixa Previsto]])) -> 9 | N138: =IF(TbRegistroEntradas[[#This Row],[Data do Caixa Previsto]]="",0,YEAR(TbRegistroEntradas[[#This Row],[Data do Caixa Previsto]])) -> 2025 | O138: =IF(AND(TbRegistroEntradas[[#This Row],[Data do Caixa Previsto]]<TODAY(),TbRegistroEntradas[[#This Row],[Data do Caixa Realizado]]=""),"Vencida","Não Vencida") -> Vencida | P138: =IF(TbRegistroEntradas[[#This Row],[Data da Competência]]=TbRegistroEntradas[[#This Row],[Data do Caixa Previsto]],"Vista","Prazo") -> Prazo | Q138: =IF(TbRegistroEntradas[[#This Row],[Data do Caixa Realizado]]<>"", IF(TbRegistroEntradas[[#This Row],[Data do Caixa Realizado]]>TbRegistroEntradas[[#This Row],[Data do Caixa Previsto]], TbRegistroEntradas[[#This Row],[Data do Caixa Realizado]]-TbRegistroEntradas[[#This Row],[Data do Caixa Previsto]], 0 ), IF(TODAY()>TbRegistroEntradas[[#This Row],[Data do Caixa Previsto]], TODAY()-TbRegistroEntradas[[#This Row],[Data do Caixa Previsto]], 0 ) ) -> 282
B139: 45914 | C139: 45907 | D139: 45914 | E139: Vendas de mercadorias | F139: Som e imagem | G139: NF3939 | H139: 2391 | I139: =IF(TbRegistroEntradas[[#This Row],[Data do Caixa Realizado]]="",0,MONTH(TbRegistroEntradas[[#This Row],[Data do Caixa Previsto]])) -> 9 | J139: =IF(TbRegistroEntradas[[#This Row],[Data do Caixa Realizado]]="",0,YEAR(TbRegistroEntradas[[#This Row],[Data do Caixa Realizado]])) -> 2025 | K139: =IF(TbRegistroEntradas[[#This Row],[Data da Competência]]="",0,MONTH(TbRegistroEntradas[[#This Row],[Data da Competência]])) -> 9 | L139: =IF(TbRegistroEntradas[[#This Row],[Data da Competência]]="",0,YEAR(TbRegistroEntradas[[#This Row],[Data da Competência]])) -> 2025 | M139: =IF(TbRegistroEntradas[[#This Row],[Data do Caixa Previsto]]="",0,MONTH(TbRegistroEntradas[[#This Row],[Data do Caixa Previsto]])) -> 9 | N139: =IF(TbRegistroEntradas[[#This Row],[Data do Caixa Previsto]]="",0,YEAR(TbRegistroEntradas[[#This Row],[Data do Caixa Previsto]])) -> 2025 | O139: =IF(AND(TbRegistroEntradas[[#This Row],[Data do Caixa Previsto]]<TODAY(),TbRegistroEntradas[[#This Row],[Data do Caixa Realizado]]=""),"Vencida","Não Vencida") -> Não Vencida | P139: =IF(TbRegistroEntradas[[#This Row],[Data da Competência]]=TbRegistroEntradas[[#This Row],[Data do Caixa Previsto]],"Vista","Prazo") -> Prazo | Q139: =IF(TbRegistroEntradas[[#This Row],[Data do Caixa Realizado]]<>"", IF(TbRegistroEntradas[[#This Row],[Data do Caixa Realizado]]>TbRegistroEntradas[[#This Row],[Data do Caixa Previsto]], TbRegistroEntradas[[#This Row],[Data do Caixa Realizado]]-TbRegistroEntradas[[#This Row],[Data do Caixa Previsto]], 0 ), IF(TODAY()>TbRegistroEntradas[[#This Row],[Data do Caixa Previsto]], TODAY()-TbRegistroEntradas[[#This Row],[Data do Caixa Previsto]], 0 ) ) -> 0
B140: 45927 | C140: 45909 | D140: 45922 | E140: Vendas de mercadorias | F140: Móveis | G140: NF3599 | H140: 3669 | I140: =IF(TbRegistroEntradas[[#This Row],[Data do Caixa Realizado]]="",0,MONTH(TbRegistroEntradas[[#This Row],[Data do Caixa Previsto]])) -> 9 | J140: =IF(TbRegistroEntradas[[#This Row],[Data do Caixa Realizado]]="",0,YEAR(TbRegistroEntradas[[#This Row],[Data do Caixa Realizado]])) -> 2025 | K140: =IF(TbRegistroEntradas[[#This Row],[Data da Competência]]="",0,MONTH(TbRegistroEntradas[[#This Row],[Data da Competência]])) -> 9 | L140: =IF(TbRegistroEntradas[[#This Row],[Data da Competência]]="",0,YEAR(TbRegistroEntradas[[#This Row],[Data da Competência]])) -> 2025 | M140: =IF(TbRegistroEntradas[[#This Row],[Data do Caixa Previsto]]="",0,MONTH(TbRegistroEntradas[[#This Row],[Data do Caixa Previsto]])) -> 9 | N140: =IF(TbRegistroEntradas[[#This Row],[Data do Caixa Previsto]]="",0,YEAR(TbRegistroEntradas[[#This Row],[Data do Caixa Previsto]])) -> 2025 | O140: =IF(AND(TbRegistroEntradas[[#This Row],[Data do Caixa Previsto]]<TODAY(),TbRegistroEntradas[[#This Row],[Data do Caixa Realizado]]=""),"Vencida","Não Vencida") -> Não Vencida | P140: =IF(TbRegistroEntradas[[#This Row],[Data da Competência]]=TbRegistroEntradas[[#This Row],[Data do Caixa Previsto]],"Vista","Prazo") -> Prazo | Q140: =IF(TbRegistroEntradas[[#This Row],[Data do Caixa Realizado]]<>"", IF(TbRegistroEntradas[[#This Row],[Data do Caixa Realizado]]>TbRegistroEntradas[[#This Row],[Data do Caixa Previsto]], TbRegistroEntradas[[#This Row],[Data do Caixa Realizado]]-TbRegistroEntradas[[#This Row],[Data do Caixa Previsto]], 0 ), IF(TODAY()>TbRegistroEntradas[[#This Row],[Data do Caixa Previsto]], TODAY()-TbRegistroEntradas[[#This Row],[Data do Caixa Previsto]], 0 ) ) -> 5
B141: 46009 | C141: 45912 | D141: 45940 | E141: Vendas de mercadorias | F141: Móveis | G141: NF9914 | H141: 1207 | I141: =IF(TbRegistroEntradas[[#This Row],[Data do Caixa Realizado]]="",0,MONTH(TbRegistroEntradas[[#This Row],[Data do Caixa Previsto]])) -> 10 | J141: =IF(TbRegistroEntradas[[#This Row],[Data do Caixa Realizado]]="",0,YEAR(TbRegistroEntradas[[#This Row],[Data do Caixa Realizado]])) -> 2025 | K141: =IF(TbRegistroEntradas[[#This Row],[Data da Competência]]="",0,MONTH(TbRegistroEntradas[[#This Row],[Data da Competência]])) -> 9 | L141: =IF(TbRegistroEntradas[[#This Row],[Data da Competência]]="",0,YEAR(TbRegistroEntradas[[#This Row],[Data da Competência]])) -> 2025 | M141: =IF(TbRegistroEntradas[[#This Row],[Data do Caixa Previsto]]="",0,MONTH(TbRegistroEntradas[[#This Row],[Data do Caixa Previsto]])) -> 10 | N141: =IF(TbRegistroEntradas[[#This Row],[Data do Caixa Previsto]]="",0,YEAR(TbRegistroEntradas[[#This Row],[Data do Caixa Previsto]])) -> 2025 | O141: =IF(AND(TbRegistroEntradas[[#This Row],[Data do Caixa Previsto]]<TODAY(),TbRegistroEntradas[[#This Row],[Data do Caixa Realizado]]=""),"Vencida","Não Vencida") -> Não Vencida | P141: =IF(TbRegistroEntradas[[#This Row],[Data da Competência]]=TbRegistroEntradas[[#This Row],[Data do Caixa Previsto]],"Vista","Prazo") -> Prazo | Q141: =IF(TbRegistroEntradas[[#This Row],[Data do Caixa Realizado]]<>"", IF(TbRegistroEntradas[[#This Row],[Data do Caixa Realizado]]>TbRegistroEntradas[[#This Row],[Data do Caixa Previsto]], TbRegistroEntradas[[#This Row],[Data do Caixa Realizado]]-TbRegistroEntradas[[#This Row],[Data do Caixa Previsto]], 0 ), IF(TODAY()>TbRegistroEntradas[[#This Row],[Data do Caixa Previsto]], TODAY()-TbRegistroEntradas[[#This Row],[Data do Caixa Previsto]], 0 ) ) -> 69
B142: 45969 | C142: 45918 | D142: 45969 | E142: Vendas de mercadorias | F142: Informática | G142: NF5492 | H142: 2539 | I142: =IF(TbRegistroEntradas[[#This Row],[Data do Caixa Realizado]]="",0,MONTH(TbRegistroEntradas[[#This Row],[Data do Caixa Previsto]])) -> 11 | J142: =IF(TbRegistroEntradas[[#This Row],[Data do Caixa Realizado]]="",0,YEAR(TbRegistroEntradas[[#This Row],[Data do Caixa Realizado]])) -> 2025 | K142: =IF(TbRegistroEntradas[[#This Row],[Data da Competência]]="",0,MONTH(TbRegistroEntradas[[#This Row],[Data da Competência]])) -> 9 | L142: =IF(TbRegistroEntradas[[#This Row],[Data da Competência]]="",0,YEAR(TbRegistroEntradas[[#This Row],[Data da Competência]])) -> 2025 | M142: =IF(TbRegistroEntradas[[#This Row],[Data do Caixa Previsto]]="",0,MONTH(TbRegistroEntradas[[#This Row],[Data do Caixa Previsto]])) -> 11 | N142: =IF(TbRegistroEntradas[[#This Row],[Data do Caixa Previsto]]="",0,YEAR(TbRegistroEntradas[[#This Row],[Data do Caixa Previsto]])) -> 2025 | O142: =IF(AND(TbRegistroEntradas[[#This Row],[Data do Caixa Previsto]]<TODAY(),TbRegistroEntradas[[#This Row],[Data do Caixa Realizado]]=""),"Vencida","Não Vencida") -> Não Vencida | P142: =IF(TbRegistroEntradas[[#This Row],[Data da Competência]]=TbRegistroEntradas[[#This Row],[Data do Caixa Previsto]],"Vista","Prazo") -> Prazo | Q142: =IF(TbRegistroEntradas[[#This Row],[Data do Caixa Realizado]]<>"", IF(TbRegistroEntradas[[#This Row],[Data do Caixa Realizado]]>TbRegistroEntradas[[#This Row],[Data do Caixa Previsto]], TbRegistroEntradas[[#This Row],[Data do Caixa Realizado]]-TbRegistroEntradas[[#This Row],[Data do Caixa Previsto]], 0 ), IF(TODAY()>TbRegistroEntradas[[#This Row],[Data do Caixa Previsto]], TODAY()-TbRegistroEntradas[[#This Row],[Data do Caixa Previsto]], 0 ) ) -> 0
B143: 45931 | C143: 45920 | D143: 45931 | E143: Vendas de mercadorias | F143: Livros | G143: NF7516 | H143: 2895 | I143: =IF(TbRegistroEntradas[[#This Row],[Data do Caixa Realizado]]="",0,MONTH(TbRegistroEntradas[[#This Row],[Data do Caixa Previsto]])) -> 10 | J143: =IF(TbRegistroEntradas[[#This Row],[Data do Caixa Realizado]]="",0,YEAR(TbRegistroEntradas[[#This Row],[Data do Caixa Realizado]])) -> 2025 | K143: =IF(TbRegistroEntradas[[#This Row],[Data da Competência]]="",0,MONTH(TbRegistroEntradas[[#This Row],[Data da Competência]])) -> 9 | L143: =IF(TbRegistroEntradas[[#This Row],[Data da Competência]]="",0,YEAR(TbRegistroEntradas[[#This Row],[Data da Competência]])) -> 2025 | M143: =IF(TbRegistroEntradas[[#This Row],[Data do Caixa Previsto]]="",0,MONTH(TbRegistroEntradas[[#This Row],[Data do Caixa Previsto]])) -> 10 | N143: =IF(TbRegistroEntradas[[#This Row],[Data do Caixa Previsto]]="",0,YEAR(TbRegistroEntradas[[#This Row],[Data do Caixa Previsto]])) -> 2025 | O143: =IF(AND(TbRegistroEntradas[[#This Row],[Data do Caixa Previsto]]<TODAY(),TbRegistroEntradas[[#This Row],[Data do Caixa Realizado]]=""),"Vencida","Não Vencida") -> Não Vencida | P143: =IF(TbRegistroEntradas[[#This Row],[Data da Competência]]=TbRegistroEntradas[[#This Row],[Data do Caixa Previsto]],"Vista","Prazo") -> Prazo | Q143: =IF(TbRegistroEntradas[[#This Row],[Data do Caixa Realizado]]<>"", IF(TbRegistroEntradas[[#This Row],[Data do Caixa Realizado]]>TbRegistroEntradas[[#This Row],[Data do Caixa Previsto]], TbRegistroEntradas[[#This Row],[Data do Caixa Realizado]]-TbRegistroEntradas[[#This Row],[Data do Caixa Previsto]], 0 ), IF(TODAY()>TbRegistroEntradas[[#This Row],[Data do Caixa Previsto]], TODAY()-TbRegistroEntradas[[#This Row],[Data do Caixa Previsto]], 0 ) ) -> 0
B144: 45945 | C144: 45921 | D144: 45934 | E144: Vendas de mercadorias | F144: Móveis | G144: NF8652 | H144: 2106 | I144: =IF(TbRegistroEntradas[[#This Row],[Data do Caixa Realizado]]="",0,MONTH(TbRegistroEntradas[[#This Row],[Data do Caixa Previsto]])) -> 10 | J144: =IF(TbRegistroEntradas[[#This Row],[Data do Caixa Realizado]]="",0,YEAR(TbRegistroEntradas[[#This Row],[Data do Caixa Realizado]])) -> 2025 | K144: =IF(TbRegistroEntradas[[#This Row],[Data da Competência]]="",0,MONTH(TbRegistroEntradas[[#This Row],[Data da Competência]])) -> 9 | L144: =IF(TbRegistroEntradas[[#This Row],[Data da Competência]]="",0,YEAR(TbRegistroEntradas[[#This Row],[Data da Competência]])) -> 2025 | M144: =IF(TbRegistroEntradas[[#This Row],[Data do Caixa Previsto]]="",0,MONTH(TbRegistroEntradas[[#This Row],[Data do Caixa Previsto]])) -> 10 | N144: =IF(TbRegistroEntradas[[#This Row],[Data do Caixa Previsto]]="",0,YEAR(TbRegistroEntradas[[#This Row],[Data do Caixa Previsto]])) -> 2025 | O144: =IF(AND(TbRegistroEntradas[[#This Row],[Data do Caixa Previsto]]<TODAY(),TbRegistroEntradas[[#This Row],[Data do Caixa Realizado]]=""),"Vencida","Não Vencida") -> Não Vencida | P144: =IF(TbRegistroEntradas[[#This Row],[Data da Competência]]=TbRegistroEntradas[[#This Row],[Data do Caixa Previsto]],"Vista","Prazo") -> Prazo | Q144: =IF(TbRegistroEntradas[[#This Row],[Data do Caixa Realizado]]<>"", IF(TbRegistroEntradas[[#This Row],[Data do Caixa Realizado]]>TbRegistroEntradas[[#This Row],[Data do Caixa Previsto]], TbRegistroEntradas[[#This Row],[Data do Caixa Realizado]]-TbRegistroEntradas[[#This Row],[Data do Caixa Previsto]], 0 ), IF(TODAY()>TbRegistroEntradas[[#This Row],[Data do Caixa Previsto]], TODAY()-TbRegistroEntradas[[#This Row],[Data do Caixa Previsto]], 0 ) ) -> 11
...

Sheet RegistroSaídas
B1: (NOME DA EMPRESA) | H1: Registro das Saídas de Caixa
B3: Data do Caixa Realizado | C3: Data da Competência | D3: Data do Caixa Previsto | E3: Conta Nível 1 | F3: Conta Nível 2 | G3: Histórico | H3: Valor | I3: Mês Caixa | J3: Ano Caixa | K3: Mês Competência | L3: Ano Competência | M3: Mês Previsto | N3: Ano Previsto | O3: Dias de Atraso
B4: 45572 | C4: 45514 | D4: 45572 | E4: Compra de mercadorias | F4: Som e imagem | G4: NF4400 | H4: 4021 | I4: =IF(TbRegistroSaídas[[#This Row],[Data do Caixa Realizado]]="",0,MONTH(TbRegistroSaídas[[#This Row],[Data do Caixa Realizado]])) -> 10 | J4: =IF(TbRegistroSaídas[[#This Row],[Data do Caixa Realizado]]="",0,YEAR(TbRegistroSaídas[[#This Row],[Data do Caixa Realizado]])) -> 2024 | K4: =IF(TbRegistroSaídas[[#This Row],[Data da Competência]]="",0,MONTH(TbRegistroSaídas[[#This Row],[Data da Competência]])) -> 8 | L4: =IF(TbRegistroSaídas[[#This Row],[Data da Competência]]="",0,YEAR(TbRegistroSaídas[[#This Row],[Data da Competência]])) -> 2024 | M4: =IF(TbRegistroSaídas[[#This Row],[Data do Caixa Previsto]]="",0,MONTH(TbRegistroSaídas[[#This Row],[Data do Caixa Previsto]])) -> 10 | N4: =IF(TbRegistroSaídas[[#This Row],[Data do Caixa Previsto]]="",0,YEAR(TbRegistroSaídas[[#This Row],[Data do Caixa Previsto]])) -> 2024 | O4: =IF(TbRegistroSaídas[[#This Row],[Data do Caixa Realizado]]<>"", IF(TbRegistroSaídas[[#This Row],[Data do Caixa Realizado]]>TbRegistroSaídas[[#This Row],[Data do Caixa Previsto]], TbRegistroSaídas[[#This Row],[Data do Caixa Realizado]]-TbRegistroSaídas[[#This Row],[Data do Caixa Previsto]], 0 ), IF(TODAY()>TbRegistroSaídas[[#This Row],[Data do Caixa Previsto]], TODAY()-TbRegistroSaídas[[#This Row],[Data do Caixa Previsto]], 0 ) ) -> 0
B5: 45552 | C5: 45517 | D5: 45552 | E5: Compra de mercadorias | F5: Vestuário | G5: NF5356 | H5: 651 | I5: =IF(TbRegistroSaídas[[#This Row],[Data do Caixa Realizado]]="",0,MONTH(TbRegistroSaídas[[#This Row],[Data do Caixa Realizado]])) -> 9 | J5: =IF(TbRegistroSaídas[[#This Row],[Data do Caixa Realizado]]="",0,YEAR(TbRegistroSaídas[[#This Row],[Data do Caixa Realizado]])) -> 2024 | K5: =IF(TbRegistroSaídas[[#This Row],[Data da Competência]]="",0,MONTH(TbRegistroSaídas[[#This Row],[Data da Competência]])) -> 8 | L5: =IF(TbRegistroSaídas[[#This Row],[Data da Competência]]="",0,YEAR(TbRegistroSaídas[[#This Row],[Data da Competência]])) -> 2024 | M5: =IF(TbRegistroSaídas[[#This Row],[Data do Caixa Previsto]]="",0,MONTH(TbRegistroSaídas[[#This Row],[Data do Caixa Previsto]])) -> 9 | N5: =IF(TbRegistroSaídas[[#This Row],[Data do Caixa Previsto]]="",0,YEAR(TbRegistroSaídas[[#This Row],[Data do Caixa Previsto]])) -> 2024 | O5: =IF(TbRegistroSaídas[[#This Row],[Data do Caixa Realizado]]<>"", IF(TbRegistroSaídas[[#This Row],[Data do Caixa Realizado]]>TbRegistroSaídas[[#This Row],[Data do Caixa Previsto]], TbRegistroSaídas[[#This Row],[Data do Caixa Realizado]]-TbRegistroSaídas[[#This Row],[Data do Caixa Previsto]], 0 ), IF(TODAY()>TbRegistroSaídas[[#This Row],[Data do Caixa Previsto]], TODAY()-TbRegistroSaídas[[#This Row],[Data do Caixa Previsto]], 0 ) ) -> 0
B6: 45540 | C6: 45522 | D6: 45540 | E6: Compra de mercadorias | F6: Som e imagem | G6: NF1847 | H6: 131 | I6: =IF(TbRegistroSaídas[[#This Row],[Data do Caixa Realizado]]="",0,MONTH(TbRegistroSaídas[[#This Row],[Data do Caixa Realizado]])) -> 9 | J6: =IF(TbRegistroSaídas[[#This Row],[Data do Caixa Realizado]]="",0,YEAR(TbRegistroSaídas[[#This Row],[Data do Caixa Realizado]])) -> 2024 | K6: =IF(TbRegistroSaídas[[#This Row],[Data da Competência]]="",0,MONTH(TbRegistroSaídas[[#This Row],[Data da Competência]])) -> 8 | L6: =IF(TbRegistroSaídas[[#This Row],[Data da Competência]]="",0,YEAR(TbRegistroSaídas[[#This Row],[Data da Competência]])) -> 2024 | M6: =IF(TbRegistroSaídas[[#This Row],[Data do Caixa Previsto]]="",0,MONTH(TbRegistroSaídas[[#This Row],[Data do Caixa Previsto]])) -> 9 | N6: =IF(TbRegistroSaídas[[#This Row],[Data do Caixa Previsto]]="",0,YEAR(TbRegistroSaídas[[#This Row],[Data do Caixa Previsto]])) -> 2024 | O6: =IF(TbRegistroSaídas[[#This Row],[Data do Caixa Realizado]]<>"", IF(TbRegistroSaídas[[#This Row],[Data do Caixa Realizado]]>TbRegistroSaídas[[#This Row],[Data do Caixa Previsto]], TbRegistroSaídas[[#This Row],[Data do Caixa Realizado]]-TbRegistroSaídas[[#This Row],[Data do Caixa Previsto]], 0 ), IF(TODAY()>TbRegistroSaídas[[#This Row],[Data do Caixa Previsto]], TODAY()-TbRegistroSaídas[[#This Row],[Data do Caixa Previsto]], 0 ) ) -> 0
B7: 45561 | C7: 45527 | D7: 45561 | E7: Compra de mercadorias | F7: Som e imagem | G7: NF7011 | H7: 803 | I7: =IF(TbRegistroSaídas[[#This Row],[Data do Caixa Realizado]]="",0,MONTH(TbRegistroSaídas[[#This Row],[Data do Caixa Realizado]])) -> 9 | J7: =IF(TbRegistroSaídas[[#This Row],[Data do Caixa Realizado]]="",0,YEAR(TbRegistroSaídas[[#This Row],[Data do Caixa Realizado]])) -> 2024 | K7: =IF(TbRegistroSaídas[[#This Row],[Data da Competência]]="",0,MONTH(TbRegistroSaídas[[#This Row],[Data da Competência]])) -> 8 | L7: =IF(TbRegistroSaídas[[#This Row],[Data da Competência]]="",0,YEAR(TbRegistroSaídas[[#This Row],[Data da Competência]])) -> 2024 | M7: =IF(TbRegistroSaídas[[#This Row],[Data do Caixa Previsto]]="",0,MONTH(TbRegistroSaídas[[#This Row],[Data do Caixa Previsto]])) -> 9 | N7: =IF(TbRegistroSaídas[[#This Row],[Data do Caixa Previsto]]="",0,YEAR(TbRegistroSaídas[[#This Row],[Data do Caixa Previsto]])) -> 2024 | O7: =IF(TbRegistroSaídas[[#This Row],[Data do Caixa Realizado]]<>"", IF(TbRegistroSaídas[[#This Row],[Data do Caixa Realizado]]>TbRegistroSaídas[[#This Row],[Data do Caixa Previsto]], TbRegistroSaídas[[#This Row],[Data do Caixa Realizado]]-TbRegistroSaídas[[#This Row],[Data do Caixa Previsto]], 0 ), IF(TODAY()>TbRegistroSaídas[[#This Row],[Data do Caixa Previsto]], TODAY()-TbRegistroSaídas[[#This Row],[Data do Caixa Previsto]], 0 ) ) -> 0
B8: 45559 | C8: 45528 | D8: 45559 | E8: Compra de mercadorias | F8: Vestuário | G8: NF7746 | H8: 4460 | I8: =IF(TbRegistroSaídas[[#This Row],[Data do Caixa Realizado]]="",0,MONTH(TbRegistroSaídas[[#This Row],[Data do Caixa Realizado]])) -> 9 | J8: =IF(TbRegistroSaídas[[#This Row],[Data do Caixa Realizado]]="",0,YEAR(TbRegistroSaídas[[#This Row],[Data do Caixa Realizado]])) -> 2024 | K8: =IF(TbRegistroSaídas[[#This Row],[Data da Competência]]="",0,MONTH(TbRegistroSaídas[[#This Row],[Data da Competência]])) -> 8 | L8: =IF(TbRegistroSaídas[[#This Row],[Data da Competência]]="",0,YEAR(TbRegistroSaídas[[#This Row],[Data da Competência]])) -> 2024 | M8: =IF(TbRegistroSaídas[[#This Row],[Data do Caixa Previsto]]="",0,MONTH(TbRegistroSaídas[[#This Row],[Data do Caixa Previsto]])) -> 9 | N8: =IF(TbRegistroSaídas[[#This Row],[Data do Caixa Previsto]]="",0,YEAR(TbRegistroSaídas[[#This Row],[Data do Caixa Previsto]])) -> 2024 | O8: =IF(TbRegistroSaídas[[#This Row],[Data do Caixa Realizado]]<>"", IF(TbRegistroSaídas[[#This Row],[Data do Caixa Realizado]]>TbRegistroSaídas[[#This Row],[Data do Caixa Previsto]], TbRegistroSaídas[[#This Row],[Data do Caixa Realizado]]-TbRegistroSaídas[[#This Row],[Data do Caixa Previsto]], 0 ), IF(TODAY()>TbRegistroSaídas[[#This Row],[Data do Caixa Previsto]], TODAY()-TbRegistroSaídas[[#This Row],[Data do Caixa Previsto]], 0 ) ) -> 0
B9: 45537 | C9: 45529 | D9: 45537 | E9: Compra de mercadorias | F9: Informática | G9: NF1507 | H9: 299 | I9: =IF(TbRegistroSaídas[[#This Row],[Data do Caixa Realizado]]="",0,MONTH(TbRegistroSaídas[[#This Row],[Data do Caixa Realizado]])) -> 9 | J9: =IF(TbRegistroSaídas[[#This Row],[Data do Caixa Realizado]]="",0,YEAR(TbRegistroSaídas[[#This Row],[Data do Caixa Realizado]])) -> 2024 | K9: =IF(TbRegistroSaídas[[#This Row],[Data da Competência]]="",0,MONTH(TbRegistroSaídas[[#This Row],[Data da Competência]])) -> 8 | L9: =IF(TbRegistroSaídas[[#This Row],[Data da Competência]]="",0,YEAR(TbRegistroSaídas[[#This Row],[Data da Competência]])) -> 2024 | M9: =IF(TbRegistroSaídas[[#This Row],[Data do Caixa Previsto]]="",0,MONTH(TbRegistroSaídas[[#This Row],[Data do Caixa Previsto]])) -> 9 | N9: =IF(TbRegistroSaídas[[#This Row],[Data do Caixa Previsto]]="",0,YEAR(TbRegistroSaídas[[#This Row],[Data do Caixa Previsto]])) -> 2024 | O9: =IF(TbRegistroSaídas[[#This Row],[Data do Caixa Realizado]]<>"", IF(TbRegistroSaídas[[#This Row],[Data do Caixa Realizado]]>TbRegistroSaídas[[#This Row],[Data do Caixa Previsto]], TbRegistroSaídas[[#This Row],[Data do Caixa Realizado]]-TbRegistroSaídas[[#This Row],[Data do Caixa Previsto]], 0 ), IF(TODAY()>TbRegistroSaídas[[#This Row],[Data do Caixa Previsto]], TODAY()-TbRegistroSaídas[[#This Row],[Data do Caixa Previsto]], 0 ) ) -> 0
B10: 45571 | C10: 45533 | D10: 45571 | E10: Compra de mercadorias | F10: Vestuário | G10: NF5445 | H10: 618 | I10: =IF(TbRegistroSaídas[[#This Row],[Data do Caixa Realizado]]="",0,MONTH(TbRegistroSaídas[[#This Row],[Data do Caixa Realizado]])) -> 10 | J10: =IF(TbRegistroSaídas[[#This Row],[Data do Caixa Realizado]]="",0,YEAR(TbRegistroSaídas[[#This Row],[Data do Caixa Realizado]])) -> 2024 | K10: =IF(TbRegistroSaídas[[#This Row],[Data da Competência]]="",0,MONTH(TbRegistroSaídas[[#This Row],[Data da Competência]])) -> 8 | L10: =IF(TbRegistroSaídas[[#This Row],[Data da Competência]]="",0,YEAR(TbRegistroSaídas[[#This Row],[Data da Competência]])) -> 2024 | M10: =IF(TbRegistroSaídas[[#This Row],[Data do Caixa Previsto]]="",0,MONTH(TbRegistroSaídas[[#This Row],[Data do Caixa Previsto]])) -> 10 | N10: =IF(TbRegistroSaídas[[#This Row],[Data do Caixa Previsto]]="",0,YEAR(TbRegistroSaídas[[#This Row],[Data do Caixa Previsto]])) -> 2024 | O10: =IF(TbRegistroSaídas[[#This Row],[Data do Caixa Realizado]]<>"", IF(TbRegistroSaídas[[#This Row],[Data do Caixa Realizado]]>TbRegistroSaídas[[#This Row],[Data do Caixa Previsto]], TbRegistroSaídas[[#This Row],[Data do Caixa Realizado]]-TbRegistroSaídas[[#This Row],[Data do Caixa Previsto]], 0 ), IF(TODAY()>TbRegistroSaídas[[#This Row],[Data do Caixa Previsto]], TODAY()-TbRegistroSaídas[[#This Row],[Data do Caixa Previsto]], 0 ) ) -> 0
B11: 45547 | C11: 45536 | D11: 45537 | E11: Compra de mercadorias | F11: Vestuário | G11: NF7526 | H11: 2505 | I11: =IF(TbRegistroSaídas[[#This Row],[Data do Caixa Realizado]]="",0,MONTH(TbRegistroSaídas[[#This Row],[Data do Caixa Realizado]])) -> 9 | J11: =IF(TbRegistroSaídas[[#This Row],[Data do Caixa Realizado]]="",0,YEAR(TbRegistroSaídas[[#This Row],[Data do Caixa Realizado]])) -> 2024 | K11: =IF(TbRegistroSaídas[[#This Row],[Data da Competência]]="",0,MONTH(TbRegistroSaídas[[#This Row],[Data da Competência]])) -> 9 | L11: =IF(TbRegistroSaídas[[#This Row],[Data da Competência]]="",0,YEAR(TbRegistroSaídas[[#This Row],[Data da Competência]])) -> 2024 | M11: =IF(TbRegistroSaídas[[#This Row],[Data do Caixa Previsto]]="",0,MONTH(TbRegistroSaídas[[#This Row],[Data do Caixa Previsto]])) -> 9 | N11: =IF(TbRegistroSaídas[[#This Row],[Data do Caixa Previsto]]="",0,YEAR(TbRegistroSaídas[[#This Row],[Data do Caixa Previsto]])) -> 2024 | O11: =IF(TbRegistroSaídas[[#This Row],[Data do Caixa Realizado]]<>"", IF(TbRegistroSaídas[[#This Row],[Data do Caixa Realizado]]>TbRegistroSaídas[[#This Row],[Data do Caixa Previsto]], TbRegistroSaídas[[#This Row],[Data do Caixa Realizado]]-TbRegistroSaídas[[#This Row],[Data do Caixa Previsto]], 0 ), IF(TODAY()>TbRegistroSaídas[[#This Row],[Data do Caixa Previsto]], TODAY()-TbRegistroSaídas[[#This Row],[Data do Caixa Previsto]], 0 ) ) -> 10
B12: 45544 | C12: 45539 | D12: 45544 | E12: Compra de mercadorias | F12: Som e imagem | G12: NF7559 | H12: 817 | I12: =IF(TbRegistroSaídas[[#This Row],[Data do Caixa Realizado]]="",0,MONTH(TbRegistroSaídas[[#This Row],[Data do Caixa Realizado]])) -> 9 | J12: =IF(TbRegistroSaídas[[#This Row],[Data do Caixa Realizado]]="",0,YEAR(TbRegistroSaídas[[#This Row],[Data do Caixa Realizado]])) -> 2024 | K12: =IF(TbRegistroSaídas[[#This Row],[Data da Competência]]="",0,MONTH(TbRegistroSaídas[[#This Row],[Data da Competência]])) -> 9 | L12: =IF(TbRegistroSaídas[[#This Row],[Data da Competência]]="",0,YEAR(TbRegistroSaídas[[#This Row],[Data da Competência]])) -> 2024 | M12: =IF(TbRegistroSaídas[[#This Row],[Data do Caixa Previsto]]="",0,MONTH(TbRegistroSaídas[[#This Row],[Data do Caixa Previsto]])) -> 9 | N12: =IF(TbRegistroSaídas[[#This Row],[Data do Caixa Previsto]]="",0,YEAR(TbRegistroSaídas[[#This Row],[Data do Caixa Previsto]])) -> 2024 | O12: =IF(TbRegistroSaídas[[#This Row],[Data do Caixa Realizado]]<>"", IF(TbRegistroSaídas[[#This Row],[Data do Caixa Realizado]]>TbRegistroSaídas[[#This Row],[Data do Caixa Previsto]], TbRegistroSaídas[[#This Row],[Data do Caixa Realizado]]-TbRegistroSaídas[[#This Row],[Data do Caixa Previsto]], 0 ), IF(TODAY()>TbRegistroSaídas[[#This Row],[Data do Caixa Previsto]], TODAY()-TbRegistroSaídas[[#This Row],[Data do Caixa Previsto]], 0 ) ) -> 0
C13: 45541 | D13: 45541 | E13: Compra de mercadorias | F13: Informática | G13: NF9357 | H13: 1565 | I13: =IF(TbRegistroSaídas[[#This Row],[Data do Caixa Realizado]]="",0,MONTH(TbRegistroSaídas[[#This Row],[Data do Caixa Realizado]])) -> 0 | J13: =IF(TbRegistroSaídas[[#This Row],[Data do Caixa Realizado]]="",0,YEAR(TbRegistroSaídas[[#This Row],[Data do Caixa Realizado]])) -> 0 | K13: =IF(TbRegistroSaídas[[#This Row],[Data da Competência]]="",0,MONTH(TbRegistroSaídas[[#This Row],[Data da Competência]])) -> 9 | L13: =IF(TbRegistroSaídas[[#This Row],[Data da Competência]]="",0,YEAR(TbRegistroSaídas[[#This Row],[Data da Competência]])) -> 2024 | M13: =IF(TbRegistroSaídas[[#This Row],[Data do Caixa Previsto]]="",0,MONTH(TbRegistroSaídas[[#This Row],[Data do Caixa Previsto]])) -> 9 | N13: =IF(TbRegistroSaídas[[#This Row],[Data do Caixa Previsto]]="",0,YEAR(TbRegistroSaídas[[#This Row],[Data do Caixa Previsto]])) -> 2024 | O13: =IF(TbRegistroSaídas[[#This Row],[Data do Caixa Realizado]]<>"", IF(TbRegistroSaídas[[#This Row],[Data do Caixa Realizado]]>TbRegistroSaídas[[#This Row],[Data do Caixa Previsto]], TbRegistroSaídas[[#This Row],[Data do Caixa Realizado]]-TbRegistroSaídas[[#This Row],[Data do Caixa Previsto]], 0 ), IF(TODAY()>TbRegistroSaídas[[#This Row],[Data do Caixa Previsto]], TODAY()-TbRegistroSaídas[[#This Row],[Data do Caixa Previsto]], 0 ) ) -> 668
C14: 45547 | D14: 45577 | E14: Compra de mercadorias | F14: Livros | G14: NF3898 | H14: 1357 | I14: =IF(TbRegistroSaídas[[#This Row],[Data do Caixa Realizado]]="",0,MONTH(TbRegistroSaídas[[#This Row],[Data do Caixa Realizado]])) -> 0 | J14: =IF(TbRegistroSaídas[[#This Row],[Data do Caixa Realizado]]="",0,YEAR(TbRegistroSaídas[[#This Row],[Data do Caixa Realizado]])) -> 0 | K14: =IF(TbRegistroSaídas[[#This Row],[Data da Competência]]="",0,MONTH(TbRegistroSaídas[[#This Row],[Data da Competência]])) -> 9 | L14: =IF(TbRegistroSaídas[[#This Row],[Data da Competência]]="",0,YEAR(TbRegistroSaídas[[#This Row],[Data da Competência]])) -> 2024 | M14: =IF(TbRegistroSaídas[[#This Row],[Data do Caixa Previsto]]="",0,MONTH(TbRegistroSaídas[[#This Row],[Data do Caixa Previsto]])) -> 10 | N14: =IF(TbRegistroSaídas[[#This Row],[Data do Caixa Previsto]]="",0,YEAR(TbRegistroSaídas[[#This Row],[Data do Caixa Previsto]])) -> 2024 | O14: =IF(TbRegistroSaídas[[#This Row],[Data do Caixa Realizado]]<>"", IF(TbRegistroSaídas[[#This Row],[Data do Caixa Realizado]]>TbRegistroSaídas[[#This Row],[Data do Caixa Previsto]], TbRegistroSaídas[[#This Row],[Data do Caixa Realizado]]-TbRegistroSaídas[[#This Row],[Data do Caixa Previsto]], 0 ), IF(TODAY()>TbRegistroSaídas[[#This Row],[Data do Caixa Previsto]], TODAY()-TbRegistroSaídas[[#This Row],[Data do Caixa Previsto]], 0 ) ) -> 632
B15: 45582 | C15: 45548 | D15: 45582 | E15: Compra de mercadorias | F15: Livros | G15: NF7275 | H15: 4739 | I15: =IF(TbRegistroSaídas[[#This Row],[Data do Caixa Realizado]]="",0,MONTH(TbRegistroSaídas[[#This Row],[Data do Caixa Realizado]])) -> 10 | J15: =IF(TbRegistroSaídas[[#This Row],[Data do Caixa Realizado]]="",0,YEAR(TbRegistroSaídas[[#This Row],[Data do Caixa Realizado]])) -> 2024 | K15: =IF(TbRegistroSaídas[[#This Row],[Data da Competência]]="",0,MONTH(TbRegistroSaídas[[#This Row],[Data da Competência]])) -> 9 | L15: =IF(TbRegistroSaídas[[#This Row],[Data da Competência]]="",0,YEAR(TbRegistroSaídas[[#This Row],[Data da Competência]])) -> 2024 | M15: =IF(TbRegistroSaídas[[#This Row],[Data do Caixa Previsto]]="",0,MONTH(TbRegistroSaídas[[#This Row],[Data do Caixa Previsto]])) -> 10 | N15: =IF(TbRegistroSaídas[[#This Row],[Data do Caixa Previsto]]="",0,YEAR(TbRegistroSaídas[[#This Row],[Data do Caixa Previsto]])) -> 2024 | O15: =IF(TbRegistroSaídas[[#This Row],[Data do Caixa Realizado]]<>"", IF(TbRegistroSaídas[[#This Row],[Data do Caixa Realizado]]>TbRegistroSaídas[[#This Row],[Data do Caixa Previsto]], TbRegistroSaídas[[#This Row],[Data do Caixa Realizado]]-TbRegistroSaídas[[#This Row],[Data do Caixa Previsto]], 0 ), IF(TODAY()>TbRegistroSaídas[[#This Row],[Data do Caixa Previsto]], TODAY()-TbRegistroSaídas[[#This Row],[Data do Caixa Previsto]], 0 ) ) -> 0
B16: 45565 | C16: 45549 | D16: 45565 | E16: Compra de mercadorias | F16: Som e imagem | G16: NF9591 | H16: 4675 | I16: =IF(TbRegistroSaídas[[#This Row],[Data do Caixa Realizado]]="",0,MONTH(TbRegistroSaídas[[#This Row],[Data do Caixa Realizado]])) -> 9 | J16: =IF(TbRegistroSaídas[[#This Row],[Data do Caixa Realizado]]="",0,YEAR(TbRegistroSaídas[[#This Row],[Data do Caixa Realizado]])) -> 2024 | K16: =IF(TbRegistroSaídas[[#This Row],[Data da Competência]]="",0,MONTH(TbRegistroSaídas[[#This Row],[Data da Competência]])) -> 9 | L16: =IF(TbRegistroSaídas[[#This Row],[Data da Competência]]="",0,YEAR(TbRegistroSaídas[[#This Row],[Data da Competência]])) -> 2024 | M16: =IF(TbRegistroSaídas[[#This Row],[Data do Caixa Previsto]]="",0,MONTH(TbRegistroSaídas[[#This Row],[Data do Caixa Previsto]])) -> 9 | N16: =IF(TbRegistroSaídas[[#This Row],[Data do Caixa Previsto]]="",0,YEAR(TbRegistroSaídas[[#This Row],[Data do Caixa Previsto]])) -> 2024 | O16: =IF(TbRegistroSaídas[[#This Row],[Data do Caixa Realizado]]<>"", IF(TbRegistroSaídas[[#This Row],[Data do Caixa Realizado]]>TbRegistroSaídas[[#This Row],[Data do Caixa Previsto]], TbRegistroSaídas[[#This Row],[Data do Caixa Realizado]]-TbRegistroSaídas[[#This Row],[Data do Caixa Previsto]], 0 ), IF(TODAY()>TbRegistroSaídas[[#This Row],[Data do Caixa Previsto]], TODAY()-TbRegistroSaídas[[#This Row],[Data do Caixa Previsto]], 0 ) ) -> 0
B17: 45561 | C17: 45554 | D17: 45561 | E17: Compra de mercadorias | F17: Vestuário | G17: NF3104 | H17: 1797 | I17: =IF(TbRegistroSaídas[[#This Row],[Data do Caixa Realizado]]="",0,MONTH(TbRegistroSaídas[[#This Row],[Data do Caixa Realizado]])) -> 9 | J17: =IF(TbRegistroSaídas[[#This Row],[Data do Caixa Realizado]]="",0,YEAR(TbRegistroSaídas[[#This Row],[Data do Caixa Realizado]])) -> 2024 | K17: =IF(TbRegistroSaídas[[#This Row],[Data da Competência]]="",0,MONTH(TbRegistroSaídas[[#This Row],[Data da Competência]])) -> 9 | L17: =IF(TbRegistroSaídas[[#This Row],[Data da Competência]]="",0,YEAR(TbRegistroSaídas[[#This Row],[Data da Competência]])) -> 2024 | M17: =IF(TbRegistroSaídas[[#This Row],[Data do Caixa Previsto]]="",0,MONTH(TbRegistroSaídas[[#This Row],[Data do Caixa Previsto]])) -> 9 | N17: =IF(TbRegistroSaídas[[#This Row],[Data do Caixa Previsto]]="",0,YEAR(TbRegistroSaídas[[#This Row],[Data do Caixa Previsto]])) -> 2024 | O17: =IF(TbRegistroSaídas[[#This Row],[Data do Caixa Realizado]]<>"", IF(TbRegistroSaídas[[#This Row],[Data do Caixa Realizado]]>TbRegistroSaídas[[#This Row],[Data do Caixa Previsto]], TbRegistroSaídas[[#This Row],[Data do Caixa Realizado]]-TbRegistroSaídas[[#This Row],[Data do Caixa Previsto]], 0 ), IF(TODAY()>TbRegistroSaídas[[#This Row],[Data do Caixa Previsto]], TODAY()-TbRegistroSaídas[[#This Row],[Data do Caixa Previsto]], 0 ) ) -> 0
B18: 45600 | C18: 45559 | D18: 45600 | E18: Compra de mercadorias | F18: Livros | G18: NF3440 | H18: 888 | I18: =IF(TbRegistroSaídas[[#This Row],[Data do Caixa Realizado]]="",0,MONTH(TbRegistroSaídas[[#This Row],[Data do Caixa Realizado]])) -> 11 | J18: =IF(TbRegistroSaídas[[#This Row],[Data do Caixa Realizado]]="",0,YEAR(TbRegistroSaídas[[#This Row],[Data do Caixa Realizado]])) -> 2024 | K18: =IF(TbRegistroSaídas[[#This Row],[Data da Competência]]="",0,MONTH(TbRegistroSaídas[[#This Row],[Data da Competência]])) -> 9 | L18: =IF(TbRegistroSaídas[[#This Row],[Data da Competência]]="",0,YEAR(TbRegistroSaídas[[#This Row],[Data da Competência]])) -> 2024 | M18: =IF(TbRegistroSaídas[[#This Row],[Data do Caixa Previsto]]="",0,MONTH(TbRegistroSaídas[[#This Row],[Data do Caixa Previsto]])) -> 11 | N18: =IF(TbRegistroSaídas[[#This Row],[Data do Caixa Previsto]]="",0,YEAR(TbRegistroSaídas[[#This Row],[Data do Caixa Previsto]])) -> 2024 | O18: =IF(TbRegistroSaídas[[#This Row],[Data do Caixa Realizado]]<>"", IF(TbRegistroSaídas[[#This Row],[Data do Caixa Realizado]]>TbRegistroSaídas[[#This Row],[Data do Caixa Previsto]], TbRegistroSaídas[[#This Row],[Data do Caixa Realizado]]-TbRegistroSaídas[[#This Row],[Data do Caixa Previsto]], 0 ), IF(TODAY()>TbRegistroSaídas[[#This Row],[Data do Caixa Previsto]], TODAY()-TbRegistroSaídas[[#This Row],[Data do Caixa Previsto]], 0 ) ) -> 0
B19: 45572 | C19: 45560 | D19: 45572 | E19: Compra de mercadorias | F19: Vestuário | G19: NF9195 | H19: 2784 | I19: =IF(TbRegistroSaídas[[#This Row],[Data do Caixa Realizado]]="",0,MONTH(TbRegistroSaídas[[#This Row],[Data do Caixa Realizado]])) -> 10 | J19: =IF(TbRegistroSaídas[[#This Row],[Data do Caixa Realizado]]="",0,YEAR(TbRegistroSaídas[[#This Row],[Data do Caixa Realizado]])) -> 2024 | K19: =IF(TbRegistroSaídas[[#This Row],[Data da Competência]]="",0,MONTH(TbRegistroSaídas[[#This Row],[Data da Competência]])) -> 9 | L19: =IF(TbRegistroSaídas[[#This Row],[Data da Competência]]="",0,YEAR(TbRegistroSaídas[[#This Row],[Data da Competência]])) -> 2024 | M19: =IF(TbRegistroSaídas[[#This Row],[Data do Caixa Previsto]]="",0,MONTH(TbRegistroSaídas[[#This Row],[Data do Caixa Previsto]])) -> 10 | N19: =IF(TbRegistroSaídas[[#This Row],[Data do Caixa Previsto]]="",0,YEAR(TbRegistroSaídas[[#This Row],[Data do Caixa Previsto]])) -> 2024 | O19: =IF(TbRegistroSaídas[[#This Row],[Data do Caixa Realizado]]<>"", IF(TbRegistroSaídas[[#This Row],[Data do Caixa Realizado]]>TbRegistroSaídas[[#This Row],[Data do Caixa Previsto]], TbRegistroSaídas[[#This Row],[Data do Caixa Realizado]]-TbRegistroSaídas[[#This Row],[Data do Caixa Previsto]], 0 ), IF(TODAY()>TbRegistroSaídas[[#This Row],[Data do Caixa Previsto]], TODAY()-TbRegistroSaídas[[#This Row],[Data do Caixa Previsto]], 0 ) ) -> 0
B20: 45567 | C20: 45560 | D20: 45567 | E20: Compra de mercadorias | F20: Informática | G20: NF1821 | H20: 707 | I20: =IF(TbRegistroSaídas[[#This Row],[Data do Caixa Realizado]]="",0,MONTH(TbRegistroSaídas[[#This Row],[Data do Caixa Realizado]])) -> 10 | J20: =IF(TbRegistroSaídas[[#This Row],[Data do Caixa Realizado]]="",0,YEAR(TbRegistroSaídas[[#This Row],[Data do Caixa Realizado]])) -> 2024 | K20: =IF(TbRegistroSaídas[[#This Row],[Data da Competência]]="",0,MONTH(TbRegistroSaídas[[#This Row],[Data da Competência]])) -> 9 | L20: =IF(TbRegistroSaídas[[#This Row],[Data da Competência]]="",0,YEAR(TbRegistroSaídas[[#This Row],[Data da Competência]])) -> 2024 | M20: =IF(TbRegistroSaídas[[#This Row],[Data do Caixa Previsto]]="",0,MONTH(TbRegistroSaídas[[#This Row],[Data do Caixa Previsto]])) -> 10 | N20: =IF(TbRegistroSaídas[[#This Row],[Data do Caixa Previsto]]="",0,YEAR(TbRegistroSaídas[[#This Row],[Data do Caixa Previsto]])) -> 2024 | O20: =IF(TbRegistroSaídas[[#This Row],[Data do Caixa Realizado]]<>"", IF(TbRegistroSaídas[[#This Row],[Data do Caixa Realizado]]>TbRegistroSaídas[[#This Row],[Data do Caixa Previsto]], TbRegistroSaídas[[#This Row],[Data do Caixa Realizado]]-TbRegistroSaídas[[#This Row],[Data do Caixa Previsto]], 0 ), IF(TODAY()>TbRegistroSaídas[[#This Row],[Data do Caixa Previsto]], TODAY()-TbRegistroSaídas[[#This Row],[Data do Caixa Previsto]], 0 ) ) -> 0
